Workbook

Sheet PUBG
B1: Sniper Rifle damage stats:
B3: Weapon | C3: Base Damage | D3: Fire Rate | E3: DPS | F3: Time to Kill | G3: Shots to Kill (Chest) | H3: Shots to Kill (Head) | I3: Availability
B4: S686 | C4: 216 | D4: 0.2 | E4: 1080 | F4: 0 | G4: 1 | H4: 1 | I4: All
B5: S1897 | C5: 216 | D5: 0.75 | E5: 288 | F5: 0 | G5: 1 | H5: 1 | I5: All
B6: S12k | C6: 198 | D6: 0.25 | E6: 792 | F6: 0 | G6: 1 | H6: 1 | I6: All
B7: AWM | C7: 120 | D7: 1.85 | E7: 65 | F7: 1.85 | G7: 2 | H7: 1 | I7: Crate Only | J7: The new Beryl M762, now available on all maps, brings a much-needed second option for 7.62 Assault Rifles.
B8: M24 | C8: 88 | D8: 1.8 | E8: 49 | F8: 1.8 | G8: 2 | H8: 1 | I8: Crate Only (Non-Crate on Sanhok)
B9: Kar98k | C9: 75 | D9: 1.9 | E9: 39 | F9: 3.8 | G9: 3 | H9: 1 | I9: All
B10: Win94 | C10: 66 | D10: 0.6 | E10: 110 | F10: 1.2 | G10: 3 | H10: 2 | I10: Miramar Only
B11: MK14* | C11: 61 | D11: 0.09 | E11: 678 | F11: 0.18 | G11: 3 | H11: 2 | I11: Crate Only
B12: SLR | C12: 58 | D12: 0.1 | E12: 580 | F12: 0.2 | G12: 3 | H12: 2 | I12: All
B13: SKS | C13: 53 | D13: 0.1 | E13: 530 | F13: 0.2 | G13: 3 | H13: 2 | I13: All
B14: DP-28 | C14: 51 | D14: 0.109 | E14: 468 | F14: 0.33 | G14: 4 | H14: 2 | I14: All
B15: Groza | C15: 49 | D15: 0.08 | E15: 613 | F15: 0.24 | G15: 4 | H15: 2 | I15: Crate Only
B16: Mk47 Mutant | C16: 49 | D16: 0.1 | E16: 490 | F16: 0.3 | G16: 4 | H16: 2 | I16: All
B17: AKM | C17: 49 | D17: 0.1 | E17: 490 | F17: 0.3 | G17: 4 | H17: 2 | I17: All
B18: QBU88 | C18: 48 | D18: 0.1 | E18: 480 | F18: 0.3 | G18: 4 | H18: 2 | I18: Sanhok Only
B19: Beryl M762 | C19: 47 | D19: 0.086 | E19: 547 | F19: 0.26 | G19: 4 | H19: 2 | I19: All
... B21: M249 | C21: 45 | D21: 0.075 | E21: 600 | F21: 0.23 | G21: 4 | H21: 3 | I21: Crate Only
B22: M16A4 | C22: 43 | D22: 0.075 | E22: 573 | F22: 0.22 / 0.26 | G22: 4 | H22: 2 | I22: All
B23: AUG A3 | C23: 43 | D23: 0.086 | E23: 502 | F23: 0.26 | G23: 4 | H23: 2 | I23: Crate Only
B24: M416 | C24: 43 | D24: 0.086 | E24: 502 | F24: 0.26 | G24: 4 | H24: 2 | I24: All
B25: G36C | C25: 43 | D25: 0.086 | E25: 502 | F25: 0.26 | G25: 4 | H25: 2 | I25: Vikendi Only
B26: QBZ 95 | C26: 43 | D26: 0.092 | E26: 466 | F26: 0.28 | G26: 4 | H26: 2 | I26: Sanhok Only
B27: Scar-L | C27: 43 | D27: 0.096 | E27: 448 | F27: 0.29 | G27: 4 | H27: 2 | I27: Erangel / Miramar
B28: VSS | C28: 41 | D28: 0.086 | E28: 479 | F28: 0.26 | G28: 4 | H28: 2 | I28: All
B29: Tommy Gun | C29: 40 | D29: 0.086 | E29: 467 | F29: 0.34 | G29: 4 | H29: 3 | I29: All
B30: UMP9 | C30: 39 | D30: 0.092 | E30: 423 | F30: 0.37 | G30: 4 | H30: 3 | I30: All
B31: Vector | C31: 34 | D31: 0.055 | E31: 624 | F31: 0.22 | G31: 5 | H31: 3 | I31: All
B32: UZI | C32: 26 | D32: 0.048 | E32: 542 | F32: 0.29 | G32: 7 | H32: 4 | I32: All

Sheet dirlist
B1: chlamydia gonorrhea test | C1: =PROPER(B1) -> Chlamydia Gonorrhea Test
B2: chlamydia risks complications | C2: =PROPER(B2) -> Chlamydia Risks Complications
B3: chlamydia symptoms | C3: =PROPER(B3) -> Chlamydia Symptoms
B4: chlamydia test | C4: =PROPER(B4) -> Chlamydia Test
B5: chlamydia testing | C5: =PROPER(B5) -> Chlamydia Testing
B6: chlamydia treatment | C6: =PROPER(B6) -> Chlamydia Treatment
B7: confidential std testing | C7: =PROPER(B7) -> Confidential Std Testing
B8: connecticut std testing | C8: =PROPER(B8) -> Connecticut Std Testing
B9: delaware std testing | C9: =PROPER(B9) -> Delaware Std Testing
B10: gonorrhea risks complications | C10: =PROPER(B10) -> Gonorrhea Risks Complications
B11: gonorrhea symptoms | C11: =PROPER(B11) -> Gonorrhea Symptoms
B12: gonorrhea test | C12: =PROPER(B12) -> Gonorrhea Test
... B79: syphilis | C79: =PROPER(B79) -> Syphilis

Sheet Sheet1
A1: Big Sister 1/ Email Address | B1: PassWord | C1: Computer Name | D1: Info:
A3: deadman315@hotmail.com | B3: robvandam315 | C3: Stix
A5: alec_vasileiadis@hotmail.com | B5: greece
A7: tammydah@hotmail.com | B7: wilsonton | C7: dahler
A9: wrx_000@hotmail.com | B9: toowoomba | C9: dahler
A11: pingustix@hotmail.com | B11: fastplant | C11: Stix
A13: psycoclown201@hotmail.com | B13: fastplant | C13: Stix
A15: adrielchen0509@yahoo.com | B15: godisking | C15: Schaefen
E16: PROJECT MADE BY SPYBOY ALL WAS DONE BY MYSELF
A17: dextdog@hotmail.com | B17: dexter | C17: harmerant
A19: nickchan91@hotmail.com | B19: isiah34
A20: kiwirulz_7811@hotmail.com | B20: fucklife | C20: nicola
A21: shahidkhan570@hotmail.com | B21: pioneer | C21: PC1
A23: h_v_mittal@hotmail.com | B23: instrument | C23: Adminstrator
A25: dubbls@hotmail.com | B25: linronda/kingston | C25: Dubbls | E25: Taken Over
A27: priya4uin@hotmail.com | B27: iloveu | C27: Mach-1
A29: primrose_lust@hotmail.com | B29: jennarayjohnston | C29: owner
A31: danny_wedge@hotmail.com | B31: THEREDS | C31: MarkWhale
A33: htegg1@hotmail.com | B33: katiedog | C33: Ian Tegg
A35: Yahoo! Games | B35: g2lgratton[TAB]825564 | C35: Laura
B37: jonothan | C37: jacqueline McAulay
A39: abed_200@hotmail.com | B39: 3l1t34b3d@hell | C39: NoName
A41: gv_of_e@hotmail.com | B41: blackadder | C41: julia vince
A43: vinnie461@hotmail.com | B43: 461739 | C43: julia vince
A45: police_17@hotmail.com | B45: choclate | C45: pc1
A47: ady@hehe.com | B47: choclate | C47: pc1
A49: waqas_ahmed16@hotmail.com | B49: wicky111 | C49: pc1
A51: yasirbutt786@hotmail.com | B51: 2575036 | C51: pc1
A53: ali_akber_jamali@hotmail.com | B53: sakina | C53: pc1
A55: aliabbaz690@hotmail.com | B55: 6624109 | C55: pc1
A57: admirable_gal@hotmail.com | B57: sillyfiz | C57: pc1
A59: ando20000@hotmail.com | B59: 124643246
A61: sexy_lil_thingy_@hotmail.com | B61: whatupthefuckers
A63: mariokart_2002@hotmail.com | B63: 1471236 | C63: Neil
A65: backermalaker@hotmail.com | B65: arsepower | C65: Ian Baker
A67: murtaza_batman@hotmail.com | B67: tummytruck309 | C67: Murtaza Yousuf Ali
A69: rashida1985@hotmail.com | B69: batool_mufi | C69: Murtaza Yousuf Ali
A71: vinnie461@hotmail.com | B71: 461739 | C71: julia vince
A73: sexy_lil_thingy_@hotmail.com | B73: whatupthefuckers | C73: default
A75: alienization@hotmail.com | B75: motherfucker17 | C75: NoName
A77: darklander@thishell.com | B77: 9617734106 | C77: NoName
A79: chillin_and_killin@hotmail.com | B79: hotdogs | C79: sam whittaker
A81: wee_paula_akashorty@hotmail.com | B81: panasonic | C81: McKinney
A83: twisted_goon@hotmail.com | B83: fuckyu | C83: default
A85: big_bow_tie@hotmail.com | B85: katiedog | C85: Ian Tegg
A87: samy2w@aol.com | B87: gorillaz | C87: sam whittaker
A89: supercooldays@hotmail.com | B89: victoria | C89: Isnin
A91: lathkhore@hotmail.com | B91: 2811972 | C91: Mach-1
A93: superdidz210 | B93: carlamama | C93: kenneth (Yahoo Games)
A95: burhan687 | B95: 3723498 | C95: Administrator(Yahoo Games)
A97: bambi3 | B97: nickeltruck | C97: Administrator(Yahoo Games)
A99: ms_naz@hotmail.com | B99: nitedel | C99: Yasir Saeed
A101: rock_007585 | B101: qazwsx | C101: PC1
A103: thalia_charles@hotmail.com | B103: acidburnb | C103: G Charles
A105: codeman_65@hotmail.com | B105: humanenviroment7 | C105: HP Authorized Customer
A107: megamanguy_20033 | B107: stingis1 | C107: Neil(Yahoo Games)
A109: jay_be90@hotmail.com | B109: stingis11 | C109: Neil
A111: sarah_in_dats_house@hotmail.com | B111: whatupniggafuckers | C111: Neil
A113: altaf_waqas@hotmail.com | B113: safwangandoo | C113: waqas altaf | D113: Comcast website???
A115: greatarbab@hotmail.com | B115: onlymeu2 | C115: Arbab Latif
A117: shazadi_gul@hotmail.com | B117: 171717 | C117: Arbab Latif
A119: ketchup0000001@hotmail.com | B119: abuabid1 | C119: u18
A121: coolmoll@hotmail.com | B121: divastars | C121: Molly Whittaker
A123: ikon_graphics@hotmail.com | B123: linuxone | C123: test
A125: laminlove@hotmail.com | B125: linuxone | C125: test
A127: desperad2000@hotmail.com | B127: vodafone | C127: pete2 | D127: sms login
A129: tesha_park@hotmail.com | B129: vodafone | C129: pete2
A131: mostafazezo313@hotmail.com | B131: 6872174 | C131: pete2
A133: mostafa_103@hotmail.com | B133: 6872174 | C133: pete2 | D133: Yahoo =
A135: gem21122000@yahoo.com | B135: matrix | C135: f16
A137: wfpk_2@yahoo.com | B137: ACESHIGH | C137: jboudreau
A139: mostafa_103@hotmail.com | B139: 6872174 | C139: petanet
A141: prince4ever7@hotmail.com | B141: 446529100 | C141: petanet | D141: Yahoo =
A143: adel_sayed_18@hotmail.com | B143: 446529100 | C143: petanet
A145: khaled_eldabaa@hotmail.com | B145: kosomak | C145: petanet
A147: belahedod@hotmail.com | B147: omak7elwa | C147: petanet
A149: coolghazni@hotmail.com | B149: mohabat | C149: shahzad
A151: matt_20062001 | B151: password | C151: lab115 | D151: Yahoo Games
A153: gsmeplayer@hotmail.com | B153: xpasswordx | C153: lab115 | D153: Forums =
A155: llvllister_llvll | B155: buceta or 011187 | C155: TALLYS SABINO | D155: Yahoo
A157: allanstevason@hotmail.com | B157: underwaterweapon | C157: Max | D157: Yahoo =
A159: alisha_virgo@hotmail.com | B159: ALLAHTALA | C159: RAHEEL
A161: tehseensagarpk@hotmail.com | B161: j20bch6266664817 | C161: NETSPY | D161: Logins =
A163: pythenbite@hotmail.com | B163: hopeless | C163: J@n@n M@g$!.
A165: ahsan_magsi@hotmail.com | B165: KARACHI | C165: J@n@n M@g$!.
A167: jmagsi@hotmail.com | B167: helpful | C167: J@n@n M@g$!.
A169: viper_bite4u@hotmail.com | B169: bestfriends | C169: J@n@n M@g$!.
A171: pythenbite@hotmail.com | B171: hopeless | C171: J@n@n M@g$!.
A173: ardalan1984@msn.com | B173: ard1984alan | C173: immortal
A175: p_p911@hotmail.com | B175: iloveyou | C175: uninet6
A177: mohamedomer112 | B177: neryyy | C177: uninet6
A179: MOHAMEDRAGAB502@hotmail.com | B179: 101484619 | C179: uninet6
A181: doctor_saleh77@hotmail.com | B181: dahabdahab | C181: uninet6
A183: megadeth009@hotmail.com | B183: hotmail | C183: uninet6
A185: shifo1985@hotmail.com | B185: ilovedina | C185: uninet6 | D185: Yahoo Groups
A187: nasirmunir71@hotmail.com | B187: khotta | C187: Nasir Munir
A189: beachshyam@hotmail.com | B189: geta77 | C189: Kanti
A191: water_boy7@msn.com | B191: geta77 | C191: Kanti
A193: vampire_mobius@hotmail.com | B193: vampire | C193: Matthew | D193: Mechg
A195: loby282003 | B195: potassium | C195: Irvine | D195: Yahoo Chat
...

Sheet Sheet4
G5: SÍFILIS | I5: =PROPER(G5) -> Sífilis
I6: =PROPER(G6)
G7: VIRUS HEPATÍTIS B | I7: =PROPER(G7) -> Virus Hepatítis B
I8: =PROPER(G8)
G9: HERPES | I9: =PROPER(G9) -> Herpes
I10: =PROPER(G10)
G11: GONORREA | I11: =PROPER(G11) -> Gonorrea
I12: =PROPER(G12)
G13: CLAMIDIA | I13: =PROPER(G13) -> Clamidia
G14: MYCOPLASMA / UREAPLASMA | I14: =PROPER(G14) -> Mycoplasma / Ureaplasma
I15: =PROPER(G15)
G16: PAPILOMA HUMANO | I16: =PROPER(G16) -> Papiloma Humano
I17: =PROPER(G17)
G18: GONORREA | I18: =PROPER(G18) -> Gonorrea
I19: =PROPER(G19)
G20: VIH (VIRUS DE INMUNODEFICIENCA HUMANA) | I20: =PROPER(G20) -> Vih (Virus De Inmunodeficienca Humana)

Sheet Body Parts
K1: blank
A2: XML Meta Tags | K2: - | L2: =LEN(K2) -> 1
C3: Body Parts | D3: Wars Removal
C4: Cheek | D4: face | E4: warts | F4: removal | G4: .html | H4: <a href=" | I4: =CONCATENATE(D4,$K$2,E4,$K$2,F4,G4) -> face-warts-removal.html | J4: "> | K4: =PROPER(CONCATENATE(D4," ",E4," ",F4)) -> Face Warts Removal | L4: </a> | M4: =CONCATENATE(H4,I4,J4,K4,L4) -> <a href="face-warts-removal.html">Face Warts Removal</a>
C5: Chin | D5: neck | E5: warts | F5: removal | G5: .html | H5: <a href=" | I5: =CONCATENATE(D5,$K$2,E5,$K$2,F5,G5) -> neck-warts-removal.html | J5: "> | K5: =PROPER(CONCATENATE(D5," ",E5," ",F5)) -> Neck Warts Removal | L5: </a> | M5: =CONCATENATE(H5,I5,J5,K5,L5) -> <a href="neck-warts-removal.html">Neck Warts Removal</a>
C6: Neck | D6: shoulder | E6: warts | F6: removal | G6: .html | H6: <a href=" | I6: =CONCATENATE(D6,$K$2,E6,$K$2,F6,G6) -> shoulder-warts-removal.html | J6: "> | K6: =PROPER(CONCATENATE(D6," ",E6," ",F6)) -> Shoulder Warts Removal | L6: </a> | M6: =CONCATENATE(H6,I6,J6,K6,L6) -> <a href="shoulder-warts-removal.html">Shoulder Warts Removal</a>
A7: <head>mole removal</head> | C7: Shoulder | D7: breast | E7: warts | F7: removal | G7: .html | H7: <a href=" | I7: =CONCATENATE(D7,$K$2,E7,$K$2,F7,G7) -> breast-warts-removal.html | J7: "> | K7: =PROPER(CONCATENATE(D7," ",E7," ",F7)) -> Breast Warts Removal | L7: </a> | M7: =CONCATENATE(H7,I7,J7,K7,L7) -> <a href="breast-warts-removal.html">Breast Warts Removal</a>
A8: <company>Cosmocare Medical Center</company> | C8: Breast | D8: back | E8: warts | F8: removal | G8: .html | H8: <a href=" | I8: =CONCATENATE(D8,$K$2,E8,$K$2,F8,G8) -> back-warts-removal.html | J8: "> | K8: =PROPER(CONCATENATE(D8," ",E8," ",F8)) -> Back Warts Removal | L8: </a> | M8: =CONCATENATE(H8,I8,J8,K8,L8) -> <a href="back-warts-removal.html">Back Warts Removal</a>
A9: <phone>04 379 8747</phone> | C9: Navel | D9: hand | E9: warts | F9: removal | G9: .html | H9: <a href=" | I9: =CONCATENATE(D9,$K$2,E9,$K$2,F9,G9) -> hand-warts-removal.html | J9: "> | K9: =PROPER(CONCATENATE(D9," ",E9," ",F9)) -> Hand Warts Removal | L9: </a> | M9: =CONCATENATE(H9,I9,J9,K9,L9) -> <a href="hand-warts-removal.html">Hand Warts Removal</a>
A10: <region name="Asia"> | C10: Abdomen | D10: buttock | E10: warts | F10: removal | G10: .html | H10: <a href=" | I10: =CONCATENATE(D10,$K$2,E10,$K$2,F10,G10) -> buttock-warts-removal.html | J10: "> | K10: =PROPER(CONCATENATE(D10," ",E10," ",F10)) -> Buttock Warts Removal | L10: </a> | M10: =CONCATENATE(H10,I10,J10,K10,L10) -> <a href="buttock-warts-removal.html">Buttock Warts Removal</a>
A11: <country name="United Arab Emirates"> | C11: Neck | D11: thigh | E11: warts | F11: removal | G11: .html | H11: <a href=" | I11: =CONCATENATE(D11,$K$2,E11,$K$2,F11,G11) -> thigh-warts-removal.html | J11: "> | K11: =PROPER(CONCATENATE(D11," ",E11," ",F11)) -> Thigh Warts Removal | L11: </a> | M11: =CONCATENATE(H11,I11,J11,K11,L11) -> <a href="thigh-warts-removal.html">Thigh Warts Removal</a>
A12: <city>Dubai</city> | C12: Shoulder Blade
A13: </country> | C13: Arm
A14: </region> | C14: Elbow
C15: Back
C16: Hand
C17: Buttock
C18: Thigh
D23: =SUM(D24:D40) -> 45 | E23: =SUM(E24:E40) -> 54
D24: 1 | E24: 3
D25: 2 | E25: 3
D26: 3 | E26: 3
D27: 4 | E27: 6
D28: 5 | E28: 6
D29: 6 | E29: 6
D30: 7 | E30: 9
D31: 8 | E31: 9
D32: 9 | E32: 9

Sheet mughal steel works
K1: blank
A2: XML Meta Tags | K2: - | L2: =LEN(K2) -> 1
C3: Body Parts | D3: Iron Welding Works
C4: iron | D4: Iron | E4: Sliding | F4: Gate | H4: <a href="works.php?welding= | I4: =CONCATENATE(D4,$K$2,E4,$K$2,F4,G4) -> Iron-Sliding-Gate | J4: "> | K4: =PROPER(CONCATENATE(D4," ",E4," ",F4)) -> Iron Sliding Gate | L4: </a> <br /> | M4: =CONCATENATE(H4,I4,J4,K4,L4) -> <a href="works.php?welding=Iron-Sliding-Gate">Iron Sliding Gate</a> <br />
D5: Iron | E5: Sliding | F5: Windows | H5: <a href="works.php?welding= | I5: =CONCATENATE(D5,$K$2,E5,$K$2,F5,G5) -> Iron-Sliding-Windows | J5: "> | K5: =PROPER(CONCATENATE(D5," ",E5," ",F5)) -> Iron Sliding Windows | L5: </a> <br /> | M5: =CONCATENATE(H5,I5,J5,K5,L5) -> <a href="works.php?welding=Iron-Sliding-Windows">Iron Sliding Windows</a> <br />
D6: Iron | E6: Kids | F6: Slide | H6: <a href="works.php?welding= | I6: =CONCATENATE(D6,$K$2,E6,$K$2,F6,G6) -> Iron-Kids-Slide | J6: "> | K6: =PROPER(CONCATENATE(D6," ",E6," ",F6)) -> Iron Kids Slide | L6: </a> <br /> | M6: =CONCATENATE(H6,I6,J6,K6,L6) -> <a href="works.php?welding=Iron-Kids-Slide">Iron Kids Slide</a> <br />
A7: <head>mole removal</head> | D7: Iron | E7: Swing | F7: Cradle | H7: <a href="works.php?welding= | I7: =CONCATENATE(D7,$K$2,E7,$K$2,F7,G7) -> Iron-Swing-Cradle | J7: "> | K7: =PROPER(CONCATENATE(D7," ",E7," ",F7)) -> Iron Swing Cradle | L7: </a> <br /> | M7: =CONCATENATE(H7,I7,J7,K7,L7) -> <a href="works.php?welding=Iron-Swing-Cradle">Iron Swing Cradle</a> <br />
A8: <company>Cosmocare Medical Center</company> | D8: Iron | E8: Tables | F8: Welding | H8: <a href="works.php?welding= | I8: =CONCATENATE(D8,$K$2,E8,$K$2,F8,G8) -> Iron-Tables-Welding | J8: "> | K8: =PROPER(CONCATENATE(D8," ",E8," ",F8)) -> Iron Tables Welding | L8: </a> <br /> | M8: =CONCATENATE(H8,I8,J8,K8,L8) -> <a href="works.php?welding=Iron-Tables-Welding">Iron Tables Welding</a> <br />
A9: <phone>04 379 8747</phone> | D9: Iron | E9: Stool | F9: Welding | H9: <a href="works.php?welding= | I9: =CONCATENATE(D9,$K$2,E9,$K$2,F9,G9) -> Iron-Stool-Welding | J9: "> | K9: =PROPER(CONCATENATE(D9," ",E9," ",F9)) -> Iron Stool Welding | L9: </a> <br /> | M9: =CONCATENATE(H9,I9,J9,K9,L9) -> <a href="works.php?welding=Iron-Stool-Welding">Iron Stool Welding</a> <br />
A10: <region name="Asia"> | D10: Iron | E10: Chairs | F10: Welding | H10: <a href="works.php?welding= | I10: =CONCATENATE(D10,$K$2,E10,$K$2,F10,G10) -> Iron-Chairs-Welding | J10: "> | K10: =PROPER(CONCATENATE(D10," ",E10," ",F10)) -> Iron Chairs Welding | L10: </a> <br /> | M10: =CONCATENATE(H10,I10,J10,K10,L10) -> <a href="works.php?welding=Iron-Chairs-Welding">Iron Chairs Welding</a> <br />
A11: <country name="United Arab Emirates"> | D11: Iron | E11: Steps | F11: Welding | H11: <a href="works.php?welding= | I11: =CONCATENATE(D11,$K$2,E11,$K$2,F11,G11) -> Iron-Steps-Welding | J11: "> | K11: =PROPER(CONCATENATE(D11," ",E11," ",F11)) -> Iron Steps Welding | L11: </a> <br /> | M11: =CONCATENATE(H11,I11,J11,K11,L11) -> <a href="works.php?welding=Iron-Steps-Welding">Iron Steps Welding</a> <br />
A12: <city>Dubai</city> | D12: Iron | E12: Racks | F12: Welding | H12: <a href="works.php?welding= | I12: =CONCATENATE(D12,$K$2,E12,$K$2,F12,G12) -> Iron-Racks-Welding | J12: "> | K12: =PROPER(CONCATENATE(D12," ",E12," ",F12)) -> Iron Racks Welding | L12: </a> <br /> | M12: =CONCATENATE(H12,I12,J12,K12,L12) -> <a href="works.php?welding=Iron-Racks-Welding">Iron Racks Welding</a> <br />
A13: </country> | D13: Iron | E13: Gate | F13: Welding | H13: <a href="works.php?welding= | I13: =CONCATENATE(D13,$K$2,E13,$K$2,F13,G13) -> Iron-Gate-Welding | J13: "> | K13: =PROPER(CONCATENATE(D13," ",E13," ",F13)) -> Iron Gate Welding | L13: </a> <br /> | M13: =CONCATENATE(H13,I13,J13,K13,L13) -> <a href="works.php?welding=Iron-Gate-Welding">Iron Gate Welding</a> <br />
A14: </region> | D14: Iron | E14: Windows | F14: Welding | H14: <a href="works.php?welding= | I14: =CONCATENATE(D14,$K$2,E14,$K$2,F14,G14) -> Iron-Windows-Welding | J14: "> | K14: =PROPER(CONCATENATE(D14," ",E14," ",F14)) -> Iron Windows Welding | L14: </a> <br /> | M14: =CONCATENATE(H14,I14,J14,K14,L14) -> <a href="works.php?welding=Iron-Windows-Welding">Iron Windows Welding</a> <br />
D15: Iron | E15: Grills | F15: Welding | H15: <a href="works.php?welding= | I15: =CONCATENATE(D15,$K$2,E15,$K$2,F15,G15) -> Iron-Grills-Welding | J15: "> | K15: =PROPER(CONCATENATE(D15," ",E15," ",F15)) -> Iron Grills Welding | L15: </a> <br /> | M15: =CONCATENATE(H15,I15,J15,K15,L15) -> <a href="works.php?welding=Iron-Grills-Welding">Iron Grills Welding</a> <br />
D16: Iron | E16: Stairs | F16: Welding | H16: <a href="works.php?welding= | I16: =CONCATENATE(D16,$K$2,E16,$K$2,F16,G16) -> Iron-Stairs-Welding | J16: "> | K16: =PROPER(CONCATENATE(D16," ",E16," ",F16)) -> Iron Stairs Welding | L16: </a> <br /> | M16: =CONCATENATE(H16,I16,J16,K16,L16) -> <a href="works.php?welding=Iron-Stairs-Welding">Iron Stairs Welding</a> <br />
D17: Iron | E17: Door | F17: Welding | H17: <a href="works.php?welding= | I17: =CONCATENATE(D17,$K$2,E17,$K$2,F17,G17) -> Iron-Door-Welding | J17: "> | K17: =PROPER(CONCATENATE(D17," ",E17," ",F17)) -> Iron Door Welding | L17: </a> <br /> | M17: =CONCATENATE(H17,I17,J17,K17,L17) -> <a href="works.php?welding=Iron-Door-Welding">Iron Door Welding</a> <br />
D18: Iron | E18: Fences | F18: Welding | H18: <a href="works.php?welding= | I18: =CONCATENATE(D18,$K$2,E18,$K$2,F18,G18) -> Iron-Fences-Welding | J18: "> | K18: =PROPER(CONCATENATE(D18," ",E18," ",F18)) -> Iron Fences Welding | L18: </a> <br /> | M18: =CONCATENATE(H18,I18,J18,K18,L18) -> <a href="works.php?welding=Iron-Fences-Welding">Iron Fences Welding</a> <br />
D19: Iron | E19: Furniture | F19: Welding | H19: <a href="works.php?welding= | I19: =CONCATENATE(D19,$K$2,E19,$K$2,F19,G19) -> Iron-Furniture-Welding | J19: "> | K19: =PROPER(CONCATENATE(D19," ",E19," ",F19)) -> Iron Furniture Welding | L19: </a> <br /> | M19: =CONCATENATE(H19,I19,J19,K19,L19) -> <a href="works.php?welding=Iron-Furniture-Welding">Iron Furniture Welding</a> <br />
D20: Iron | E20: Railings | F20: Welding | H20: <a href="works.php?welding= | I20: =CONCATENATE(D20,$K$2,E20,$K$2,F20,G20) -> Iron-Railings-Welding | J20: "> | K20: =PROPER(CONCATENATE(D20," ",E20," ",F20)) -> Iron Railings Welding | L20: </a> <br /> | M20: =CONCATENATE(H20,I20,J20,K20,L20) -> <a href="works.php?welding=Iron-Railings-Welding">Iron Railings Welding</a> <br />
D21: Iron | E21: Chokhat | F21: Welding | H21: <a href="works.php?welding= | I21: =CONCATENATE(D21,$K$2,E21,$K$2,F21,G21) -> Iron-Chokhat-Welding | J21: "> | K21: =PROPER(CONCATENATE(D21," ",E21," ",F21)) -> Iron Chokhat Welding | L21: </a> <br /> | M21: =CONCATENATE(H21,I21,J21,K21,L21) -> <a href="works.php?welding=Iron-Chokhat-Welding">Iron Chokhat Welding</a> <br />
D22: Folding | E22: Gate | F22: Welding | H22: <a href="works.php?welding= | I22: =CONCATENATE(D22,$K$2,E22,$K$2,F22,G22) -> Folding-Gate-Welding | J22: "> | K22: =PROPER(CONCATENATE(D22," ",E22," ",F22)) -> Folding Gate Welding | L22: </a> <br /> | M22: =CONCATENATE(H22,I22,J22,K22,L22) -> <a href="works.php?welding=Folding-Gate-Welding">Folding Gate Welding</a> <br />
D23: Shutter | E23: Gate | F23: Welding | H23: <a href="works.php?welding= | I23: =CONCATENATE(D23,$K$2,E23,$K$2,F23,G23) -> Shutter-Gate-Welding | J23: "> | K23: =PROPER(CONCATENATE(D23," ",E23," ",F23)) -> Shutter Gate Welding | L23: </a> <br /> | M23: =CONCATENATE(H23,I23,J23,K23,L23) -> <a href="works.php?welding=Shutter-Gate-Welding">Shutter Gate Welding</a> <br />
D24: Round | E24: Stairs | F24: Welding | H24: <a href="works.php?welding= | I24: =CONCATENATE(D24,$K$2,E24,$K$2,F24,G24) -> Round-Stairs-Welding | J24: "> | K24: =PROPER(CONCATENATE(D24," ",E24," ",F24)) -> Round Stairs Welding | L24: </a> <br /> | M24: =CONCATENATE(H24,I24,J24,K24,L24) -> <a href="works.php?welding=Round-Stairs-Welding">Round Stairs Welding</a> <br />
D25: Steel | E25: Gate | F25: Welding | H25: <a href="works.php?welding= | I25: =CONCATENATE(D25,$K$2,E25,$K$2,F25,G25) -> Steel-Gate-Welding | J25: "> | K25: =PROPER(CONCATENATE(D25," ",E25," ",F25)) -> Steel Gate Welding | L25: </a> <br /> | M25: =CONCATENATE(H25,I25,J25,K25,L25) -> <a href="works.php?welding=Steel-Gate-Welding">Steel Gate Welding</a> <br />
D26: Steel | E26: Windows | F26: Welding | H26: <a href="works.php?welding= | I26: =CONCATENATE(D26,$K$2,E26,$K$2,F26,G26) -> Steel-Windows-Welding | J26: "> | K26: =PROPER(CONCATENATE(D26," ",E26," ",F26)) -> Steel Windows Welding | L26: </a> <br /> | M26: =CONCATENATE(H26,I26,J26,K26,L26) -> <a href="works.php?welding=Steel-Windows-Welding">Steel Windows Welding</a> <br />
... D74: Rod | E74: Iron | F74: Bed | H74: <a href="works.php?welding= | I74: =CONCATENATE(D74,$K$2,E74,$K$2,F74,G74) -> Rod-Iron-Bed | J74: "> | K74: =PROPER(CONCATENATE(D74," ",E74," ",F74)) -> Rod Iron Bed | L74: </a> <br /> | M74: =CONCATENATE(H74,I74,J74,K74,L74) -> <a href="works.php?welding=Rod-Iron-Bed">Rod Iron Bed</a> <br />

Sheet mughal steel works (2)
I1: .html | K1: blank
A2: XML Meta Tags | K2: - | L2: =LEN(K2) -> 1
C3: Body Parts | D3: Iron Welding Works
C4: iron | D4: Iron | E4: Sliding | F4: Gate | H4: <a href="work/ | I4: =CONCATENATE(D4,$K$2,E4,$K$2,F4,G4,$I$1) -> Iron-Sliding-Gate.html | J4: " target="_blank"> | K4: =PROPER(CONCATENATE(D4," ",E4," ",F4)) -> Iron Sliding Gate | L4: </a> <br /> | M4: =CONCATENATE(H4,I4,J4,K4,L4) -> <a href="work/Iron-Sliding-Gate.html" target="_blank">Iron Sliding Gate</a> <br />
D5: Iron | E5: Sliding | F5: Windows | H5: <a href="work/ | I5: =CONCATENATE(D5,$K$2,E5,$K$2,F5,G5,$I$1) -> Iron-Sliding-Windows.html | J5: " target="_blank"> | K5: =PROPER(CONCATENATE(D5," ",E5," ",F5)) -> Iron Sliding Windows | L5: </a> <br /> | M5: =CONCATENATE(H5,I5,J5,K5,L5) -> <a href="work/Iron-Sliding-Windows.html" target="_blank">Iron Sliding Windows</a> <br />
D6: Iron | E6: Kids | F6: Slide | H6: <a href="work/ | I6: =CONCATENATE(D6,$K$2,E6,$K$2,F6,G6,$I$1) -> Iron-Kids-Slide.html | J6: " target="_blank"> | K6: =PROPER(CONCATENATE(D6," ",E6," ",F6)) -> Iron Kids Slide | L6: </a> <br /> | M6: =CONCATENATE(H6,I6,J6,K6,L6) -> <a href="work/Iron-Kids-Slide.html" target="_blank">Iron Kids Slide</a> <br />
A7: <head>mole removal</head> | D7: Iron | E7: Swing | F7: Cradle | H7: <a href="work/ | I7: =CONCATENATE(D7,$K$2,E7,$K$2,F7,G7,$I$1) -> Iron-Swing-Cradle.html | J7: " target="_blank"> | K7: =PROPER(CONCATENATE(D7," ",E7," ",F7)) -> Iron Swing Cradle | L7: </a> <br /> | M7: =CONCATENATE(H7,I7,J7,K7,L7) -> <a href="work/Iron-Swing-Cradle.html" target="_blank">Iron Swing Cradle</a> <br />
A8: <company>Cosmocare Medical Center</company> | D8: Iron | E8: Tables | F8: Welding | H8: <a href="work/ | I8: =CONCATENATE(D8,$K$2,E8,$K$2,F8,G8,$I$1) -> Iron-Tables-Welding.html | J8: " target="_blank"> | K8: =PROPER(CONCATENATE(D8," ",E8," ",F8)) -> Iron Tables Welding | L8: </a> <br /> | M8: =CONCATENATE(H8,I8,J8,K8,L8) -> <a href="work/Iron-Tables-Welding.html" target="_blank">Iron Tables Welding</a> <br />
A9: <phone>04 379 8747</phone> | D9: Iron | E9: Stool | F9: Welding | H9: <a href="work/ | I9: =CONCATENATE(D9,$K$2,E9,$K$2,F9,G9,$I$1) -> Iron-Stool-Welding.html | J9: " target="_blank"> | K9: =PROPER(CONCATENATE(D9," ",E9," ",F9)) -> Iron Stool Welding | L9: </a> <br /> | M9: =CONCATENATE(H9,I9,J9,K9,L9) -> <a href="work/Iron-Stool-Welding.html" target="_blank">Iron Stool Welding</a> <br />
A10: <region name="Asia"> | D10: Iron | E10: Chairs | F10: Welding | H10: <a href="work/ | I10: =CONCATENATE(D10,$K$2,E10,$K$2,F10,G10,$I$1) -> Iron-Chairs-Welding.html | J10: " target="_blank"> | K10: =PROPER(CONCATENATE(D10," ",E10," ",F10)) -> Iron Chairs Welding | L10: </a> <br /> | M10: =CONCATENATE(H10,I10,J10,K10,L10) -> <a href="work/Iron-Chairs-Welding.html" target="_blank">Iron Chairs Welding</a> <br />
A11: <country name="United Arab Emirates"> | D11: Iron | E11: Steps | F11: Welding | H11: <a href="work/ | I11: =CONCATENATE(D11,$K$2,E11,$K$2,F11,G11,$I$1) -> Iron-Steps-Welding.html | J11: " target="_blank"> | K11: =PROPER(CONCATENATE(D11," ",E11," ",F11)) -> Iron Steps Welding | L11: </a> <br /> | M11: =CONCATENATE(H11,I11,J11,K11,L11) -> <a href="work/Iron-Steps-Welding.html" target="_blank">Iron Steps Welding</a> <br />
A12: <city>Dubai</city> | D12: Iron | E12: Racks | F12: Welding | H12: <a href="work/ | I12: =CONCATENATE(D12,$K$2,E12,$K$2,F12,G12,$I$1) -> Iron-Racks-Welding.html | J12: " target="_blank"> | K12: =PROPER(CONCATENATE(D12," ",E12," ",F12)) -> Iron Racks Welding | L12: </a> <br /> | M12: =CONCATENATE(H12,I12,J12,K12,L12) -> <a href="work/Iron-Racks-Welding.html" target="_blank">Iron Racks Welding</a> <br />
A13: </country> | D13: Iron | E13: Gate | F13: Welding | H13: <a href="work/ | I13: =CONCATENATE(D13,$K$2,E13,$K$2,F13,G13,$I$1) -> Iron-Gate-Welding.html | J13: " target="_blank"> | K13: =PROPER(CONCATENATE(D13," ",E13," ",F13)) -> Iron Gate Welding | L13: </a> <br /> | M13: =CONCATENATE(H13,I13,J13,K13,L13) -> <a href="work/Iron-Gate-Welding.html" target="_blank">Iron Gate Welding</a> <br />
A14: </region> | D14: Iron | E14: Windows | F14: Welding | H14: <a href="work/ | I14: =CONCATENATE(D14,$K$2,E14,$K$2,F14,G14,$I$1) -> Iron-Windows-Welding.html | J14: " target="_blank"> | K14: =PROPER(CONCATENATE(D14," ",E14," ",F14)) -> Iron Windows Welding | L14: </a> <br /> | M14: =CONCATENATE(H14,I14,J14,K14,L14) -> <a href="work/Iron-Windows-Welding.html" target="_blank">Iron Windows Welding</a> <br />
D15: Iron | E15: Grills | F15: Welding | H15: <a href="work/ | I15: =CONCATENATE(D15,$K$2,E15,$K$2,F15,G15,$I$1) -> Iron-Grills-Welding.html | J15: " target="_blank"> | K15: =PROPER(CONCATENATE(D15," ",E15," ",F15)) -> Iron Grills Welding | L15: </a> <br /> | M15: =CONCATENATE(H15,I15,J15,K15,L15) -> <a href="work/Iron-Grills-Welding.html" target="_blank">Iron Grills Welding</a> <br />
D16: Iron | E16: Stairs | F16: Welding | H16: <a href="work/ | I16: =CONCATENATE(D16,$K$2,E16,$K$2,F16,G16,$I$1) -> Iron-Stairs-Welding.html | J16: " target="_blank"> | K16: =PROPER(CONCATENATE(D16," ",E16," ",F16)) -> Iron Stairs Welding | L16: </a> <br /> | M16: =CONCATENATE(H16,I16,J16,K16,L16) -> <a href="work/Iron-Stairs-Welding.html" target="_blank">Iron Stairs Welding</a> <br />
D17: Iron | E17: Door | F17: Welding | H17: <a href="work/ | I17: =CONCATENATE(D17,$K$2,E17,$K$2,F17,G17,$I$1) -> Iron-Door-Welding.html | J17: " target="_blank"> | K17: =PROPER(CONCATENATE(D17," ",E17," ",F17)) -> Iron Door Welding | L17: </a> <br /> | M17: =CONCATENATE(H17,I17,J17,K17,L17) -> <a href="work/Iron-Door-Welding.html" target="_blank">Iron Door Welding</a> <br />
D18: Iron | E18: Fences | F18: Welding | H18: <a href="work/ | I18: =CONCATENATE(D18,$K$2,E18,$K$2,F18,G18,$I$1) -> Iron-Fences-Welding.html | J18: " target="_blank"> | K18: =PROPER(CONCATENATE(D18," ",E18," ",F18)) -> Iron Fences Welding | L18: </a> <br /> | M18: =CONCATENATE(H18,I18,J18,K18,L18) -> <a href="work/Iron-Fences-Welding.html" target="_blank">Iron Fences Welding</a> <br />
D19: Iron | E19: Furniture | F19: Welding | H19: <a href="work/ | I19: =CONCATENATE(D19,$K$2,E19,$K$2,F19,G19,$I$1) -> Iron-Furniture-Welding.html | J19: " target="_blank"> | K19: =PROPER(CONCATENATE(D19," ",E19," ",F19)) -> Iron Furniture Welding | L19: </a> <br /> | M19: =CONCATENATE(H19,I19,J19,K19,L19) -> <a href="work/Iron-Furniture-Welding.html" target="_blank">Iron Furniture Welding</a> <br />
D20: Iron | E20: Railings | F20: Welding | H20: <a href="work/ | I20: =CONCATENATE(D20,$K$2,E20,$K$2,F20,G20,$I$1) -> Iron-Railings-Welding.html | J20: " target="_blank"> | K20: =PROPER(CONCATENATE(D20," ",E20," ",F20)) -> Iron Railings Welding | L20: </a> <br /> | M20: =CONCATENATE(H20,I20,J20,K20,L20) -> <a href="work/Iron-Railings-Welding.html" target="_blank">Iron Railings Welding</a> <br />
D21: Iron | E21: Chokhat | F21: Welding | H21: <a href="work/ | I21: =CONCATENATE(D21,$K$2,E21,$K$2,F21,G21,$I$1) -> Iron-Chokhat-Welding.html | J21: " target="_blank"> | K21: =PROPER(CONCATENATE(D21," ",E21," ",F21)) -> Iron Chokhat Welding | L21: </a> <br /> | M21: =CONCATENATE(H21,I21,J21,K21,L21) -> <a href="work/Iron-Chokhat-Welding.html" target="_blank">Iron Chokhat Welding</a> <br />
D22: Folding | E22: Gate | F22: Welding | H22: <a href="work/ | I22: =CONCATENATE(D22,$K$2,E22,$K$2,F22,G22,$I$1) -> Folding-Gate-Welding.html | J22: " target="_blank"> | K22: =PROPER(CONCATENATE(D22," ",E22," ",F22)) -> Folding Gate Welding | L22: </a> <br /> | M22: =CONCATENATE(H22,I22,J22,K22,L22) -> <a href="work/Folding-Gate-Welding.html" target="_blank">Folding Gate Welding</a> <br />
D23: Shutter | E23: Gate | F23: Welding | H23: <a href="work/ | I23: =CONCATENATE(D23,$K$2,E23,$K$2,F23,G23,$I$1) -> Shutter-Gate-Welding.html | J23: " target="_blank"> | K23: =PROPER(CONCATENATE(D23," ",E23," ",F23)) -> Shutter Gate Welding | L23: </a> <br /> | M23: =CONCATENATE(H23,I23,J23,K23,L23) -> <a href="work/Shutter-Gate-Welding.html" target="_blank">Shutter Gate Welding</a> <br />
D24: Round | E24: Stairs | F24: Welding | H24: <a href="work/ | I24: =CONCATENATE(D24,$K$2,E24,$K$2,F24,G24,$I$1) -> Round-Stairs-Welding.html | J24: " target="_blank"> | K24: =PROPER(CONCATENATE(D24," ",E24," ",F24)) -> Round Stairs Welding | L24: </a> <br /> | M24: =CONCATENATE(H24,I24,J24,K24,L24) -> <a href="work/Round-Stairs-Welding.html" target="_blank">Round Stairs Welding</a> <br />
D25: Steel | E25: Gate | F25: Welding | H25: <a href="work/ | I25: =CONCATENATE(D25,$K$2,E25,$K$2,F25,G25,$I$1) -> Steel-Gate-Welding.html | J25: " target="_blank"> | K25: =PROPER(CONCATENATE(D25," ",E25," ",F25)) -> Steel Gate Welding | L25: </a> <br /> | M25: =CONCATENATE(H25,I25,J25,K25,L25) -> <a href="work/Steel-Gate-Welding.html" target="_blank">Steel Gate Welding</a> <br />
D26: Steel | E26: Windows | F26: Welding | H26: <a href="work/ | I26: =CONCATENATE(D26,$K$2,E26,$K$2,F26,G26,$I$1) -> Steel-Windows-Welding.html | J26: " target="_blank"> | K26: =PROPER(CONCATENATE(D26," ",E26," ",F26)) -> Steel Windows Welding | L26: </a> <br /> | M26: =CONCATENATE(H26,I26,J26,K26,L26) -> <a href="work/Steel-Windows-Welding.html" target="_blank">Steel Windows Welding</a> <br />
... D74: Rod | E74: Iron | F74: Bed | H74: <a href="work/ | I74: =CONCATENATE(D74,$K$2,E74,$K$2,F74,G74,$I$1) -> Rod-Iron-Bed.html | J74: " target="_blank"> | K74: =PROPER(CONCATENATE(D74," ",E74," ",F74)) -> Rod Iron Bed | L74: </a> <br /> | M74: =CONCATENATE(H74,I74,J74,K74,L74) -> <a href="work/Rod-Iron-Bed.html" target="_blank">Rod Iron Bed</a> <br />

Sheet Removal Moles
L1: blank
A2: XML Meta Tags | L2: - | M2: =LEN(L2) -> 1
C3: Body Parts | D3: Iron Welding Works
C4: Abdomen | D4: Mole | E4: Removal | F4: On | G4: Abdomen | I4: <a target="_blank" href="dubai.php?uae= | J4: =CONCATENATE(D4,$L$2,E4,$L$2,F4,$L$2,G4,H4) -> Mole-Removal-On-Abdomen | K4: "> | L4: =PROPER(CONCATENATE(D4," ",E4," ",F4," ",G4," ",H4)) -> Mole Removal On Abdomen | M4: </a> <br /> | N4: =CONCATENATE(I4,J4,K4,L4,M4) -> <a target="_blank" href="dubai.php?uae=Mole-Removal-On-Abdomen">Mole Removal On Abdomen </a> <br />
C5: Arm | D5: Mole | E5: Removal | F5: On | G5: Arm | I5: <a target="_blank" href="dubai.php?uae= | J5: =CONCATENATE(D5,$L$2,E5,$L$2,F5,$L$2,G5,H5) -> Mole-Removal-On-Arm | K5: "> | L5: =PROPER(CONCATENATE(D5," ",E5," ",F5," ",G5," ",H5)) -> Mole Removal On Arm | M5: </a> <br /> | N5: =CONCATENATE(I5,J5,K5,L5,M5) -> <a target="_blank" href="dubai.php?uae=Mole-Removal-On-Arm">Mole Removal On Arm </a> <br />
C6: Back | D6: Mole | E6: Removal | F6: On | G6: Armpit | I6: <a target="_blank" href="dubai.php?uae= | J6: =CONCATENATE(D6,$L$2,E6,$L$2,F6,$L$2,G6,H6) -> Mole-Removal-On-Armpit | K6: "> | L6: =PROPER(CONCATENATE(D6," ",E6," ",F6," ",G6," ",H6)) -> Mole Removal On Armpit | M6: </a> <br /> | N6: =CONCATENATE(I6,J6,K6,L6,M6) -> <a target="_blank" href="dubai.php?uae=Mole-Removal-On-Armpit">Mole Removal On Armpit </a> <br />
C7: Breast | D7: Mole | E7: Removal | F7: On | G7: Back | I7: <a target="_blank" href="dubai.php?uae= | J7: =CONCATENATE(D7,$L$2,E7,$L$2,F7,$L$2,G7,H7) -> Mole-Removal-On-Back | K7: "> | L7: =PROPER(CONCATENATE(D7," ",E7," ",F7," ",G7," ",H7)) -> Mole Removal On Back | M7: </a> <br /> | N7: =CONCATENATE(I7,J7,K7,L7,M7) -> <a target="_blank" href="dubai.php?uae=Mole-Removal-On-Back">Mole Removal On Back </a> <br />
C8: Buttock | D8: Mole | E8: Removal | F8: On | G8: Breast | I8: <a target="_blank" href="dubai.php?uae= | J8: =CONCATENATE(D8,$L$2,E8,$L$2,F8,$L$2,G8,H8) -> Mole-Removal-On-Breast | K8: "> | L8: =PROPER(CONCATENATE(D8," ",E8," ",F8," ",G8," ",H8)) -> Mole Removal On Breast | M8: </a> <br /> | N8: =CONCATENATE(I8,J8,K8,L8,M8) -> <a target="_blank" href="dubai.php?uae=Mole-Removal-On-Breast">Mole Removal On Breast </a> <br />
C9: Chest | D9: Mole | E9: Removal | F9: On | G9: Buttock | I9: <a target="_blank" href="dubai.php?uae= | J9: =CONCATENATE(D9,$L$2,E9,$L$2,F9,$L$2,G9,H9) -> Mole-Removal-On-Buttock | K9: "> | L9: =PROPER(CONCATENATE(D9," ",E9," ",F9," ",G9," ",H9)) -> Mole Removal On Buttock | M9: </a> <br /> | N9: =CONCATENATE(I9,J9,K9,L9,M9) -> <a target="_blank" href="dubai.php?uae=Mole-Removal-On-Buttock">Mole Removal On Buttock </a> <br />
C10: Cheek | D10: Mole | E10: Removal | F10: On | G10: Cheek | I10: <a target="_blank" href="dubai.php?uae= | J10: =CONCATENATE(D10,$L$2,E10,$L$2,F10,$L$2,G10,H10) -> Mole-Removal-On-Cheek | K10: "> | L10: =PROPER(CONCATENATE(D10," ",E10," ",F10," ",G10," ",H10)) -> Mole Removal On Cheek | M10: </a> <br /> | N10: =CONCATENATE(I10,J10,K10,L10,M10) -> <a target="_blank" href="dubai.php?uae=Mole-Removal-On-Cheek">Mole Removal On Cheek </a> <br />
C11: Chin | D11: Mole | E11: Removal | F11: On | G11: Chest | I11: <a target="_blank" href="dubai.php?uae= | J11: =CONCATENATE(D11,$L$2,E11,$L$2,F11,$L$2,G11,H11) -> Mole-Removal-On-Chest | K11: "> | L11: =PROPER(CONCATENATE(D11," ",E11," ",F11," ",G11," ",H11)) -> Mole Removal On Chest | M11: </a> <br /> | N11: =CONCATENATE(I11,J11,K11,L11,M11) -> <a target="_blank" href="dubai.php?uae=Mole-Removal-On-Chest">Mole Removal On Chest </a> <br />
C12: Elbow | D12: Mole | E12: Removal | F12: On | G12: Chin | I12: <a target="_blank" href="dubai.php?uae= | J12: =CONCATENATE(D12,$L$2,E12,$L$2,F12,$L$2,G12,H12) -> Mole-Removal-On-Chin | K12: "> | L12: =PROPER(CONCATENATE(D12," ",E12," ",F12," ",G12," ",H12)) -> Mole Removal On Chin | M12: </a> <br /> | N12: =CONCATENATE(I12,J12,K12,L12,M12) -> <a target="_blank" href="dubai.php?uae=Mole-Removal-On-Chin">Mole Removal On Chin </a> <br />
C13: Hand | D13: Mole | E13: Removal | F13: On | G13: Ear | I13: <a target="_blank" href="dubai.php?uae= | J13: =CONCATENATE(D13,$L$2,E13,$L$2,F13,$L$2,G13,H13) -> Mole-Removal-On-Ear | K13: "> | L13: =PROPER(CONCATENATE(D13," ",E13," ",F13," ",G13," ",H13)) -> Mole Removal On Ear | M13: </a> <br /> | N13: =CONCATENATE(I13,J13,K13,L13,M13) -> <a target="_blank" href="dubai.php?uae=Mole-Removal-On-Ear">Mole Removal On Ear </a> <br />
C14: Navel | D14: Mole | E14: Removal | F14: On | G14: Elbow | I14: <a target="_blank" href="dubai.php?uae= | J14: =CONCATENATE(D14,$L$2,E14,$L$2,F14,$L$2,G14,H14) -> Mole-Removal-On-Elbow | K14: "> | L14: =PROPER(CONCATENATE(D14," ",E14," ",F14," ",G14," ",H14)) -> Mole Removal On Elbow | M14: </a> <br /> | N14: =CONCATENATE(I14,J14,K14,L14,M14) -> <a target="_blank" href="dubai.php?uae=Mole-Removal-On-Elbow">Mole Removal On Elbow </a> <br />
C15: Neck | D15: Mole | E15: Removal | F15: On | G15: Eyebrow | I15: <a target="_blank" href="dubai.php?uae= | J15: =CONCATENATE(D15,$L$2,E15,$L$2,F15,$L$2,G15,H15) -> Mole-Removal-On-Eyebrow | K15: "> | L15: =PROPER(CONCATENATE(D15," ",E15," ",F15," ",G15," ",H15)) -> Mole Removal On Eyebrow | M15: </a> <br /> | N15: =CONCATENATE(I15,J15,K15,L15,M15) -> <a target="_blank" href="dubai.php?uae=Mole-Removal-On-Eyebrow">Mole Removal On Eyebrow </a> <br />
... C26: Hips | D26: Mole | E26: Removal | F26: On | G26: Thigh | I26: <a target="_blank" href="dubai.php?uae= | J26: =CONCATENATE(D26,$L$2,E26,$L$2,F26,$L$2,G26,H26) -> Mole-Removal-On-Thigh | K26: "> | L26: =PROPER(CONCATENATE(D26," ",E26," ",F26," ",G26," ",H26)) -> Mole Removal On Thigh | M26: </a> <br /> | N26: =CONCATENATE(I26,J26,K26,L26,M26) -> <a target="_blank" href="dubai.php?uae=Mole-Removal-On-Thigh">Mole Removal On Thigh </a> <br />
D27: Mole | E27: Treatment | F27: On | G27: Abdomen | I27: <a target="_blank" href="dubai.php?uae= | J27: =CONCATENATE(D27,$L$2,E27,$L$2,F27,$L$2,G27,H27) -> Mole-Treatment-On-Abdomen | K27: "> | L27: =PROPER(CONCATENATE(D27," ",E27," ",F27," ",G27," ",H27)) -> Mole Treatment On Abdomen | M27: </a> <br /> | N27: =CONCATENATE(I27,J27,K27,L27,M27) -> <a target="_blank" href="dubai.php?uae=Mole-Treatment-On-Abdomen">Mole Treatment On Abdomen </a> <br />
D28: Mole | E28: Treatment | F28: On | G28: Arm | I28: <a target="_blank" href="dubai.php?uae= | J28: =CONCATENATE(D28,$L$2,E28,$L$2,F28,$L$2,G28,H28) -> Mole-Treatment-On-Arm | K28: "> | L28: =PROPER(CONCATENATE(D28," ",E28," ",F28," ",G28," ",H28)) -> Mole Treatment On Arm | M28: </a> <br /> | N28: =CONCATENATE(I28,J28,K28,L28,M28) -> <a target="_blank" href="dubai.php?uae=Mole-Treatment-On-Arm">Mole Treatment On Arm </a> <br />
D29: Mole | E29: Treatment | F29: On | G29: Armpit | I29: <a target="_blank" href="dubai.php?uae= | J29: =CONCATENATE(D29,$L$2,E29,$L$2,F29,$L$2,G29,H29) -> Mole-Treatment-On-Armpit | K29: "> | L29: =PROPER(CONCATENATE(D29," ",E29," ",F29," ",G29," ",H29)) -> Mole Treatment On Armpit | M29: </a> <br /> | N29: =CONCATENATE(I29,J29,K29,L29,M29) -> <a target="_blank" href="dubai.php?uae=Mole-Treatment-On-Armpit">Mole Treatment On Armpit </a> <br />
D30: Mole | E30: Treatment | F30: On | G30: Back | I30: <a target="_blank" href="dubai.php?uae= | J30: =CONCATENATE(D30,$L$2,E30,$L$2,F30,$L$2,G30,H30) -> Mole-Treatment-On-Back | K30: "> | L30: =PROPER(CONCATENATE(D30," ",E30," ",F30," ",G30," ",H30)) -> Mole Treatment On Back | M30: </a> <br /> | N30: =CONCATENATE(I30,J30,K30,L30,M30) -> <a target="_blank" href="dubai.php?uae=Mole-Treatment-On-Back">Mole Treatment On Back </a> <br />
D31: Mole | E31: Treatment | F31: On | G31: Breast | I31: <a target="_blank" href="dubai.php?uae= | J31: =CONCATENATE(D31,$L$2,E31,$L$2,F31,$L$2,G31,H31) -> Mole-Treatment-On-Breast | K31: "> | L31: =PROPER(CONCATENATE(D31," ",E31," ",F31," ",G31," ",H31)) -> Mole Treatment On Breast | M31: </a> <br /> | N31: =CONCATENATE(I31,J31,K31,L31,M31) -> <a target="_blank" href="dubai.php?uae=Mole-Treatment-On-Breast">Mole Treatment On Breast </a> <br />
D32: Mole | E32: Treatment | F32: On | G32: Buttock | I32: <a target="_blank" href="dubai.php?uae= | J32: =CONCATENATE(D32,$L$2,E32,$L$2,F32,$L$2,G32,H32) -> Mole-Treatment-On-Buttock | K32: "> | L32: =PROPER(CONCATENATE(D32," ",E32," ",F32," ",G32," ",H32)) -> Mole Treatment On Buttock | M32: </a> <br /> | N32: =CONCATENATE(I32,J32,K32,L32,M32) -> <a target="_blank" href="dubai.php?uae=Mole-Treatment-On-Buttock">Mole Treatment On Buttock </a> <br />
D33: Mole | E33: Treatment | F33: On | G33: Cheek | I33: <a target="_blank" href="dubai.php?uae= | J33: =CONCATENATE(D33,$L$2,E33,$L$2,F33,$L$2,G33,H33) -> Mole-Treatment-On-Cheek | K33: "> | L33: =PROPER(CONCATENATE(D33," ",E33," ",F33," ",G33," ",H33)) -> Mole Treatment On Cheek | M33: </a> <br /> | N33: =CONCATENATE(I33,J33,K33,L33,M33) -> <a target="_blank" href="dubai.php?uae=Mole-Treatment-On-Cheek">Mole Treatment On Cheek </a> <br />
D34: Mole | E34: Treatment | F34: On | G34: Chest | I34: <a target="_blank" href="dubai.php?uae= | J34: =CONCATENATE(D34,$L$2,E34,$L$2,F34,$L$2,G34,H34) -> Mole-Treatment-On-Chest | K34: "> | L34: =PROPER(CONCATENATE(D34," ",E34," ",F34," ",G34," ",H34)) -> Mole Treatment On Chest | M34: </a> <br /> | N34: =CONCATENATE(I34,J34,K34,L34,M34) -> <a target="_blank" href="dubai.php?uae=Mole-Treatment-On-Chest">Mole Treatment On Chest </a> <br />
D35: Mole | E35: Treatment | F35: On | G35: Chin | I35: <a target="_blank" href="dubai.php?uae= | J35: =CONCATENATE(D35,$L$2,E35,$L$2,F35,$L$2,G35,H35) -> Mole-Treatment-On-Chin | K35: "> | L35: =PROPER(CONCATENATE(D35," ",E35," ",F35," ",G35," ",H35)) -> Mole Treatment On Chin | M35: </a> <br /> | N35: =CONCATENATE(I35,J35,K35,L35,M35) -> <a target="_blank" href="dubai.php?uae=Mole-Treatment-On-Chin">Mole Treatment On Chin </a> <br />
D36: Mole | E36: Treatment | F36: On | G36: Ear | I36: <a target="_blank" href="dubai.php?uae= | J36: =CONCATENATE(D36,$L$2,E36,$L$2,F36,$L$2,G36,H36) -> Mole-Treatment-On-Ear | K36: "> | L36: =PROPER(CONCATENATE(D36," ",E36," ",F36," ",G36," ",H36)) -> Mole Treatment On Ear | M36: </a> <br /> | N36: =CONCATENATE(I36,J36,K36,L36,M36) -> <a target="_blank" href="dubai.php?uae=Mole-Treatment-On-Ear">Mole Treatment On Ear </a> <br />
D37: Mole | E37: Treatment | F37: On | G37: Elbow | I37: <a target="_blank" href="dubai.php?uae= | J37: =CONCATENATE(D37,$L$2,E37,$L$2,F37,$L$2,G37,H37) -> Mole-Treatment-On-Elbow | K37: "> | L37: =PROPER(CONCATENATE(D37," ",E37," ",F37," ",G37," ",H37)) -> Mole Treatment On Elbow | M37: </a> <br /> | N37: =CONCATENATE(I37,J37,K37,L37,M37) -> <a target="_blank" href="dubai.php?uae=Mole-Treatment-On-Elbow">Mole Treatment On Elbow </a> <br />
D38: Mole | E38: Treatment | F38: On | G38: Eyebrow | I38: <a target="_blank" href="dubai.php?uae= | J38: =CONCATENATE(D38,$L$2,E38,$L$2,F38,$L$2,G38,H38) -> Mole-Treatment-On-Eyebrow | K38: "> | L38: =PROPER(CONCATENATE(D38," ",E38," ",F38," ",G38," ",H38)) -> Mole Treatment On Eyebrow | M38: </a> <br /> | N38: =CONCATENATE(I38,J38,K38,L38,M38) -> <a target="_blank" href="dubai.php?uae=Mole-Treatment-On-Eyebrow">Mole Treatment On Eyebrow </a> <br />
... D95: Thigh | E95: Laser | F95: Mole | G95: Treatment | I95: <a target="_blank" href="dubai.php?uae= | J95: =CONCATENATE(D95,$L$2,E95,$L$2,F95,$L$2,G95,H95) -> Thigh-Laser-Mole-Treatment | K95: "> | L95: =PROPER(CONCATENATE(D95," ",E95," ",F95," ",G95," ",H95)) -> Thigh Laser Mole Treatment | M95: </a> <br /> | N95: =CONCATENATE(I95,J95,K95,L95,M95) -> <a target="_blank" href="dubai.php?uae=Thigh-Laser-Mole-Treatment">Thigh Laser Mole Treatment </a> <br />

Sheet Removal Warts
L1: blank
A2: XML Meta Tags | L2: - | M2: =LEN(L2) -> 1
C3: Body Parts | D3: Iron Welding Works
C4: Abdomen | D4: Warts | E4: Removal | F4: On | G4: Abdomen | I4: <a target="_blank" href="dubai.php?uae= | J4: =CONCATENATE(D4,$L$2,E4,$L$2,F4,$L$2,G4,H4) -> Warts-Removal-On-Abdomen | K4: "> | L4: =PROPER(CONCATENATE(D4," ",E4," ",F4," ",G4," ",H4)) -> Warts Removal On Abdomen | M4: </a> <br /> | N4: =CONCATENATE(I4,J4,K4,L4,M4) -> <a target="_blank" href="dubai.php?uae=Warts-Removal-On-Abdomen">Warts Removal On Abdomen </a> <br />
C5: Arm | D5: Warts | E5: Removal | F5: On | G5: Arm | I5: <a target="_blank" href="dubai.php?uae= | J5: =CONCATENATE(D5,$L$2,E5,$L$2,F5,$L$2,G5,H5) -> Warts-Removal-On-Arm | K5: "> | L5: =PROPER(CONCATENATE(D5," ",E5," ",F5," ",G5," ",H5)) -> Warts Removal On Arm | M5: </a> <br /> | N5: =CONCATENATE(I5,J5,K5,L5,M5) -> <a target="_blank" href="dubai.php?uae=Warts-Removal-On-Arm">Warts Removal On Arm </a> <br />
C6: Back | D6: Warts | E6: Removal | F6: On | G6: Armpit | I6: <a target="_blank" href="dubai.php?uae= | J6: =CONCATENATE(D6,$L$2,E6,$L$2,F6,$L$2,G6,H6) -> Warts-Removal-On-Armpit | K6: "> | L6: =PROPER(CONCATENATE(D6," ",E6," ",F6," ",G6," ",H6)) -> Warts Removal On Armpit | M6: </a> <br /> | N6: =CONCATENATE(I6,J6,K6,L6,M6) -> <a target="_blank" href="dubai.php?uae=Warts-Removal-On-Armpit">Warts Removal On Armpit </a> <br />
C7: Breast | D7: Warts | E7: Removal | F7: On | G7: Back | I7: <a target="_blank" href="dubai.php?uae= | J7: =CONCATENATE(D7,$L$2,E7,$L$2,F7,$L$2,G7,H7) -> Warts-Removal-On-Back | K7: "> | L7: =PROPER(CONCATENATE(D7," ",E7," ",F7," ",G7," ",H7)) -> Warts Removal On Back | M7: </a> <br /> | N7: =CONCATENATE(I7,J7,K7,L7,M7) -> <a target="_blank" href="dubai.php?uae=Warts-Removal-On-Back">Warts Removal On Back </a> <br />
C8: Buttock | D8: Warts | E8: Removal | F8: On | G8: Breast | I8: <a target="_blank" href="dubai.php?uae= | J8: =CONCATENATE(D8,$L$2,E8,$L$2,F8,$L$2,G8,H8) -> Warts-Removal-On-Breast | K8: "> | L8: =PROPER(CONCATENATE(D8," ",E8," ",F8," ",G8," ",H8)) -> Warts Removal On Breast | M8: </a> <br /> | N8: =CONCATENATE(I8,J8,K8,L8,M8) -> <a target="_blank" href="dubai.php?uae=Warts-Removal-On-Breast">Warts Removal On Breast </a> <br />
C9: Chest | D9: Warts | E9: Removal | F9: On | G9: Buttock | I9: <a target="_blank" href="dubai.php?uae= | J9: =CONCATENATE(D9,$L$2,E9,$L$2,F9,$L$2,G9,H9) -> Warts-Removal-On-Buttock | K9: "> | L9: =PROPER(CONCATENATE(D9," ",E9," ",F9," ",G9," ",H9)) -> Warts Removal On Buttock | M9: </a> <br /> | N9: =CONCATENATE(I9,J9,K9,L9,M9) -> <a target="_blank" href="dubai.php?uae=Warts-Removal-On-Buttock">Warts Removal On Buttock </a> <br />
C10: Cheek | D10: Warts | E10: Removal | F10: On | G10: Cheek | I10: <a target="_blank" href="dubai.php?uae= | J10: =CONCATENATE(D10,$L$2,E10,$L$2,F10,$L$2,G10,H10) -> Warts-Removal-On-Cheek | K10: "> | L10: =PROPER(CONCATENATE(D10," ",E10," ",F10," ",G10," ",H10)) -> Warts Removal On Cheek | M10: </a> <br /> | N10: =CONCATENATE(I10,J10,K10,L10,M10) -> <a target="_blank" href="dubai.php?uae=Warts-Removal-On-Cheek">Warts Removal On Cheek </a> <br />
C11: Chin | D11: Warts | E11: Removal | F11: On | G11: Chest | I11: <a target="_blank" href="dubai.php?uae= | J11: =CONCATENATE(D11,$L$2,E11,$L$2,F11,$L$2,G11,H11) -> Warts-Removal-On-Chest | K11: "> | L11: =PROPER(CONCATENATE(D11," ",E11," ",F11," ",G11," ",H11)) -> Warts Removal On Chest | M11: </a> <br /> | N11: =CONCATENATE(I11,J11,K11,L11,M11) -> <a target="_blank" href="dubai.php?uae=Warts-Removal-On-Chest">Warts Removal On Chest </a> <br />
C12: Elbow | D12: Warts | E12: Removal | F12: On | G12: Chin | I12: <a target="_blank" href="dubai.php?uae= | J12: =CONCATENATE(D12,$L$2,E12,$L$2,F12,$L$2,G12,H12) -> Warts-Removal-On-Chin | K12: "> | L12: =PROPER(CONCATENATE(D12," ",E12," ",F12," ",G12," ",H12)) -> Warts Removal On Chin | M12: </a> <br /> | N12: =CONCATENATE(I12,J12,K12,L12,M12) -> <a target="_blank" href="dubai.php?uae=Warts-Removal-On-Chin">Warts Removal On Chin </a> <br />
C13: Hand | D13: Warts | E13: Removal | F13: On | G13: Ear | I13: <a target="_blank" href="dubai.php?uae= | J13: =CONCATENATE(D13,$L$2,E13,$L$2,F13,$L$2,G13,H13) -> Warts-Removal-On-Ear | K13: "> | L13: =PROPER(CONCATENATE(D13," ",E13," ",F13," ",G13," ",H13)) -> Warts Removal On Ear | M13: </a> <br /> | N13: =CONCATENATE(I13,J13,K13,L13,M13) -> <a target="_blank" href="dubai.php?uae=Warts-Removal-On-Ear">Warts Removal On Ear </a> <br />
C14: Navel | D14: Warts | E14: Removal | F14: On | G14: Elbow | I14: <a target="_blank" href="dubai.php?uae= | J14: =CONCATENATE(D14,$L$2,E14,$L$2,F14,$L$2,G14,H14) -> Warts-Removal-On-Elbow | K14: "> | L14: =PROPER(CONCATENATE(D14," ",E14," ",F14," ",G14," ",H14)) -> Warts Removal On Elbow | M14: </a> <br /> | N14: =CONCATENATE(I14,J14,K14,L14,M14) -> <a target="_blank" href="dubai.php?uae=Warts-Removal-On-Elbow">Warts Removal On Elbow </a> <br />
C15: Neck | D15: Warts | E15: Removal | F15: On | G15: Eyebrow | I15: <a target="_blank" href="dubai.php?uae= | J15: =CONCATENATE(D15,$L$2,E15,$L$2,F15,$L$2,G15,H15) -> Warts-Removal-On-Eyebrow | K15: "> | L15: =PROPER(CONCATENATE(D15," ",E15," ",F15," ",G15," ",H15)) -> Warts Removal On Eyebrow | M15: </a> <br /> | N15: =CONCATENATE(I15,J15,K15,L15,M15) -> <a target="_blank" href="dubai.php?uae=Warts-Removal-On-Eyebrow">Warts Removal On Eyebrow </a> <br />
... C26: Hips | D26: Warts | E26: Removal | F26: On | G26: Thigh | I26: <a target="_blank" href="dubai.php?uae= | J26: =CONCATENATE(D26,$L$2,E26,$L$2,F26,$L$2,G26,H26) -> Warts-Removal-On-Thigh | K26: "> | L26: =PROPER(CONCATENATE(D26," ",E26," ",F26," ",G26," ",H26)) -> Warts Removal On Thigh | M26: </a> <br /> | N26: =CONCATENATE(I26,J26,K26,L26,M26) -> <a target="_blank" href="dubai.php?uae=Warts-Removal-On-Thigh">Warts Removal On Thigh </a> <br />
D27: Warts | E27: Treatment | F27: On | G27: Abdomen | I27: <a target="_blank" href="dubai.php?uae= | J27: =CONCATENATE(D27,$L$2,E27,$L$2,F27,$L$2,G27,H27) -> Warts-Treatment-On-Abdomen | K27: "> | L27: =PROPER(CONCATENATE(D27," ",E27," ",F27," ",G27," ",H27)) -> Warts Treatment On Abdomen | M27: </a> <br /> | N27: =CONCATENATE(I27,J27,K27,L27,M27) -> <a target="_blank" href="dubai.php?uae=Warts-Treatment-On-Abdomen">Warts Treatment On Abdomen </a> <br />
D28: Warts | E28: Treatment | F28: On | G28: Arm | I28: <a target="_blank" href="dubai.php?uae= | J28: =CONCATENATE(D28,$L$2,E28,$L$2,F28,$L$2,G28,H28) -> Warts-Treatment-On-Arm | K28: "> | L28: =PROPER(CONCATENATE(D28," ",E28," ",F28," ",G28," ",H28)) -> Warts Treatment On Arm | M28: </a> <br /> | N28: =CONCATENATE(I28,J28,K28,L28,M28) -> <a target="_blank" href="dubai.php?uae=Warts-Treatment-On-Arm">Warts Treatment On Arm </a> <br />
D29: Warts | E29: Treatment | F29: On | G29: Armpit | I29: <a target="_blank" href="dubai.php?uae= | J29: =CONCATENATE(D29,$L$2,E29,$L$2,F29,$L$2,G29,H29) -> Warts-Treatment-On-Armpit | K29: "> | L29: =PROPER(CONCATENATE(D29," ",E29," ",F29," ",G29," ",H29)) -> Warts Treatment On Armpit | M29: </a> <br /> | N29: =CONCATENATE(I29,J29,K29,L29,M29) -> <a target="_blank" href="dubai.php?uae=Warts-Treatment-On-Armpit">Warts Treatment On Armpit </a> <br />
D30: Warts | E30: Treatment | F30: On | G30: Back | I30: <a target="_blank" href="dubai.php?uae= | J30: =CONCATENATE(D30,$L$2,E30,$L$2,F30,$L$2,G30,H30) -> Warts-Treatment-On-Back | K30: "> | L30: =PROPER(CONCATENATE(D30," ",E30," ",F30," ",G30," ",H30)) -> Warts Treatment On Back | M30: </a> <br /> | N30: =CONCATENATE(I30,J30,K30,L30,M30) -> <a target="_blank" href="dubai.php?uae=Warts-Treatment-On-Back">Warts Treatment On Back </a> <br />
D31: Warts | E31: Treatment | F31: On | G31: Breast | I31: <a target="_blank" href="dubai.php?uae= | J31: =CONCATENATE(D31,$L$2,E31,$L$2,F31,$L$2,G31,H31) -> Warts-Treatment-On-Breast | K31: "> | L31: =PROPER(CONCATENATE(D31," ",E31," ",F31," ",G31," ",H31)) -> Warts Treatment On Breast | M31: </a> <br /> | N31: =CONCATENATE(I31,J31,K31,L31,M31) -> <a target="_blank" href="dubai.php?uae=Warts-Treatment-On-Breast">Warts Treatment On Breast </a> <br />
D32: Warts | E32: Treatment | F32: On | G32: Buttock | I32: <a target="_blank" href="dubai.php?uae= | J32: =CONCATENATE(D32,$L$2,E32,$L$2,F32,$L$2,G32,H32) -> Warts-Treatment-On-Buttock | K32: "> | L32: =PROPER(CONCATENATE(D32," ",E32," ",F32," ",G32," ",H32)) -> Warts Treatment On Buttock | M32: </a> <br /> | N32: =CONCATENATE(I32,J32,K32,L32,M32) -> <a target="_blank" href="dubai.php?uae=Warts-Treatment-On-Buttock">Warts Treatment On Buttock </a> <br />
D33: Warts | E33: Treatment | F33: On | G33: Cheek | I33: <a target="_blank" href="dubai.php?uae= | J33: =CONCATENATE(D33,$L$2,E33,$L$2,F33,$L$2,G33,H33) -> Warts-Treatment-On-Cheek | K33: "> | L33: =PROPER(CONCATENATE(D33," ",E33," ",F33," ",G33," ",H33)) -> Warts Treatment On Cheek | M33: </a> <br /> | N33: =CONCATENATE(I33,J33,K33,L33,M33) -> <a target="_blank" href="dubai.php?uae=Warts-Treatment-On-Cheek">Warts Treatment On Cheek </a> <br />
D34: Warts | E34: Treatment | F34: On | G34: Chest | I34: <a target="_blank" href="dubai.php?uae= | J34: =CONCATENATE(D34,$L$2,E34,$L$2,F34,$L$2,G34,H34) -> Warts-Treatment-On-Chest | K34: "> | L34: =PROPER(CONCATENATE(D34," ",E34," ",F34," ",G34," ",H34)) -> Warts Treatment On Chest | M34: </a> <br /> | N34: =CONCATENATE(I34,J34,K34,L34,M34) -> <a target="_blank" href="dubai.php?uae=Warts-Treatment-On-Chest">Warts Treatment On Chest </a> <br />
D35: Warts | E35: Treatment | F35: On | G35: Chin | I35: <a target="_blank" href="dubai.php?uae= | J35: =CONCATENATE(D35,$L$2,E35,$L$2,F35,$L$2,G35,H35) -> Warts-Treatment-On-Chin | K35: "> | L35: =PROPER(CONCATENATE(D35," ",E35," ",F35," ",G35," ",H35)) -> Warts Treatment On Chin | M35: </a> <br /> | N35: =CONCATENATE(I35,J35,K35,L35,M35) -> <a target="_blank" href="dubai.php?uae=Warts-Treatment-On-Chin">Warts Treatment On Chin </a> <br />
D36: Warts | E36: Treatment | F36: On | G36: Ear | I36: <a target="_blank" href="dubai.php?uae= | J36: =CONCATENATE(D36,$L$2,E36,$L$2,F36,$L$2,G36,H36) -> Warts-Treatment-On-Ear | K36: "> | L36: =PROPER(CONCATENATE(D36," ",E36," ",F36," ",G36," ",H36)) -> Warts Treatment On Ear | M36: </a> <br /> | N36: =CONCATENATE(I36,J36,K36,L36,M36) -> <a target="_blank" href="dubai.php?uae=Warts-Treatment-On-Ear">Warts Treatment On Ear </a> <br />
D37: Warts | E37: Treatment | F37: On | G37: Elbow | I37: <a target="_blank" href="dubai.php?uae= | J37: =CONCATENATE(D37,$L$2,E37,$L$2,F37,$L$2,G37,H37) -> Warts-Treatment-On-Elbow | K37: "> | L37: =PROPER(CONCATENATE(D37," ",E37," ",F37," ",G37," ",H37)) -> Warts Treatment On Elbow | M37: </a> <br /> | N37: =CONCATENATE(I37,J37,K37,L37,M37) -> <a target="_blank" href="dubai.php?uae=Warts-Treatment-On-Elbow">Warts Treatment On Elbow </a> <br />
D38: Warts | E38: Treatment | F38: On | G38: Eyebrow | I38: <a target="_blank" href="dubai.php?uae= | J38: =CONCATENATE(D38,$L$2,E38,$L$2,F38,$L$2,G38,H38) -> Warts-Treatment-On-Eyebrow | K38: "> | L38: =PROPER(CONCATENATE(D38," ",E38," ",F38," ",G38," ",H38)) -> Warts Treatment On Eyebrow | M38: </a> <br /> | N38: =CONCATENATE(I38,J38,K38,L38,M38) -> <a target="_blank" href="dubai.php?uae=Warts-Treatment-On-Eyebrow">Warts Treatment On Eyebrow </a> <br />
... D94: Shoulder | E94: Laser | F94: Warts | G94: Treatment | I94: <a target="_blank" href="dubai.php?uae= | J94: =CONCATENATE(D94,$L$2,E94,$L$2,F94,$L$2,G94,H94) -> Shoulder-Laser-Warts-Treatment | K94: "> | L94: =PROPER(CONCATENATE(D94," ",E94," ",F94," ",G94," ",H94)) -> Shoulder Laser Warts Treatment | M94: </a> <br /> | N94: =CONCATENATE(I94,J94,K94,L94,M94) -> <a target="_blank" href="dubai.php?uae=Shoulder-Laser-Warts-Treatment">Shoulder Laser Warts Treatment </a> <br />
D95: Thigh | E95: Laser | F95: Warts | G95: Treatment | I95: <a target="_blank" href="dubai.php?uae= | J95: <a target="_blank" href="dubai.php?uae= | K95: <a target="_blank" href="dubai.php?uae= | L95: <a target="_blank" href="dubai.php?uae= | M95: <a target="_blank" href="dubai.php?uae= | N95: <a target="_blank" href="dubai.php?uae=
A96: With Free Consultation | B96: -With-Free-Consultation | D96: Abdomen | E96: Laser | F96: Warts | G96: Removal | I96: <a target="_blank" href="dubai.php?uae= | J96: <a target="_blank" href="dubai.php?uae= | K96: <a target="_blank" href="dubai.php?uae= | L96: <a target="_blank" href="dubai.php?uae= | M96: <a target="_blank" href="dubai.php?uae= | N96: <a target="_blank" href="dubai.php?uae=
D97: Arm | E97: Laser | F97: Warts | G97: Removal | I97: <a target="_blank" href="dubai.php?uae= | J97: <a target="_blank" href="dubai.php?uae= | K97: <a target="_blank" href="dubai.php?uae= | L97: <a target="_blank" href="dubai.php?uae= | M97: <a target="_blank" href="dubai.php?uae= | N97: <a target="_blank" href="dubai.php?uae=
D98: Armpit | E98: Laser | F98: Warts | G98: Removal | I98: <a target="_blank" href="dubai.php?uae= | J98: <a target="_blank" href="dubai.php?uae= | K98: <a target="_blank" href="dubai.php?uae= | L98: <a target="_blank" href="dubai.php?uae= | M98: <a target="_blank" href="dubai.php?uae= | N98: <a target="_blank" href="dubai.php?uae=
D99: Back | E99: Laser | F99: Warts | G99: Removal | I99: <a target="_blank" href="dubai.php?uae= | J99: <a target="_blank" href="dubai.php?uae= | K99: <a target="_blank" href="dubai.php?uae= | L99: <a target="_blank" href="dubai.php?uae= | M99: <a target="_blank" href="dubai.php?uae= | N99: <a target="_blank" href="dubai.php?uae=
D100: Breast | E100: Laser | F100: Warts | G100: Removal | I100: <a target="_blank" href="dubai.php?uae= | J100: <a target="_blank" href="dubai.php?uae= | K100: <a target="_blank" href="dubai.php?uae= | L100: <a target="_blank" href="dubai.php?uae= | M100: <a target="_blank" href="dubai.php?uae= | N100: <a target="_blank" href="dubai.php?uae=
D101: Buttock | E101: Laser | F101: Warts | G101: Removal | I101: <a target="_blank" href="dubai.php?uae= | J101: <a target="_blank" href="dubai.php?uae= | K101: <a target="_blank" href="dubai.php?uae= | L101: <a target="_blank" href="dubai.php?uae= | M101: <a target="_blank" href="dubai.php?uae= | N101: <a target="_blank" href="dubai.php?uae=
D102: Cheek | E102: Laser | F102: Warts | G102: Removal | I102: <a target="_blank" href="dubai.php?uae= | J102: <a target="_blank" href="dubai.php?uae= | K102: <a target="_blank" href="dubai.php?uae= | L102: <a target="_blank" href="dubai.php?uae= | M102: <a target="_blank" href="dubai.php?uae= | N102: <a target="_blank" href="dubai.php?uae=
D103: Chest | E103: Laser | F103: Warts | G103: Removal | I103: <a target="_blank" href="dubai.php?uae= | J103: <a target="_blank" href="dubai.php?uae= | K103: <a target="_blank" href="dubai.php?uae= | L103: <a target="_blank" href="dubai.php?uae= | M103: <a target="_blank" href="dubai.php?uae= | N103: <a target="_blank" href="dubai.php?uae=
D104: Chin | E104: Laser | F104: Warts | G104: Removal | I104: <a target="_blank" href="dubai.php?uae= | J104: <a target="_blank" href="dubai.php?uae= | K104: <a target="_blank" href="dubai.php?uae= | L104: <a target="_blank" href="dubai.php?uae= | M104: <a target="_blank" href="dubai.php?uae= | N104: <a target="_blank" href="dubai.php?uae=
D105: Ear | E105: Laser | F105: Warts | G105: Removal | I105: <a target="_blank" href="dubai.php?uae= | J105: <a target="_blank" href="dubai.php?uae= | K105: <a target="_blank" href="dubai.php?uae= | L105: <a target="_blank" href="dubai.php?uae= | M105: <a target="_blank" href="dubai.php?uae= | N105: <a target="_blank" href="dubai.php?uae=
D106: Elbow | E106: Laser | F106: Warts | G106: Removal | I106: <a target="_blank" href="dubai.php?uae= | J106: <a target="_blank" href="dubai.php?uae= | K106: <a target="_blank" href="dubai.php?uae= | L106: <a target="_blank" href="dubai.php?uae= | M106: <a target="_blank" href="dubai.php?uae= | N106: <a target="_blank" href="dubai.php?uae=
D107: Eyebrow | E107: Laser | F107: Warts | G107: Removal | I107: <a target="_blank" href="dubai.php?uae= | J107: <a target="_blank" href="dubai.php?uae= | K107: <a target="_blank" href="dubai.php?uae= | L107: <a target="_blank" href="dubai.php?uae= | M107: <a target="_blank" href="dubai.php?uae= | N107: <a target="_blank" href="dubai.php?uae=
D108: Face | E108: Laser | F108: Warts | G108: Removal | I108: <a target="_blank" href="dubai.php?uae= | J108: <a target="_blank" href="dubai.php?uae= | K108: <a target="_blank" href="dubai.php?uae= | L108: <a target="_blank" href="dubai.php?uae= | M108: <a target="_blank" href="dubai.php?uae= | N108: <a target="_blank" href="dubai.php?uae=
... D141: Thigh | E141: Laser | F141: Warts | G141: Treatment | I141: <a target="_blank" href="dubai.php?uae= | J141: <a target="_blank" href="dubai.php?uae= | K141: <a target="_blank" href="dubai.php?uae= | L141: <a target="_blank" href="dubai.php?uae= | M141: <a target="_blank" href="dubai.php?uae= | N141: <a target="_blank" href="dubai.php?uae=

Sheet Removal Skin Tags
J1: .html | L1: blank
A2: XML Meta Tags | L2: - | M2: =LEN(L2) -> 1
C3: Body Parts | D3: Iron Welding Works
C4: Abdomen | D4: Skin | E4: Tags | F4: Removal | G4: On | H4: Abdomen | I4: <a target="_blank" href="skin_tag/ | J4: =CONCATENATE(D4,$L$2,E4,$L$2,F4,$L$2,G4,$L$2,H4,$J$1) -> Skin-Tags-Removal-On-Abdomen.html | K4: "> | L4: =PROPER(CONCATENATE(D4," ",E4," ",F4," ",G4," ",H4)) -> Skin Tags Removal On Abdomen | M4: </a> <br /> | N4: =CONCATENATE(I4,J4,K4,L4,M4) -> <a target="_blank" href="skin_tag/Skin-Tags-Removal-On-Abdomen.html">Skin Tags Removal On Abdomen</a> <br />
C5: Arm | D5: Skin | E5: Tags | F5: Removal | G5: On | H5: Arm | I5: <a target="_blank" href="skin_tag/ | J5: =CONCATENATE(D5,$L$2,E5,$L$2,F5,$L$2,G5,$L$2,H5,$J$1) -> Skin-Tags-Removal-On-Arm.html | K5: "> | L5: =PROPER(CONCATENATE(D5," ",E5," ",F5," ",G5," ",H5)) -> Skin Tags Removal On Arm | M5: </a> <br /> | N5: =CONCATENATE(I5,J5,K5,L5,M5) -> <a target="_blank" href="skin_tag/Skin-Tags-Removal-On-Arm.html">Skin Tags Removal On Arm</a> <br />
C6: Back | D6: Skin | E6: Tags | F6: Removal | G6: On | H6: Armpit | I6: <a target="_blank" href="skin_tag/ | J6: =CONCATENATE(D6,$L$2,E6,$L$2,F6,$L$2,G6,$L$2,H6,$J$1) -> Skin-Tags-Removal-On-Armpit.html | K6: "> | L6: =PROPER(CONCATENATE(D6," ",E6," ",F6," ",G6," ",H6)) -> Skin Tags Removal On Armpit | M6: </a> <br /> | N6: =CONCATENATE(I6,J6,K6,L6,M6) -> <a target="_blank" href="skin_tag/Skin-Tags-Removal-On-Armpit.html">Skin Tags Removal On Armpit</a> <br />
C7: Breast | D7: Skin | E7: Tags | F7: Removal | G7: On | H7: Back | I7: <a target="_blank" href="skin_tag/ | J7: =CONCATENATE(D7,$L$2,E7,$L$2,F7,$L$2,G7,$L$2,H7,$J$1) -> Skin-Tags-Removal-On-Back.html | K7: "> | L7: =PROPER(CONCATENATE(D7," ",E7," ",F7," ",G7," ",H7)) -> Skin Tags Removal On Back | M7: </a> <br /> | N7: =CONCATENATE(I7,J7,K7,L7,M7) -> <a target="_blank" href="skin_tag/Skin-Tags-Removal-On-Back.html">Skin Tags Removal On Back</a> <br />
C8: Buttock | D8: Skin | E8: Tags | F8: Removal | G8: On | H8: Breast | I8: <a target="_blank" href="skin_tag/ | J8: =CONCATENATE(D8,$L$2,E8,$L$2,F8,$L$2,G8,$L$2,H8,$J$1) -> Skin-Tags-Removal-On-Breast.html | K8: "> | L8: =PROPER(CONCATENATE(D8," ",E8," ",F8," ",G8," ",H8)) -> Skin Tags Removal On Breast | M8: </a> <br /> | N8: =CONCATENATE(I8,J8,K8,L8,M8) -> <a target="_blank" href="skin_tag/Skin-Tags-Removal-On-Breast.html">Skin Tags Removal On Breast</a> <br />
C9: Chest | D9: Skin | E9: Tags | F9: Removal | G9: On | H9: Buttock | I9: <a target="_blank" href="skin_tag/ | J9: =CONCATENATE(D9,$L$2,E9,$L$2,F9,$L$2,G9,$L$2,H9,$J$1) -> Skin-Tags-Removal-On-Buttock.html | K9: "> | L9: =PROPER(CONCATENATE(D9," ",E9," ",F9," ",G9," ",H9)) -> Skin Tags Removal On Buttock | M9: </a> <br /> | N9: =CONCATENATE(I9,J9,K9,L9,M9) -> <a target="_blank" href="skin_tag/Skin-Tags-Removal-On-Buttock.html">Skin Tags Removal On Buttock</a> <br />
C10: Cheek | D10: Skin | E10: Tags | F10: Removal | G10: On | H10: Cheek | I10: <a target="_blank" href="skin_tag/ | J10: =CONCATENATE(D10,$L$2,E10,$L$2,F10,$L$2,G10,$L$2,H10,$J$1) -> Skin-Tags-Removal-On-Cheek.html | K10: "> | L10: =PROPER(CONCATENATE(D10," ",E10," ",F10," ",G10," ",H10)) -> Skin Tags Removal On Cheek | M10: </a> <br /> | N10: =CONCATENATE(I10,J10,K10,L10,M10) -> <a target="_blank" href="skin_tag/Skin-Tags-Removal-On-Cheek.html">Skin Tags Removal On Cheek</a> <br />
C11: Chin | D11: Skin | E11: Tags | F11: Removal | G11: On | H11: Chest | I11: <a target="_blank" href="skin_tag/ | J11: =CONCATENATE(D11,$L$2,E11,$L$2,F11,$L$2,G11,$L$2,H11,$J$1) -> Skin-Tags-Removal-On-Chest.html | K11: "> | L11: =PROPER(CONCATENATE(D11," ",E11," ",F11," ",G11," ",H11)) -> Skin Tags Removal On Chest | M11: </a> <br /> | N11: =CONCATENATE(I11,J11,K11,L11,M11) -> <a target="_blank" href="skin_tag/Skin-Tags-Removal-On-Chest.html">Skin Tags Removal On Chest</a> <br />
C12: Elbow | D12: Skin | E12: Tags | F12: Removal | G12: On | H12: Chin | I12: <a target="_blank" href="skin_tag/ | J12: =CONCATENATE(D12,$L$2,E12,$L$2,F12,$L$2,G12,$L$2,H12,$J$1) -> Skin-Tags-Removal-On-Chin.html | K12: "> | L12: =PROPER(CONCATENATE(D12," ",E12," ",F12," ",G12," ",H12)) -> Skin Tags Removal On Chin | M12: </a> <br /> | N12: =CONCATENATE(I12,J12,K12,L12,M12) -> <a target="_blank" href="skin_tag/Skin-Tags-Removal-On-Chin.html">Skin Tags Removal On Chin</a> <br />
C13: Hand | D13: Skin | E13: Tags | F13: Removal | G13: On | H13: Ear | I13: <a target="_blank" href="skin_tag/ | J13: =CONCATENATE(D13,$L$2,E13,$L$2,F13,$L$2,G13,$L$2,H13,$J$1) -> Skin-Tags-Removal-On-Ear.html | K13: "> | L13: =PROPER(CONCATENATE(D13," ",E13," ",F13," ",G13," ",H13)) -> Skin Tags Removal On Ear | M13: </a> <br /> | N13: =CONCATENATE(I13,J13,K13,L13,M13) -> <a target="_blank" href="skin_tag/Skin-Tags-Removal-On-Ear.html">Skin Tags Removal On Ear</a> <br />
C14: Navel | D14: Skin | E14: Tags | F14: Removal | G14: On | H14: Elbow | I14: <a target="_blank" href="skin_tag/ | J14: =CONCATENATE(D14,$L$2,E14,$L$2,F14,$L$2,G14,$L$2,H14,$J$1) -> Skin-Tags-Removal-On-Elbow.html | K14: "> | L14: =PROPER(CONCATENATE(D14," ",E14," ",F14," ",G14," ",H14)) -> Skin Tags Removal On Elbow | M14: </a> <br /> | N14: =CONCATENATE(I14,J14,K14,L14,M14) -> <a target="_blank" href="skin_tag/Skin-Tags-Removal-On-Elbow.html">Skin Tags Removal On Elbow</a> <br />
C15: Neck | D15: Skin | E15: Tags | F15: Removal | G15: On | H15: Eyebrow | I15: <a target="_blank" href="skin_tag/ | J15: =CONCATENATE(D15,$L$2,E15,$L$2,F15,$L$2,G15,$L$2,H15,$J$1) -> Skin-Tags-Removal-On-Eyebrow.html | K15: "> | L15: =PROPER(CONCATENATE(D15," ",E15," ",F15," ",G15," ",H15)) -> Skin Tags Removal On Eyebrow | M15: </a> <br /> | N15: =CONCATENATE(I15,J15,K15,L15,M15) -> <a target="_blank" href="skin_tag/Skin-Tags-Removal-On-Eyebrow.html">Skin Tags Removal On Eyebrow</a> <br />
... C26: Hips | D26: Skin | E26: Tags | F26: Removal | G26: On | H26: Thigh | I26: <a target="_blank" href="skin_tag/ | J26: =CONCATENATE(D26,$L$2,E26,$L$2,F26,$L$2,G26,$L$2,H26,$J$1) -> Skin-Tags-Removal-On-Thigh.html | K26: "> | L26: =PROPER(CONCATENATE(D26," ",E26," ",F26," ",G26," ",H26)) -> Skin Tags Removal On Thigh | M26: </a> <br /> | N26: =CONCATENATE(I26,J26,K26,L26,M26) -> <a target="_blank" href="skin_tag/Skin-Tags-Removal-On-Thigh.html">Skin Tags Removal On Thigh</a> <br />
D27: Skin | E27: Tags | F27: Treatment | G27: On | H27: Abdomen | I27: <a target="_blank" href="skin_tag/ | J27: =CONCATENATE(D27,$L$2,E27,$L$2,F27,$L$2,G27,$L$2,H27,$J$1) -> Skin-Tags-Treatment-On-Abdomen.html | K27: "> | L27: =PROPER(CONCATENATE(D27," ",E27," ",F27," ",G27," ",H27)) -> Skin Tags Treatment On Abdomen | M27: </a> <br /> | N27: =CONCATENATE(I27,J27,K27,L27,M27) -> <a target="_blank" href="skin_tag/Skin-Tags-Treatment-On-Abdomen.html">Skin Tags Treatment On Abdomen</a> <br />
D28: Skin | E28: Tags | F28: Treatment | G28: On | H28: Arm | I28: <a target="_blank" href="skin_tag/ | J28: =CONCATENATE(D28,$L$2,E28,$L$2,F28,$L$2,G28,$L$2,H28,$J$1) -> Skin-Tags-Treatment-On-Arm.html | K28: "> | L28: =PROPER(CONCATENATE(D28," ",E28," ",F28," ",G28," ",H28)) -> Skin Tags Treatment On Arm | M28: </a> <br /> | N28: =CONCATENATE(I28,J28,K28,L28,M28) -> <a target="_blank" href="skin_tag/Skin-Tags-Treatment-On-Arm.html">Skin Tags Treatment On Arm</a> <br />
D29: Skin | E29: Tags | F29: Treatment | G29: On | H29: Armpit | I29: <a target="_blank" href="skin_tag/ | J29: =CONCATENATE(D29,$L$2,E29,$L$2,F29,$L$2,G29,$L$2,H29,$J$1) -> Skin-Tags-Treatment-On-Armpit.html | K29: "> | L29: =PROPER(CONCATENATE(D29," ",E29," ",F29," ",G29," ",H29)) -> Skin Tags Treatment On Armpit | M29: </a> <br /> | N29: =CONCATENATE(I29,J29,K29,L29,M29) -> <a target="_blank" href="skin_tag/Skin-Tags-Treatment-On-Armpit.html">Skin Tags Treatment On Armpit</a> <br />
D30: Skin | E30: Tags | F30: Treatment | G30: On | H30: Back | I30: <a target="_blank" href="skin_tag/ | J30: =CONCATENATE(D30,$L$2,E30,$L$2,F30,$L$2,G30,$L$2,H30,$J$1) -> Skin-Tags-Treatment-On-Back.html | K30: "> | L30: =PROPER(CONCATENATE(D30," ",E30," ",F30," ",G30," ",H30)) -> Skin Tags Treatment On Back | M30: </a> <br /> | N30: =CONCATENATE(I30,J30,K30,L30,M30) -> <a target="_blank" href="skin_tag/Skin-Tags-Treatment-On-Back.html">Skin Tags Treatment On Back</a> <br />
D31: Skin | E31: Tags | F31: Treatment | G31: On | H31: Breast | I31: <a target="_blank" href="skin_tag/ | J31: =CONCATENATE(D31,$L$2,E31,$L$2,F31,$L$2,G31,$L$2,H31,$J$1) -> Skin-Tags-Treatment-On-Breast.html | K31: "> | L31: =PROPER(CONCATENATE(D31," ",E31," ",F31," ",G31," ",H31)) -> Skin Tags Treatment On Breast | M31: </a> <br /> | N31: =CONCATENATE(I31,J31,K31,L31,M31) -> <a target="_blank" href="skin_tag/Skin-Tags-Treatment-On-Breast.html">Skin Tags Treatment On Breast</a> <br />
D32: Skin | E32: Tags | F32: Treatment | G32: On | H32: Buttock | I32: <a target="_blank" href="skin_tag/ | J32: =CONCATENATE(D32,$L$2,E32,$L$2,F32,$L$2,G32,$L$2,H32,$J$1) -> Skin-Tags-Treatment-On-Buttock.html | K32: "> | L32: =PROPER(CONCATENATE(D32," ",E32," ",F32," ",G32," ",H32)) -> Skin Tags Treatment On Buttock | M32: </a> <br /> | N32: =CONCATENATE(I32,J32,K32,L32,M32) -> <a target="_blank" href="skin_tag/Skin-Tags-Treatment-On-Buttock.html">Skin Tags Treatment On Buttock</a> <br />
D33: Skin | E33: Tags | F33: Treatment | G33: On | H33: Cheek | I33: <a target="_blank" href="skin_tag/ | J33: =CONCATENATE(D33,$L$2,E33,$L$2,F33,$L$2,G33,$L$2,H33,$J$1) -> Skin-Tags-Treatment-On-Cheek.html | K33: "> | L33: =PROPER(CONCATENATE(D33," ",E33," ",F33," ",G33," ",H33)) -> Skin Tags Treatment On Cheek | M33: </a> <br /> | N33: =CONCATENATE(I33,J33,K33,L33,M33) -> <a target="_blank" href="skin_tag/Skin-Tags-Treatment-On-Cheek.html">Skin Tags Treatment On Cheek</a> <br />
D34: Skin | E34: Tags | F34: Treatment | G34: On | H34: Chest | I34: <a target="_blank" href="skin_tag/ | J34: =CONCATENATE(D34,$L$2,E34,$L$2,F34,$L$2,G34,$L$2,H34,$J$1) -> Skin-Tags-Treatment-On-Chest.html | K34: "> | L34: =PROPER(CONCATENATE(D34," ",E34," ",F34," ",G34," ",H34)) -> Skin Tags Treatment On Chest | M34: </a> <br /> | N34: =CONCATENATE(I34,J34,K34,L34,M34) -> <a target="_blank" href="skin_tag/Skin-Tags-Treatment-On-Chest.html">Skin Tags Treatment On Chest</a> <br />
D35: Skin | E35: Tags | F35: Treatment | G35: On | H35: Chin | I35: <a target="_blank" href="skin_tag/ | J35: =CONCATENATE(D35,$L$2,E35,$L$2,F35,$L$2,G35,$L$2,H35,$J$1) -> Skin-Tags-Treatment-On-Chin.html | K35: "> | L35: =PROPER(CONCATENATE(D35," ",E35," ",F35," ",G35," ",H35)) -> Skin Tags Treatment On Chin | M35: </a> <br /> | N35: =CONCATENATE(I35,J35,K35,L35,M35) -> <a target="_blank" href="skin_tag/Skin-Tags-Treatment-On-Chin.html">Skin Tags Treatment On Chin</a> <br />
D36: Skin | E36: Tags | F36: Treatment | G36: On | H36: Ear | I36: <a target="_blank" href="skin_tag/ | J36: =CONCATENATE(D36,$L$2,E36,$L$2,F36,$L$2,G36,$L$2,H36,$J$1) -> Skin-Tags-Treatment-On-Ear.html | K36: "> | L36: =PROPER(CONCATENATE(D36," ",E36," ",F36," ",G36," ",H36)) -> Skin Tags Treatment On Ear | M36: </a> <br /> | N36: =CONCATENATE(I36,J36,K36,L36,M36) -> <a target="_blank" href="skin_tag/Skin-Tags-Treatment-On-Ear.html">Skin Tags Treatment On Ear</a> <br />
D37: Skin | E37: Tags | F37: Treatment | G37: On | H37: Elbow | I37: <a target="_blank" href="skin_tag/ | J37: =CONCATENATE(D37,$L$2,E37,$L$2,F37,$L$2,G37,$L$2,H37,$J$1) -> Skin-Tags-Treatment-On-Elbow.html | K37: "> | L37: =PROPER(CONCATENATE(D37," ",E37," ",F37," ",G37," ",H37)) -> Skin Tags Treatment On Elbow | M37: </a> <br /> | N37: =CONCATENATE(I37,J37,K37,L37,M37) -> <a target="_blank" href="skin_tag/Skin-Tags-Treatment-On-Elbow.html">Skin Tags Treatment On Elbow</a> <br />
D38: Skin | E38: Tags | F38: Treatment | G38: On | H38: Eyebrow | I38: <a target="_blank" href="skin_tag/ | J38: =CONCATENATE(D38,$L$2,E38,$L$2,F38,$L$2,G38,$L$2,H38,$J$1) -> Skin-Tags-Treatment-On-Eyebrow.html | K38: "> | L38: =PROPER(CONCATENATE(D38," ",E38," ",F38," ",G38," ",H38)) -> Skin Tags Treatment On Eyebrow | M38: </a> <br /> | N38: =CONCATENATE(I38,J38,K38,L38,M38) -> <a target="_blank" href="skin_tag/Skin-Tags-Treatment-On-Eyebrow.html">Skin Tags Treatment On Eyebrow</a> <br />
... D95: Thigh | E95: Laser | F95: Skin | G95: Tags | H95: Treatment | I95: <a target="_blank" href="skin_tag/ | J95: =CONCATENATE(D95,$L$2,E95,$L$2,F95,$L$2,G95,$L$2,H95,$J$1) -> Thigh-Laser-Skin-Tags-Treatment.html | K95: "> | L95: =PROPER(CONCATENATE(D95," ",E95," ",F95," ",G95," ",H95)) -> Thigh Laser Skin Tags Treatment | M95: </a> <br /> | N95: =CONCATENATE(I95,J95,K95,L95,M95) -> <a target="_blank" href="skin_tag/Thigh-Laser-Skin-Tags-Treatment.html">Thigh Laser Skin Tags Treatment</a> <br />
A96: With Free Consultation | B96: -With-Free-Consultation | D96: Abdomen | E96: Laser | F96: Skin | G96: Tags | H96: Removal | I96: <a target="_blank" href="skin_tag/ | J96: =CONCATENATE(D96,$L$2,E96,$L$2,F96,$L$2,G96,$L$2,H96,B96,$J$1) -> Abdomen-Laser-Skin-Tags-Removal-With-Free-Consultation.html | K96: "> | L96: =PROPER(CONCATENATE(D96," ",E96," ",F96," ",G96," ",H96)) -> Abdomen Laser Skin Tags Removal | M96: </a> <br /> | N96: =CONCATENATE(I96,J96,K96,L96," ",A96,M96) -> <a target="_blank" href="skin_tag/Abdomen-Laser-Skin-Tags-Removal-With-Free-Consultation.html">Abdomen Laser Skin Tags Removal With Free Consultation</a> <br />
A97: With Free Consultation | B97: -With-Free-Consultation | D97: Arm | E97: Laser | F97: Skin | G97: Tags | H97: Removal | I97: <a target="_blank" href="skin_tag/ | J97: =CONCATENATE(D97,$L$2,E97,$L$2,F97,$L$2,G97,$L$2,H97,B97,$J$1) -> Arm-Laser-Skin-Tags-Removal-With-Free-Consultation.html | K97: "> | L97: =PROPER(CONCATENATE(D97," ",E97," ",F97," ",G97," ",H97)) -> Arm Laser Skin Tags Removal | M97: </a> <br /> | N97: =CONCATENATE(I97,J97,K97,L97," ",A97,M97) -> <a target="_blank" href="skin_tag/Arm-Laser-Skin-Tags-Removal-With-Free-Consultation.html">Arm Laser Skin Tags Removal With Free Consultation</a> <br />
A98: With Free Consultation | B98: -With-Free-Consultation | D98: Armpit | E98: Laser | F98: Skin | G98: Tags | H98: Removal | I98: <a target="_blank" href="skin_tag/ | J98: =CONCATENATE(D98,$L$2,E98,$L$2,F98,$L$2,G98,$L$2,H98,B98,$J$1) -> Armpit-Laser-Skin-Tags-Removal-With-Free-Consultation.html | K98: "> | L98: =PROPER(CONCATENATE(D98," ",E98," ",F98," ",G98," ",H98)) -> Armpit Laser Skin Tags Removal | M98: </a> <br /> | N98: =CONCATENATE(I98,J98,K98,L98," ",A98,M98) -> <a target="_blank" href="skin_tag/Armpit-Laser-Skin-Tags-Removal-With-Free-Consultation.html">Armpit Laser Skin Tags Removal With Free Consultation</a> <br />
A99: With Free Consultation | B99: -With-Free-Consultation | D99: Back | E99: Laser | F99: Skin | G99: Tags | H99: Removal | I99: <a target="_blank" href="skin_tag/ | J99: =CONCATENATE(D99,$L$2,E99,$L$2,F99,$L$2,G99,$L$2,H99,B99,$J$1) -> Back-Laser-Skin-Tags-Removal-With-Free-Consultation.html | K99: "> | L99: =PROPER(CONCATENATE(D99," ",E99," ",F99," ",G99," ",H99)) -> Back Laser Skin Tags Removal | M99: </a> <br /> | N99: =CONCATENATE(I99,J99,K99,L99," ",A99,M99) -> <a target="_blank" href="skin_tag/Back-Laser-Skin-Tags-Removal-With-Free-Consultation.html">Back Laser Skin Tags Removal With Free Consultation</a> <br />
A100: With Free Consultation | B100: -With-Free-Consultation | D100: Breast | E100: Laser | F100: Skin | G100: Tags | H100: Removal | I100: <a target="_blank" href="skin_tag/ | J100: =CONCATENATE(D100,$L$2,E100,$L$2,F100,$L$2,G100,$L$2,H100,B100,$J$1) -> Breast-Laser-Skin-Tags-Removal-With-Free-Consultation.html | K100: "> | L100: =PROPER(CONCATENATE(D100," ",E100," ",F100," ",G100," ",H100)) -> Breast Laser Skin Tags Removal | M100: </a> <br /> | N100: =CONCATENATE(I100,J100,K100,L100," ",A100,M100) -> <a target="_blank" href="skin_tag/Breast-Laser-Skin-Tags-Removal-With-Free-Consultation.html">Breast Laser Skin Tags Removal With Free Consultation</a> <br />
A101: With Free Consultation | B101: -With-Free-Consultation | D101: Buttock | E101: Laser | F101: Skin | G101: Tags | H101: Removal | I101: <a target="_blank" href="skin_tag/ | J101: =CONCATENATE(D101,$L$2,E101,$L$2,F101,$L$2,G101,$L$2,H101,B101,$J$1) -> Buttock-Laser-Skin-Tags-Removal-With-Free-Consultation.html | K101: "> | L101: =PROPER(CONCATENATE(D101," ",E101," ",F101," ",G101," ",H101)) -> Buttock Laser Skin Tags Removal | M101: </a> <br /> | N101: =CONCATENATE(I101,J101,K101,L101," ",A101,M101) -> <a target="_blank" href="skin_tag/Buttock-Laser-Skin-Tags-Removal-With-Free-Consultation.html">Buttock Laser Skin Tags Removal With Free Consultation</a> <br />
A102: With Free Consultation | B102: -With-Free-Consultation | D102: Cheek | E102: Laser | F102: Skin | G102: Tags | H102: Removal | I102: <a target="_blank" href="skin_tag/ | J102: =CONCATENATE(D102,$L$2,E102,$L$2,F102,$L$2,G102,$L$2,H102,B102,$J$1) -> Cheek-Laser-Skin-Tags-Removal-With-Free-Consultation.html | K102: "> | L102: =PROPER(CONCATENATE(D102," ",E102," ",F102," ",G102," ",H102)) -> Cheek Laser Skin Tags Removal | M102: </a> <br /> | N102: =CONCATENATE(I102,J102,K102,L102," ",A102,M102) -> <a target="_blank" href="skin_tag/Cheek-Laser-Skin-Tags-Removal-With-Free-Consultation.html">Cheek Laser Skin Tags Removal With Free Consultation</a> <br />
A103: With Free Consultation | B103: -With-Free-Consultation | D103: Chest | E103: Laser | F103: Skin | G103: Tags | H103: Removal | I103: <a target="_blank" href="skin_tag/ | J103: =CONCATENATE(D103,$L$2,E103,$L$2,F103,$L$2,G103,$L$2,H103,B103,$J$1) -> Chest-Laser-Skin-Tags-Removal-With-Free-Consultation.html | K103: "> | L103: =PROPER(CONCATENATE(D103," ",E103," ",F103," ",G103," ",H103)) -> Chest Laser Skin Tags Removal | M103: </a> <br /> | N103: =CONCATENATE(I103,J103,K103,L103," ",A103,M103) -> <a target="_blank" href="skin_tag/Chest-Laser-Skin-Tags-Removal-With-Free-Consultation.html">Chest Laser Skin Tags Removal With Free Consultation</a> <br />
A104: With Free Consultation | B104: -With-Free-Consultation | D104: Chin | E104: Laser | F104: Skin | G104: Tags | H104: Removal | I104: <a target="_blank" href="skin_tag/ | J104: =CONCATENATE(D104,$L$2,E104,$L$2,F104,$L$2,G104,$L$2,H104,B104,$J$1) -> Chin-Laser-Skin-Tags-Removal-With-Free-Consultation.html | K104: "> | L104: =PROPER(CONCATENATE(D104," ",E104," ",F104," ",G104," ",H104)) -> Chin Laser Skin Tags Removal | M104: </a> <br /> | N104: =CONCATENATE(I104,J104,K104,L104," ",A104,M104) -> <a target="_blank" href="skin_tag/Chin-Laser-Skin-Tags-Removal-With-Free-Consultation.html">Chin Laser Skin Tags Removal With Free Consultation</a> <br />
A105: With Free Consultation | B105: -With-Free-Consultation | D105: Ear | E105: Laser | F105: Skin | G105: Tags | H105: Removal | I105: <a target="_blank" href="skin_tag/ | J105: =CONCATENATE(D105,$L$2,E105,$L$2,F105,$L$2,G105,$L$2,H105,B105,$J$1) -> Ear-Laser-Skin-Tags-Removal-With-Free-Consultation.html | K105: "> | L105: =PROPER(CONCATENATE(D105," ",E105," ",F105," ",G105," ",H105)) -> Ear Laser Skin Tags Removal | M105: </a> <br /> | N105: =CONCATENATE(I105,J105,K105,L105," ",A105,M105) -> <a target="_blank" href="skin_tag/Ear-Laser-Skin-Tags-Removal-With-Free-Consultation.html">Ear Laser Skin Tags Removal With Free Consultation</a> <br />
A106: With Free Consultation | B106: -With-Free-Consultation | D106: Elbow | E106: Laser | F106: Skin | G106: Tags | H106: Removal | I106: <a target="_blank" href="skin_tag/ | J106: =CONCATENATE(D106,$L$2,E106,$L$2,F106,$L$2,G106,$L$2,H106,B106,$J$1) -> Elbow-Laser-Skin-Tags-Removal-With-Free-Consultation.html | K106: "> | L106: =PROPER(CONCATENATE(D106," ",E106," ",F106," ",G106," ",H106)) -> Elbow Laser Skin Tags Removal | M106: </a> <br /> | N106: =CONCATENATE(I106,J106,K106,L106," ",A106,M106) -> <a target="_blank" href="skin_tag/Elbow-Laser-Skin-Tags-Removal-With-Free-Consultation.html">Elbow Laser Skin Tags Removal With Free Consultation</a> <br />
A107: With Free Consultation | B107: -With-Free-Consultation | D107: Eyebrow | E107: Laser | F107: Skin | G107: Tags | H107: Removal | I107: <a target="_blank" href="skin_tag/ | J107: =CONCATENATE(D107,$L$2,E107,$L$2,F107,$L$2,G107,$L$2,H107,B107,$J$1) -> Eyebrow-Laser-Skin-Tags-Removal-With-Free-Consultation.html | K107: "> | L107: =PROPER(CONCATENATE(D107," ",E107," ",F107," ",G107," ",H107)) -> Eyebrow Laser Skin Tags Removal | M107: </a> <br /> | N107: =CONCATENATE(I107,J107,K107,L107," ",A107,M107) -> <a target="_blank" href="skin_tag/Eyebrow-Laser-Skin-Tags-Removal-With-Free-Consultation.html">Eyebrow Laser Skin Tags Removal With Free Consultation</a> <br />
... A141: With Free Consultation | B141: -With-Free-Consultation | D141: Thigh | E141: Laser | F141: Skin | G141: Tags | H141: Treatment | I141: <a target="_blank" href="skin_tag/ | J141: =CONCATENATE(D141,$L$2,E141,$L$2,F141,$L$2,G141,$L$2,H141,B141,$J$1) -> Thigh-Laser-Skin-Tags-Treatment-With-Free-Consultation.html | K141: "> | L141: =PROPER(CONCATENATE(D141," ",E141," ",F141," ",G141," ",H141)) -> Thigh Laser Skin Tags Treatment | M141: </a> <br /> | N141: =CONCATENATE(I141,J141,K141,L141," ",A141,M141) -> <a target="_blank" href="skin_tag/Thigh-Laser-Skin-Tags-Treatment-With-Free-Consultation.html">Thigh Laser Skin Tags Treatment With Free Consultation</a> <br />

Sheet Removal Lesion
L1: blank
A2: XML Meta Tags | L2: - | M2: =LEN(L2) -> 1
C3: Body Parts | D3: Iron Welding Works
C4: Abdomen | D4: Lesion | E4: Removal | F4: On | G4: Abdomen | I4: <a target="_blank" href="dubai.php?uae= | J4: =CONCATENATE(D4,$L$2,E4,$L$2,F4,$L$2,G4,H4) -> Lesion-Removal-On-Abdomen | K4: "> | L4: =PROPER(CONCATENATE(D4," ",E4," ",F4," ",G4," ",H4)) -> Lesion Removal On Abdomen | M4: </a> <br /> | N4: =CONCATENATE(I4,J4,K4,L4,M4) -> <a target="_blank" href="dubai.php?uae=Lesion-Removal-On-Abdomen">Lesion Removal On Abdomen </a> <br />
C5: Areola | D5: Lesion | E5: Removal | F5: On | G5: Arm | I5: <a target="_blank" href="dubai.php?uae= | J5: =CONCATENATE(D5,$L$2,E5,$L$2,F5,$L$2,G5,H5) -> Lesion-Removal-On-Arm | K5: "> | L5: =PROPER(CONCATENATE(D5," ",E5," ",F5," ",G5," ",H5)) -> Lesion Removal On Arm | M5: </a> <br /> | N5: =CONCATENATE(I5,J5,K5,L5,M5) -> <a target="_blank" href="dubai.php?uae=Lesion-Removal-On-Arm">Lesion Removal On Arm </a> <br />
C6: Arm | D6: Lesion | E6: Removal | F6: On | G6: Armpit | I6: <a target="_blank" href="dubai.php?uae= | J6: =CONCATENATE(D6,$L$2,E6,$L$2,F6,$L$2,G6,H6) -> Lesion-Removal-On-Armpit | K6: "> | L6: =PROPER(CONCATENATE(D6," ",E6," ",F6," ",G6," ",H6)) -> Lesion Removal On Armpit | M6: </a> <br /> | N6: =CONCATENATE(I6,J6,K6,L6,M6) -> <a target="_blank" href="dubai.php?uae=Lesion-Removal-On-Armpit">Lesion Removal On Armpit </a> <br />
C7: Armpit | D7: Lesion | E7: Removal | F7: On | G7: Back | I7: <a target="_blank" href="dubai.php?uae= | J7: =CONCATENATE(D7,$L$2,E7,$L$2,F7,$L$2,G7,H7) -> Lesion-Removal-On-Back | K7: "> | L7: =PROPER(CONCATENATE(D7," ",E7," ",F7," ",G7," ",H7)) -> Lesion Removal On Back | M7: </a> <br /> | N7: =CONCATENATE(I7,J7,K7,L7,M7) -> <a target="_blank" href="dubai.php?uae=Lesion-Removal-On-Back">Lesion Removal On Back </a> <br />
C8: Back | D8: Lesion | E8: Removal | F8: On | G8: Breast | I8: <a target="_blank" href="dubai.php?uae= | J8: =CONCATENATE(D8,$L$2,E8,$L$2,F8,$L$2,G8,H8) -> Lesion-Removal-On-Breast | K8: "> | L8: =PROPER(CONCATENATE(D8," ",E8," ",F8," ",G8," ",H8)) -> Lesion Removal On Breast | M8: </a> <br /> | N8: =CONCATENATE(I8,J8,K8,L8,M8) -> <a target="_blank" href="dubai.php?uae=Lesion-Removal-On-Breast">Lesion Removal On Breast </a> <br />
C9: Back-Neck | D9: Lesion | E9: Removal | F9: On | G9: Buttock | I9: <a target="_blank" href="dubai.php?uae= | J9: =CONCATENATE(D9,$L$2,E9,$L$2,F9,$L$2,G9,H9) -> Lesion-Removal-On-Buttock | K9: "> | L9: =PROPER(CONCATENATE(D9," ",E9," ",F9," ",G9," ",H9)) -> Lesion Removal On Buttock | M9: </a> <br /> | N9: =CONCATENATE(I9,J9,K9,L9,M9) -> <a target="_blank" href="dubai.php?uae=Lesion-Removal-On-Buttock">Lesion Removal On Buttock </a> <br />
C10: Basic-Bikini | D10: Lesion | E10: Removal | F10: On | G10: Cheek | I10: <a target="_blank" href="dubai.php?uae= | J10: =CONCATENATE(D10,$L$2,E10,$L$2,F10,$L$2,G10,H10) -> Lesion-Removal-On-Cheek | K10: "> | L10: =PROPER(CONCATENATE(D10," ",E10," ",F10," ",G10," ",H10)) -> Lesion Removal On Cheek | M10: </a> <br /> | N10: =CONCATENATE(I10,J10,K10,L10,M10) -> <a target="_blank" href="dubai.php?uae=Lesion-Removal-On-Cheek">Lesion Removal On Cheek </a> <br />
C11: Beard-Line | D11: Lesion | E11: Removal | F11: On | G11: Chest | I11: <a target="_blank" href="dubai.php?uae= | J11: =CONCATENATE(D11,$L$2,E11,$L$2,F11,$L$2,G11,H11) -> Lesion-Removal-On-Chest | K11: "> | L11: =PROPER(CONCATENATE(D11," ",E11," ",F11," ",G11," ",H11)) -> Lesion Removal On Chest | M11: </a> <br /> | N11: =CONCATENATE(I11,J11,K11,L11,M11) -> <a target="_blank" href="dubai.php?uae=Lesion-Removal-On-Chest">Lesion Removal On Chest </a> <br />
C12: Bikini | D12: Lesion | E12: Removal | F12: On | G12: Chin | I12: <a target="_blank" href="dubai.php?uae= | J12: =CONCATENATE(D12,$L$2,E12,$L$2,F12,$L$2,G12,H12) -> Lesion-Removal-On-Chin | K12: "> | L12: =PROPER(CONCATENATE(D12," ",E12," ",F12," ",G12," ",H12)) -> Lesion Removal On Chin | M12: </a> <br /> | N12: =CONCATENATE(I12,J12,K12,L12,M12) -> <a target="_blank" href="dubai.php?uae=Lesion-Removal-On-Chin">Lesion Removal On Chin </a> <br />
C13: Brazilian | D13: Lesion | E13: Removal | F13: On | G13: Ear | I13: <a target="_blank" href="dubai.php?uae= | J13: =CONCATENATE(D13,$L$2,E13,$L$2,F13,$L$2,G13,H13) -> Lesion-Removal-On-Ear | K13: "> | L13: =PROPER(CONCATENATE(D13," ",E13," ",F13," ",G13," ",H13)) -> Lesion Removal On Ear | M13: </a> <br /> | N13: =CONCATENATE(I13,J13,K13,L13,M13) -> <a target="_blank" href="dubai.php?uae=Lesion-Removal-On-Ear">Lesion Removal On Ear </a> <br />
C14: Breast | D14: Lesion | E14: Removal | F14: On | G14: Elbow | I14: <a target="_blank" href="dubai.php?uae= | J14: =CONCATENATE(D14,$L$2,E14,$L$2,F14,$L$2,G14,H14) -> Lesion-Removal-On-Elbow | K14: "> | L14: =PROPER(CONCATENATE(D14," ",E14," ",F14," ",G14," ",H14)) -> Lesion Removal On Elbow | M14: </a> <br /> | N14: =CONCATENATE(I14,J14,K14,L14,M14) -> <a target="_blank" href="dubai.php?uae=Lesion-Removal-On-Elbow">Lesion Removal On Elbow </a> <br />
C15: Buttock | D15: Lesion | E15: Removal | F15: On | G15: Eyebrow | I15: <a target="_blank" href="dubai.php?uae= | J15: =CONCATENATE(D15,$L$2,E15,$L$2,F15,$L$2,G15,H15) -> Lesion-Removal-On-Eyebrow | K15: "> | L15: =PROPER(CONCATENATE(D15," ",E15," ",F15," ",G15," ",H15)) -> Lesion Removal On Eyebrow | M15: </a> <br /> | N15: =CONCATENATE(I15,J15,K15,L15,M15) -> <a target="_blank" href="dubai.php?uae=Lesion-Removal-On-Eyebrow">Lesion Removal On Eyebrow </a> <br />
... C52: Upper-Lip | D52: Armpit | E52: Laser | F52: Lesion | G52: Removal | I52: <a target="_blank" href="dubai.php?uae= | J52: =CONCATENATE(D52,$L$2,E52,$L$2,F52,$L$2,G52,H52) -> Armpit-Laser-Lesion-Removal | K52: "> | L52: =PROPER(CONCATENATE(D52," ",E52," ",F52," ",G52," ",H52)) -> Armpit Laser Lesion Removal | M52: </a> <br /> | N52: =CONCATENATE(I52,J52,K52,L52,M52) -> <a target="_blank" href="dubai.php?uae=Armpit-Laser-Lesion-Removal">Armpit Laser Lesion Removal </a> <br />
D53: Back | E53: Laser | F53: Lesion | G53: Removal | I53: <a target="_blank" href="dubai.php?uae= | J53: =CONCATENATE(D53,$L$2,E53,$L$2,F53,$L$2,G53,H53) -> Back-Laser-Lesion-Removal | K53: "> | L53: =PROPER(CONCATENATE(D53," ",E53," ",F53," ",G53," ",H53)) -> Back Laser Lesion Removal | M53: </a> <br /> | N53: =CONCATENATE(I53,J53,K53,L53,M53) -> <a target="_blank" href="dubai.php?uae=Back-Laser-Lesion-Removal">Back Laser Lesion Removal </a> <br />
D54: Breast | E54: Laser | F54: Lesion | G54: Removal | I54: <a target="_blank" href="dubai.php?uae= | J54: =CONCATENATE(D54,$L$2,E54,$L$2,F54,$L$2,G54,H54) -> Breast-Laser-Lesion-Removal | K54: "> | L54: =PROPER(CONCATENATE(D54," ",E54," ",F54," ",G54," ",H54)) -> Breast Laser Lesion Removal | M54: </a> <br /> | N54: =CONCATENATE(I54,J54,K54,L54,M54) -> <a target="_blank" href="dubai.php?uae=Breast-Laser-Lesion-Removal">Breast Laser Lesion Removal </a> <br />
D55: Buttock | E55: Laser | F55: Lesion | G55: Removal | I55: <a target="_blank" href="dubai.php?uae= | J55: =CONCATENATE(D55,$L$2,E55,$L$2,F55,$L$2,G55,H55) -> Buttock-Laser-Lesion-Removal | K55: "> | L55: =PROPER(CONCATENATE(D55," ",E55," ",F55," ",G55," ",H55)) -> Buttock Laser Lesion Removal | M55: </a> <br /> | N55: =CONCATENATE(I55,J55,K55,L55,M55) -> <a target="_blank" href="dubai.php?uae=Buttock-Laser-Lesion-Removal">Buttock Laser Lesion Removal </a> <br />
D56: Cheek | E56: Laser | F56: Lesion | G56: Removal | I56: <a target="_blank" href="dubai.php?uae= | J56: =CONCATENATE(D56,$L$2,E56,$L$2,F56,$L$2,G56,H56) -> Cheek-Laser-Lesion-Removal | K56: "> | L56: =PROPER(CONCATENATE(D56," ",E56," ",F56," ",G56," ",H56)) -> Cheek Laser Lesion Removal | M56: </a> <br /> | N56: =CONCATENATE(I56,J56,K56,L56,M56) -> <a target="_blank" href="dubai.php?uae=Cheek-Laser-Lesion-Removal">Cheek Laser Lesion Removal </a> <br />
D57: Chest | E57: Laser | F57: Lesion | G57: Removal | I57: <a target="_blank" href="dubai.php?uae= | J57: =CONCATENATE(D57,$L$2,E57,$L$2,F57,$L$2,G57,H57) -> Chest-Laser-Lesion-Removal | K57: "> | L57: =PROPER(CONCATENATE(D57," ",E57," ",F57," ",G57," ",H57)) -> Chest Laser Lesion Removal | M57: </a> <br /> | N57: =CONCATENATE(I57,J57,K57,L57,M57) -> <a target="_blank" href="dubai.php?uae=Chest-Laser-Lesion-Removal">Chest Laser Lesion Removal </a> <br />
D58: Chin | E58: Laser | F58: Lesion | G58: Removal | I58: <a target="_blank" href="dubai.php?uae= | J58: =CONCATENATE(D58,$L$2,E58,$L$2,F58,$L$2,G58,H58) -> Chin-Laser-Lesion-Removal | K58: "> | L58: =PROPER(CONCATENATE(D58," ",E58," ",F58," ",G58," ",H58)) -> Chin Laser Lesion Removal | M58: </a> <br /> | N58: =CONCATENATE(I58,J58,K58,L58,M58) -> <a target="_blank" href="dubai.php?uae=Chin-Laser-Lesion-Removal">Chin Laser Lesion Removal </a> <br />
D59: Ear | E59: Laser | F59: Lesion | G59: Removal | I59: <a target="_blank" href="dubai.php?uae= | J59: =CONCATENATE(D59,$L$2,E59,$L$2,F59,$L$2,G59,H59) -> Ear-Laser-Lesion-Removal | K59: "> | L59: =PROPER(CONCATENATE(D59," ",E59," ",F59," ",G59," ",H59)) -> Ear Laser Lesion Removal | M59: </a> <br /> | N59: =CONCATENATE(I59,J59,K59,L59,M59) -> <a target="_blank" href="dubai.php?uae=Ear-Laser-Lesion-Removal">Ear Laser Lesion Removal </a> <br />
D60: Elbow | E60: Laser | F60: Lesion | G60: Removal | I60: <a target="_blank" href="dubai.php?uae= | J60: =CONCATENATE(D60,$L$2,E60,$L$2,F60,$L$2,G60,H60) -> Elbow-Laser-Lesion-Removal | K60: "> | L60: =PROPER(CONCATENATE(D60," ",E60," ",F60," ",G60," ",H60)) -> Elbow Laser Lesion Removal | M60: </a> <br /> | N60: =CONCATENATE(I60,J60,K60,L60,M60) -> <a target="_blank" href="dubai.php?uae=Elbow-Laser-Lesion-Removal">Elbow Laser Lesion Removal </a> <br />
D61: Eyebrow | E61: Laser | F61: Lesion | G61: Removal | I61: <a target="_blank" href="dubai.php?uae= | J61: =CONCATENATE(D61,$L$2,E61,$L$2,F61,$L$2,G61,H61) -> Eyebrow-Laser-Lesion-Removal | K61: "> | L61: =PROPER(CONCATENATE(D61," ",E61," ",F61," ",G61," ",H61)) -> Eyebrow Laser Lesion Removal | M61: </a> <br /> | N61: =CONCATENATE(I61,J61,K61,L61,M61) -> <a target="_blank" href="dubai.php?uae=Eyebrow-Laser-Lesion-Removal">Eyebrow Laser Lesion Removal </a> <br />
D62: Face | E62: Laser | F62: Lesion | G62: Removal | I62: <a target="_blank" href="dubai.php?uae= | J62: =CONCATENATE(D62,$L$2,E62,$L$2,F62,$L$2,G62,H62) -> Face-Laser-Lesion-Removal | K62: "> | L62: =PROPER(CONCATENATE(D62," ",E62," ",F62," ",G62," ",H62)) -> Face Laser Lesion Removal | M62: </a> <br /> | N62: =CONCATENATE(I62,J62,K62,L62,M62) -> <a target="_blank" href="dubai.php?uae=Face-Laser-Lesion-Removal">Face Laser Lesion Removal </a> <br />
D63: Forehead | E63: Laser | F63: Lesion | G63: Removal | I63: <a target="_blank" href="dubai.php?uae= | J63: =CONCATENATE(D63,$L$2,E63,$L$2,F63,$L$2,G63,H63) -> Forehead-Laser-Lesion-Removal | K63: "> | L63: =PROPER(CONCATENATE(D63," ",E63," ",F63," ",G63," ",H63)) -> Forehead Laser Lesion Removal | M63: </a> <br /> | N63: =CONCATENATE(I63,J63,K63,L63,M63) -> <a target="_blank" href="dubai.php?uae=Forehead-Laser-Lesion-Removal">Forehead Laser Lesion Removal </a> <br />
D64: Hand | E64: Laser | F64: Lesion | G64: Removal | I64: <a target="_blank" href="dubai.php?uae= | J64: =CONCATENATE(D64,$L$2,E64,$L$2,F64,$L$2,G64,H64) -> Hand-Laser-Lesion-Removal | K64: "> | L64: =PROPER(CONCATENATE(D64," ",E64," ",F64," ",G64," ",H64)) -> Hand Laser Lesion Removal | M64: </a> <br /> | N64: =CONCATENATE(I64,J64,K64,L64,M64) -> <a target="_blank" href="dubai.php?uae=Hand-Laser-Lesion-Removal">Hand Laser Lesion Removal </a> <br />
... D95: Thigh | E95: Laser | F95: Lesion | G95: Treatment | I95: <a target="_blank" href="dubai.php?uae= | J95: =CONCATENATE(D95,$L$2,E95,$L$2,F95,$L$2,G95,H95) -> Thigh-Laser-Lesion-Treatment | K95: "> | L95: =PROPER(CONCATENATE(D95," ",E95," ",F95," ",G95," ",H95)) -> Thigh Laser Lesion Treatment | M95: </a> <br /> | N95: =CONCATENATE(I95,J95,K95,L95,M95) -> <a target="_blank" href="dubai.php?uae=Thigh-Laser-Lesion-Treatment">Thigh Laser Lesion Treatment </a> <br />

Sheet Laser Hair Removal 
O1: blank
O2: - | P2: =LEN(O2) -> 1
F3: Iron Welding Works
A4: ='Laser Price'!E5 -> 160 | B4: AED | F4: Laser | G4: Hair | H4: Removal | I4: For | J4: Abdomen | L4: <a target="_blank" href="laser.php?permanent= | M4: =CONCATENATE(F4,$O$2,G4,$O$2,H4,$O$2,I4,$O$2,J4) -> Laser-Hair-Removal-For-Abdomen | N4: "> | O4: =PROPER(CONCATENATE(F4," ",G4," ",H4," ",I4," ",J4)) -> Laser Hair Removal For Abdomen | P4: </a> <br /> | Q4: =CONCATENATE(L4,M4,N4,O4,P4) -> <a target="_blank" href="laser.php?permanent=Laser-Hair-Removal-For-Abdomen">Laser Hair Removal For Abdomen</a> <br />
A5: ='Laser Price'!E6 -> 160 | B5: AED | F5: Laser | G5: Hair | H5: Removal | I5: For | J5: Areola | L5: <a target="_blank" href="laser.php?permanent= | M5: =CONCATENATE(F5,$O$2,G5,$O$2,H5,$O$2,I5,$O$2,J5) -> Laser-Hair-Removal-For-Areola | N5: "> | O5: =PROPER(CONCATENATE(F5," ",G5," ",H5," ",I5," ",J5)) -> Laser Hair Removal For Areola | P5: </a> <br /> | Q5: =CONCATENATE(L5,M5,N5,O5,P5) -> <a target="_blank" href="laser.php?permanent=Laser-Hair-Removal-For-Areola">Laser Hair Removal For Areola</a> <br />
A6: ='Laser Price'!E7 -> 320 | B6: AED | F6: Laser | G6: Hair | H6: Removal | I6: For | J6: Arm | L6: <a target="_blank" href="laser.php?permanent= | M6: =CONCATENATE(F6,$O$2,G6,$O$2,H6,$O$2,I6,$O$2,J6) -> Laser-Hair-Removal-For-Arm | N6: "> | O6: =PROPER(CONCATENATE(F6," ",G6," ",H6," ",I6," ",J6)) -> Laser Hair Removal For Arm | P6: </a> <br /> | Q6: =CONCATENATE(L6,M6,N6,O6,P6) -> <a target="_blank" href="laser.php?permanent=Laser-Hair-Removal-For-Arm">Laser Hair Removal For Arm</a> <br />
A7: ='Laser Price'!E8 -> 200 | B7: AED | F7: Laser | G7: Hair | H7: Removal | I7: For | J7: Armpit | L7: <a target="_blank" href="laser.php?permanent= | M7: =CONCATENATE(F7,$O$2,G7,$O$2,H7,$O$2,I7,$O$2,J7) -> Laser-Hair-Removal-For-Armpit | N7: "> | O7: =PROPER(CONCATENATE(F7," ",G7," ",H7," ",I7," ",J7)) -> Laser Hair Removal For Armpit | P7: </a> <br /> | Q7: =CONCATENATE(L7,M7,N7,O7,P7) -> <a target="_blank" href="laser.php?permanent=Laser-Hair-Removal-For-Armpit">Laser Hair Removal For Armpit</a> <br />
A8: ='Laser Price'!E9 -> 400 | B8: AED | F8: Laser | G8: Hair | H8: Removal | I8: For | J8: Back | L8: <a target="_blank" href="laser.php?permanent= | M8: =CONCATENATE(F8,$O$2,G8,$O$2,H8,$O$2,I8,$O$2,J8) -> Laser-Hair-Removal-For-Back | N8: "> | O8: =PROPER(CONCATENATE(F8," ",G8," ",H8," ",I8," ",J8)) -> Laser Hair Removal For Back | P8: </a> <br /> | Q8: =CONCATENATE(L8,M8,N8,O8,P8) -> <a target="_blank" href="laser.php?permanent=Laser-Hair-Removal-For-Back">Laser Hair Removal For Back</a> <br />
A9: ='Laser Price'!E10 -> 128 | B9: AED | F9: Laser | G9: Hair | H9: Removal | I9: For | J9: Back-Neck | L9: <a target="_blank" href="laser.php?permanent= | M9: =CONCATENATE(F9,$O$2,G9,$O$2,H9,$O$2,I9,$O$2,J9) -> Laser-Hair-Removal-For-Back-Neck | N9: "> | O9: =PROPER(CONCATENATE(F9," ",G9," ",H9," ",I9," ",J9)) -> Laser Hair Removal For Back-Neck | P9: </a> <br /> | Q9: =CONCATENATE(L9,M9,N9,O9,P9) -> <a target="_blank" href="laser.php?permanent=Laser-Hair-Removal-For-Back-Neck">Laser Hair Removal For Back-Neck</a> <br />
A10: ='Laser Price'!E11 -> 160 | B10: AED | F10: Laser | G10: Hair | H10: Removal | I10: For | J10: Basic-Bikini | L10: <a target="_blank" href="laser.php?permanent= | M10: =CONCATENATE(F10,$O$2,G10,$O$2,H10,$O$2,I10,$O$2,J10) -> Laser-Hair-Removal-For-Basic-Bikini | N10: "> | O10: =PROPER(CONCATENATE(F10," ",G10," ",H10," ",I10," ",J10)) -> Laser Hair Removal For Basic-Bikini | P10: </a> <br /> | Q10: =CONCATENATE(L10,M10,N10,O10,P10) -> <a target="_blank" href="laser.php?permanent=Laser-Hair-Removal-For-Basic-Bikini">Laser Hair Removal For Basic-Bikini</a> <br />
A11: ='Laser Price'!E12 -> 80 | B11: AED | F11: Laser | G11: Hair | H11: Removal | I11: For | J11: Beard-Line | L11: <a target="_blank" href="laser.php?permanent= | M11: =CONCATENATE(F11,$O$2,G11,$O$2,H11,$O$2,I11,$O$2,J11) -> Laser-Hair-Removal-For-Beard-Line | N11: "> | O11: =PROPER(CONCATENATE(F11," ",G11," ",H11," ",I11," ",J11)) -> Laser Hair Removal For Beard-Line | P11: </a> <br /> | Q11: =CONCATENATE(L11,M11,N11,O11,P11) -> <a target="_blank" href="laser.php?permanent=Laser-Hair-Removal-For-Beard-Line">Laser Hair Removal For Beard-Line</a> <br />
A12: ='Laser Price'!E14 -> 160 | B12: AED | F12: Laser | G12: Hair | H12: Removal | I12: For | J12: Bikini | L12: <a target="_blank" href="laser.php?permanent= | M12: =CONCATENATE(F12,$O$2,G12,$O$2,H12,$O$2,I12,$O$2,J12) -> Laser-Hair-Removal-For-Bikini | N12: "> | O12: =PROPER(CONCATENATE(F12," ",G12," ",H12," ",I12," ",J12)) -> Laser Hair Removal For Bikini | P12: </a> <br /> | Q12: =CONCATENATE(L12,M12,N12,O12,P12) -> <a target="_blank" href="laser.php?permanent=Laser-Hair-Removal-For-Bikini">Laser Hair Removal For Bikini</a> <br />
A13: ='Laser Price'!E15 -> 160 | B13: AED | F13: Laser | G13: Hair | H13: Removal | I13: For | J13: Brazilian | L13: <a target="_blank" href="laser.php?permanent= | M13: =CONCATENATE(F13,$O$2,G13,$O$2,H13,$O$2,I13,$O$2,J13) -> Laser-Hair-Removal-For-Brazilian | N13: "> | O13: =PROPER(CONCATENATE(F13," ",G13," ",H13," ",I13," ",J13)) -> Laser Hair Removal For Brazilian | P13: </a> <br /> | Q13: =CONCATENATE(L13,M13,N13,O13,P13) -> <a target="_blank" href="laser.php?permanent=Laser-Hair-Removal-For-Brazilian">Laser Hair Removal For Brazilian</a> <br />
A14: ='Laser Price'!E16 -> 400 | B14: AED | F14: Laser | G14: Hair | H14: Removal | I14: For | J14: Breast | L14: <a target="_blank" href="laser.php?permanent= | M14: =CONCATENATE(F14,$O$2,G14,$O$2,H14,$O$2,I14,$O$2,J14) -> Laser-Hair-Removal-For-Breast | N14: "> | O14: =PROPER(CONCATENATE(F14," ",G14," ",H14," ",I14," ",J14)) -> Laser Hair Removal For Breast | P14: </a> <br /> | Q14: =CONCATENATE(L14,M14,N14,O14,P14) -> <a target="_blank" href="laser.php?permanent=Laser-Hair-Removal-For-Breast">Laser Hair Removal For Breast</a> <br />
A15: ='Laser Price'!E17 -> 400 | B15: AED | F15: Laser | G15: Hair | H15: Removal | I15: For | J15: Buttock | L15: <a target="_blank" href="laser.php?permanent= | M15: =CONCATENATE(F15,$O$2,G15,$O$2,H15,$O$2,I15,$O$2,J15) -> Laser-Hair-Removal-For-Buttock | N15: "> | O15: =PROPER(CONCATENATE(F15," ",G15," ",H15," ",I15," ",J15)) -> Laser Hair Removal For Buttock | P15: </a> <br /> | Q15: =CONCATENATE(L15,M15,N15,O15,P15) -> <a target="_blank" href="laser.php?permanent=Laser-Hair-Removal-For-Buttock">Laser Hair Removal For Buttock</a> <br />
A16: ='Laser Price'!E18 -> 120 | B16: AED | F16: Laser | G16: Hair | H16: Removal | I16: For | J16: Cheek | L16: <a target="_blank" href="laser.php?permanent= | M16: =CONCATENATE(F16,$O$2,G16,$O$2,H16,$O$2,I16,$O$2,J16) -> Laser-Hair-Removal-For-Cheek | N16: "> | O16: =PROPER(CONCATENATE(F16," ",G16," ",H16," ",I16," ",J16)) -> Laser Hair Removal For Cheek | P16: </a> <br /> | Q16: =CONCATENATE(L16,M16,N16,O16,P16) -> <a target="_blank" href="laser.php?permanent=Laser-Hair-Removal-For-Cheek">Laser Hair Removal For Cheek</a> <br />
A17: ='Laser Price'!E19 -> 400 | B17: AED | F17: Laser | G17: Hair | H17: Removal | I17: For | J17: Chest | L17: <a target="_blank" href="laser.php?permanent= | M17: =CONCATENATE(F17,$O$2,G17,$O$2,H17,$O$2,I17,$O$2,J17) -> Laser-Hair-Removal-For-Chest | N17: "> | O17: =PROPER(CONCATENATE(F17," ",G17," ",H17," ",I17," ",J17)) -> Laser Hair Removal For Chest | P17: </a> <br /> | Q17: =CONCATENATE(L17,M17,N17,O17,P17) -> <a target="_blank" href="laser.php?permanent=Laser-Hair-Removal-For-Chest">Laser Hair Removal For Chest</a> <br />
A18: ='Laser Price'!E20 -> 40 | B18: AED | F18: Laser | G18: Hair | H18: Removal | I18: For | J18: Chin | L18: <a target="_blank" href="laser.php?permanent= | M18: =CONCATENATE(F18,$O$2,G18,$O$2,H18,$O$2,I18,$O$2,J18) -> Laser-Hair-Removal-For-Chin | N18: "> | O18: =PROPER(CONCATENATE(F18," ",G18," ",H18," ",I18," ",J18)) -> Laser Hair Removal For Chin | P18: </a> <br /> | Q18: =CONCATENATE(L18,M18,N18,O18,P18) -> <a target="_blank" href="laser.php?permanent=Laser-Hair-Removal-For-Chin">Laser Hair Removal For Chin</a> <br />
A19: ='Laser Price'!E21 -> 40 | B19: AED | F19: Laser | G19: Hair | H19: Removal | I19: For | J19: Ear | L19: <a target="_blank" href="laser.php?permanent= | M19: =CONCATENATE(F19,$O$2,G19,$O$2,H19,$O$2,I19,$O$2,J19) -> Laser-Hair-Removal-For-Ear | N19: "> | O19: =PROPER(CONCATENATE(F19," ",G19," ",H19," ",I19," ",J19)) -> Laser Hair Removal For Ear | P19: </a> <br /> | Q19: =CONCATENATE(L19,M19,N19,O19,P19) -> <a target="_blank" href="laser.php?permanent=Laser-Hair-Removal-For-Ear">Laser Hair Removal For Ear</a> <br />
A20: ='Laser Price'!E22 -> 160 | B20: AED | F20: Laser | G20: Hair | H20: Removal | I20: For | J20: Elbow | L20: <a target="_blank" href="laser.php?permanent= | M20: =CONCATENATE(F20,$O$2,G20,$O$2,H20,$O$2,I20,$O$2,J20) -> Laser-Hair-Removal-For-Elbow | N20: "> | O20: =PROPER(CONCATENATE(F20," ",G20," ",H20," ",I20," ",J20)) -> Laser Hair Removal For Elbow | P20: </a> <br /> | Q20: =CONCATENATE(L20,M20,N20,O20,P20) -> <a target="_blank" href="laser.php?permanent=Laser-Hair-Removal-For-Elbow">Laser Hair Removal For Elbow</a> <br />
A21: ='Laser Price'!E23 -> 120 | B21: AED | F21: Laser | G21: Hair | H21: Removal | I21: For | J21: Eyebrow | L21: <a target="_blank" href="laser.php?permanent= | M21: =CONCATENATE(F21,$O$2,G21,$O$2,H21,$O$2,I21,$O$2,J21) -> Laser-Hair-Removal-For-Eyebrow | N21: "> | O21: =PROPER(CONCATENATE(F21," ",G21," ",H21," ",I21," ",J21)) -> Laser Hair Removal For Eyebrow | P21: </a> <br /> | Q21: =CONCATENATE(L21,M21,N21,O21,P21) -> <a target="_blank" href="laser.php?permanent=Laser-Hair-Removal-For-Eyebrow">Laser Hair Removal For Eyebrow</a> <br />
A22: ='Laser Price'!E24 -> 80 | B22: AED | F22: Laser | G22: Hair | H22: Removal | I22: For | J22: Face | L22: <a target="_blank" href="laser.php?permanent= | M22: =CONCATENATE(F22,$O$2,G22,$O$2,H22,$O$2,I22,$O$2,J22) -> Laser-Hair-Removal-For-Face | N22: "> | O22: =PROPER(CONCATENATE(F22," ",G22," ",H22," ",I22," ",J22)) -> Laser Hair Removal For Face | P22: </a> <br /> | Q22: =CONCATENATE(L22,M22,N22,O22,P22) -> <a target="_blank" href="laser.php?permanent=Laser-Hair-Removal-For-Face">Laser Hair Removal For Face</a> <br />
A23: ='Laser Price'!E25 -> 80 | B23: AED | F23: Laser | G23: Hair | H23: Removal | I23: For | J23: Feet | L23: <a target="_blank" href="laser.php?permanent= | M23: =CONCATENATE(F23,$O$2,G23,$O$2,H23,$O$2,I23,$O$2,J23) -> Laser-Hair-Removal-For-Feet | N23: "> | O23: =PROPER(CONCATENATE(F23," ",G23," ",H23," ",I23," ",J23)) -> Laser Hair Removal For Feet | P23: </a> <br /> | Q23: =CONCATENATE(L23,M23,N23,O23,P23) -> <a target="_blank" href="laser.php?permanent=Laser-Hair-Removal-For-Feet">Laser Hair Removal For Feet</a> <br />
... A52: ='Laser Price'!E54 -> 40 | B52: AED | F52: Laser | G52: Hair | H52: Removal | I52: For | J52: Upper-Lip | L52: <a target="_blank" href="laser.php?permanent= | M52: =CONCATENATE(F52,$O$2,G52,$O$2,H52,$O$2,I52,$O$2,J52) -> Laser-Hair-Removal-For-Upper-Lip | N52: "> | O52: =PROPER(CONCATENATE(F52," ",G52," ",H52," ",I52," ",J52)) -> Laser Hair Removal For Upper-Lip | P52: </a> <br /> | Q52: =CONCATENATE(L52,M52,N52,O52,P52) -> <a target="_blank" href="laser.php?permanent=Laser-Hair-Removal-For-Upper-Lip">Laser Hair Removal For Upper-Lip</a> <br />
A53: 160 | B53: AED | F53: Men | G53: Laser | H53: Hair | I53: Removal | J53: Abdomen | L53: <a target="_blank" href="laser.php?permanent= | M53: =CONCATENATE(F53,$O$2,G53,$O$2,H53,$O$2,I53,$O$2,J53) -> Men-Laser-Hair-Removal-Abdomen | N53: "> | O53: =PROPER(CONCATENATE(F53," ",G53," ",H53," ",I53," ",J53)) -> Men Laser Hair Removal Abdomen | P53: </a> <br /> | Q53: =CONCATENATE(L53,M53,N53,O53,P53) -> <a target="_blank" href="laser.php?permanent=Men-Laser-Hair-Removal-Abdomen">Men Laser Hair Removal Abdomen</a> <br />
A54: 160 | B54: AED | F54: Men | G54: Laser | H54: Hair | I54: Removal | J54: Areola | L54: <a target="_blank" href="laser.php?permanent= | M54: =CONCATENATE(F54,$O$2,G54,$O$2,H54,$O$2,I54,$O$2,J54) -> Men-Laser-Hair-Removal-Areola | N54: "> | O54: =PROPER(CONCATENATE(F54," ",G54," ",H54," ",I54," ",J54)) -> Men Laser Hair Removal Areola | P54: </a> <br /> | Q54: =CONCATENATE(L54,M54,N54,O54,P54) -> <a target="_blank" href="laser.php?permanent=Men-Laser-Hair-Removal-Areola">Men Laser Hair Removal Areola</a> <br />
A55: 320 | B55: AED | F55: Men | G55: Laser | H55: Hair | I55: Removal | J55: Arm | L55: <a target="_blank" href="laser.php?permanent= | M55: =CONCATENATE(F55,$O$2,G55,$O$2,H55,$O$2,I55,$O$2,J55) -> Men-Laser-Hair-Removal-Arm | N55: "> | O55: =PROPER(CONCATENATE(F55," ",G55," ",H55," ",I55," ",J55)) -> Men Laser Hair Removal Arm | P55: </a> <br /> | Q55: =CONCATENATE(L55,M55,N55,O55,P55) -> <a target="_blank" href="laser.php?permanent=Men-Laser-Hair-Removal-Arm">Men Laser Hair Removal Arm</a> <br />
A56: 200 | B56: AED | F56: Men | G56: Laser | H56: Hair | I56: Removal | J56: Armpit | L56: <a target="_blank" href="laser.php?permanent= | M56: =CONCATENATE(F56,$O$2,G56,$O$2,H56,$O$2,I56,$O$2,J56) -> Men-Laser-Hair-Removal-Armpit | N56: "> | O56: =PROPER(CONCATENATE(F56," ",G56," ",H56," ",I56," ",J56)) -> Men Laser Hair Removal Armpit | P56: </a> <br /> | Q56: =CONCATENATE(L56,M56,N56,O56,P56) -> <a target="_blank" href="laser.php?permanent=Men-Laser-Hair-Removal-Armpit">Men Laser Hair Removal Armpit</a> <br />
A57: 400 | B57: AED | F57: Men | G57: Laser | H57: Hair | I57: Removal | J57: Back | L57: <a target="_blank" href="laser.php?permanent= | M57: =CONCATENATE(F57,$O$2,G57,$O$2,H57,$O$2,I57,$O$2,J57) -> Men-Laser-Hair-Removal-Back | N57: "> | O57: =PROPER(CONCATENATE(F57," ",G57," ",H57," ",I57," ",J57)) -> Men Laser Hair Removal Back | P57: </a> <br /> | Q57: =CONCATENATE(L57,M57,N57,O57,P57) -> <a target="_blank" href="laser.php?permanent=Men-Laser-Hair-Removal-Back">Men Laser Hair Removal Back</a> <br />
A58: 128 | B58: AED | F58: Men | G58: Laser | H58: Hair | I58: Removal | J58: Back-Neck | L58: <a target="_blank" href="laser.php?permanent= | M58: =CONCATENATE(F58,$O$2,G58,$O$2,H58,$O$2,I58,$O$2,J58) -> Men-Laser-Hair-Removal-Back-Neck | N58: "> | O58: =PROPER(CONCATENATE(F58," ",G58," ",H58," ",I58," ",J58)) -> Men Laser Hair Removal Back-Neck | P58: </a> <br /> | Q58: =CONCATENATE(L58,M58,N58,O58,P58) -> <a target="_blank" href="laser.php?permanent=Men-Laser-Hair-Removal-Back-Neck">Men Laser Hair Removal Back-Neck</a> <br />
A59: 160 | B59: AED | F59: Men | G59: Laser | H59: Hair | I59: Removal | J59: Basic-Bikini | L59: <a target="_blank" href="laser.php?permanent= | M59: =CONCATENATE(F59,$O$2,G59,$O$2,H59,$O$2,I59,$O$2,J59) -> Men-Laser-Hair-Removal-Basic-Bikini | N59: "> | O59: =PROPER(CONCATENATE(F59," ",G59," ",H59," ",I59," ",J59)) -> Men Laser Hair Removal Basic-Bikini | P59: </a> <br /> | Q59: =CONCATENATE(L59,M59,N59,O59,P59) -> <a target="_blank" href="laser.php?permanent=Men-Laser-Hair-Removal-Basic-Bikini">Men Laser Hair Removal Basic-Bikini</a> <br />
A60: 120 | B60: AED | F60: Men | G60: Laser | H60: Hair | I60: Removal | J60: Beard-Line | L60: <a target="_blank" href="laser.php?permanent= | M60: =CONCATENATE(F60,$O$2,G60,$O$2,H60,$O$2,I60,$O$2,J60) -> Men-Laser-Hair-Removal-Beard-Line | N60: "> | O60: =PROPER(CONCATENATE(F60," ",G60," ",H60," ",I60," ",J60)) -> Men Laser Hair Removal Beard-Line | P60: </a> <br /> | Q60: =CONCATENATE(L60,M60,N60,O60,P60) -> <a target="_blank" href="laser.php?permanent=Men-Laser-Hair-Removal-Beard-Line">Men Laser Hair Removal Beard-Line</a> <br />
A61: 160 | B61: AED | F61: Men | G61: Laser | H61: Hair | I61: Removal | J61: Bikini | L61: <a target="_blank" href="laser.php?permanent= | M61: =CONCATENATE(F61,$O$2,G61,$O$2,H61,$O$2,I61,$O$2,J61) -> Men-Laser-Hair-Removal-Bikini | N61: "> | O61: =PROPER(CONCATENATE(F61," ",G61," ",H61," ",I61," ",J61)) -> Men Laser Hair Removal Bikini | P61: </a> <br /> | Q61: =CONCATENATE(L61,M61,N61,O61,P61) -> <a target="_blank" href="laser.php?permanent=Men-Laser-Hair-Removal-Bikini">Men Laser Hair Removal Bikini</a> <br />
A62: 160 | B62: AED | F62: Men | G62: Laser | H62: Hair | I62: Removal | J62: Brazilian | L62: <a target="_blank" href="laser.php?permanent= | M62: =CONCATENATE(F62,$O$2,G62,$O$2,H62,$O$2,I62,$O$2,J62) -> Men-Laser-Hair-Removal-Brazilian | N62: "> | O62: =PROPER(CONCATENATE(F62," ",G62," ",H62," ",I62," ",J62)) -> Men Laser Hair Removal Brazilian | P62: </a> <br /> | Q62: =CONCATENATE(L62,M62,N62,O62,P62) -> <a target="_blank" href="laser.php?permanent=Men-Laser-Hair-Removal-Brazilian">Men Laser Hair Removal Brazilian</a> <br />
A63: 400 | B63: AED | F63: Men | G63: Laser | H63: Hair | I63: Removal | J63: Breast | L63: <a target="_blank" href="laser.php?permanent= | M63: =CONCATENATE(F63,$O$2,G63,$O$2,H63,$O$2,I63,$O$2,J63) -> Men-Laser-Hair-Removal-Breast | N63: "> | O63: =PROPER(CONCATENATE(F63," ",G63," ",H63," ",I63," ",J63)) -> Men Laser Hair Removal Breast | P63: </a> <br /> | Q63: =CONCATENATE(L63,M63,N63,O63,P63) -> <a target="_blank" href="laser.php?permanent=Men-Laser-Hair-Removal-Breast">Men Laser Hair Removal Breast</a> <br />
A64: 400 | B64: AED | F64: Men | G64: Laser | H64: Hair | I64: Removal | J64: Buttock | L64: <a target="_blank" href="laser.php?permanent= | M64: =CONCATENATE(F64,$O$2,G64,$O$2,H64,$O$2,I64,$O$2,J64) -> Men-Laser-Hair-Removal-Buttock | N64: "> | O64: =PROPER(CONCATENATE(F64," ",G64," ",H64," ",I64," ",J64)) -> Men Laser Hair Removal Buttock | P64: </a> <br /> | Q64: =CONCATENATE(L64,M64,N64,O64,P64) -> <a target="_blank" href="laser.php?permanent=Men-Laser-Hair-Removal-Buttock">Men Laser Hair Removal Buttock</a> <br />
... A150: 40 | B150: AED | F150: Upper-Lip | G150: Permanent | H150: Laser | I150: Hair | J150: Removal | L150: <a target="_blank" href="laser.php?permanent= | M150: =CONCATENATE(F150,$O$2,G150,$O$2,H150,$O$2,I150,$O$2,J150) -> Upper-Lip-Permanent-Laser-Hair-Removal | N150: "> | O150: =PROPER(CONCATENATE(F150," ",G150," ",H150," ",I150," ",J150)) -> Upper-Lip Permanent Laser Hair Removal | P150: </a> <br /> | Q150: =CONCATENATE(L150,M150,N150,O150,P150) -> <a target="_blank" href="laser.php?permanent=Upper-Lip-Permanent-Laser-Hair-Removal">Upper-Lip Permanent Laser Hair Removal</a> <br />
A151: 160 | B151: AED | C151: Price | D151: =CONCATENATE($O$2,B151,$O$2,A151) -> -AED-160 | F151: Abdomen | G151: Laser | H151: Hair | I151: Removal | J151: =CONCATENATE(C151,D151) -> Price-AED-160 | L151: <a target="_blank" href="laser.php?permanent= | M151: =CONCATENATE(F151,$O$2,G151,$O$2,H151,$O$2,I151,$O$2,J151) -> Abdomen-Laser-Hair-Removal-Price-AED-160 | N151: "> | O151: =PROPER(CONCATENATE(F151," ",G151," ",H151," ",I151," ",J151)) -> Abdomen Laser Hair Removal Price-Aed-160 | P151: </a> <br /> | Q151: =CONCATENATE(L151,M151,N151,O151,P151) -> <a target="_blank" href="laser.php?permanent=Abdomen-Laser-Hair-Removal-Price-AED-160">Abdomen Laser Hair Removal Price-Aed-160</a> <br />
A152: 160 | B152: AED | C152: Price | D152: =CONCATENATE($O$2,B152,$O$2,A152) -> -AED-160 | F152: Areola | G152: Laser | H152: Hair | I152: Removal | J152: =CONCATENATE(C152,D152) -> Price-AED-160 | L152: <a target="_blank" href="laser.php?permanent= | M152: =CONCATENATE(F152,$O$2,G152,$O$2,H152,$O$2,I152,$O$2,J152) -> Areola-Laser-Hair-Removal-Price-AED-160 | N152: "> | O152: =PROPER(CONCATENATE(F152," ",G152," ",H152," ",I152," ",J152)) -> Areola Laser Hair Removal Price-Aed-160 | P152: </a> <br /> | Q152: =CONCATENATE(L152,M152,N152,O152,P152) -> <a target="_blank" href="laser.php?permanent=Areola-Laser-Hair-Removal-Price-AED-160">Areola Laser Hair Removal Price-Aed-160</a> <br />
A153: 320 | B153: AED | C153: Price | D153: =CONCATENATE($O$2,B153,$O$2,A153) -> -AED-320 | F153: Arm | G153: Laser | H153: Hair | I153: Removal | J153: =CONCATENATE(C153,D153) -> Price-AED-320 | L153: <a target="_blank" href="laser.php?permanent= | M153: =CONCATENATE(F153,$O$2,G153,$O$2,H153,$O$2,I153,$O$2,J153) -> Arm-Laser-Hair-Removal-Price-AED-320 | N153: "> | O153: =PROPER(CONCATENATE(F153," ",G153," ",H153," ",I153," ",J153)) -> Arm Laser Hair Removal Price-Aed-320 | P153: </a> <br /> | Q153: =CONCATENATE(L153,M153,N153,O153,P153) -> <a target="_blank" href="laser.php?permanent=Arm-Laser-Hair-Removal-Price-AED-320">Arm Laser Hair Removal Price-Aed-320</a> <br />
A154: 200 | B154: AED | C154: Price | D154: =CONCATENATE($O$2,B154,$O$2,A154) -> -AED-200 | F154: Armpit | G154: Laser | H154: Hair | I154: Removal | J154: =CONCATENATE(C154,D154) -> Price-AED-200 | L154: <a target="_blank" href="laser.php?permanent= | M154: =CONCATENATE(F154,$O$2,G154,$O$2,H154,$O$2,I154,$O$2,J154) -> Armpit-Laser-Hair-Removal-Price-AED-200 | N154: "> | O154: =PROPER(CONCATENATE(F154," ",G154," ",H154," ",I154," ",J154)) -> Armpit Laser Hair Removal Price-Aed-200 | P154: </a> <br /> | Q154: =CONCATENATE(L154,M154,N154,O154,P154) -> <a target="_blank" href="laser.php?permanent=Armpit-Laser-Hair-Removal-Price-AED-200">Armpit Laser Hair Removal Price-Aed-200</a> <br />
A155: 400 | B155: AED | C155: Price | D155: =CONCATENATE($O$2,B155,$O$2,A155) -> -AED-400 | F155: Back | G155: Laser | H155: Hair | I155: Removal | J155: =CONCATENATE(C155,D155) -> Price-AED-400 | L155: <a target="_blank" href="laser.php?permanent= | M155: =CONCATENATE(F155,$O$2,G155,$O$2,H155,$O$2,I155,$O$2,J155) -> Back-Laser-Hair-Removal-Price-AED-400 | N155: "> | O155: =PROPER(CONCATENATE(F155," ",G155," ",H155," ",I155," ",J155)) -> Back Laser Hair Removal Price-Aed-400 | P155: </a> <br /> | Q155: =CONCATENATE(L155,M155,N155,O155,P155) -> <a target="_blank" href="laser.php?permanent=Back-Laser-Hair-Removal-Price-AED-400">Back Laser Hair Removal Price-Aed-400</a> <br />
A156: 128 | B156: AED | C156: Price | D156: =CONCATENATE($O$2,B156,$O$2,A156) -> -AED-128 | F156: Back-Neck | G156: Laser | H156: Hair | I156: Removal | J156: =CONCATENATE(C156,D156) -> Price-AED-128 | L156: <a target="_blank" href="laser.php?permanent= | M156: =CONCATENATE(F156,$O$2,G156,$O$2,H156,$O$2,I156,$O$2,J156) -> Back-Neck-Laser-Hair-Removal-Price-AED-128 | N156: "> | O156: =PROPER(CONCATENATE(F156," ",G156," ",H156," ",I156," ",J156)) -> Back-Neck Laser Hair Removal Price-Aed-128 | P156: </a> <br /> | Q156: =CONCATENATE(L156,M156,N156,O156,P156) -> <a target="_blank" href="laser.php?permanent=Back-Neck-Laser-Hair-Removal-Price-AED-128">Back-Neck Laser Hair Removal Price-Aed-128</a> <br />
A157: 160 | B157: AED | C157: Price | D157: =CONCATENATE($O$2,B157,$O$2,A157) -> -AED-160 | F157: Basic-Bikini | G157: Laser | H157: Hair | I157: Removal | J157: =CONCATENATE(C157,D157) -> Price-AED-160 | L157: <a target="_blank" href="laser.php?permanent= | M157: =CONCATENATE(F157,$O$2,G157,$O$2,H157,$O$2,I157,$O$2,J157) -> Basic-Bikini-Laser-Hair-Removal-Price-AED-160 | N157: "> | O157: =PROPER(CONCATENATE(F157," ",G157," ",H157," ",I157," ",J157)) -> Basic-Bikini Laser Hair Removal Price-Aed-160 | P157: </a> <br /> | Q157: =CONCATENATE(L157,M157,N157,O157,P157) -> <a target="_blank" href="laser.php?permanent=Basic-Bikini-Laser-Hair-Removal-Price-AED-160">Basic-Bikini Laser Hair Removal Price-Aed-160</a> <br />
A158: 120 | B158: AED | C158: Price | D158: =CONCATENATE($O$2,B158,$O$2,A158) -> -AED-120 | F158: Beard-Line | G158: Laser | H158: Hair | I158: Removal | J158: =CONCATENATE(C158,D158) -> Price-AED-120 | L158: <a target="_blank" href="laser.php?permanent= | M158: =CONCATENATE(F158,$O$2,G158,$O$2,H158,$O$2,I158,$O$2,J158) -> Beard-Line-Laser-Hair-Removal-Price-AED-120 | N158: "> | O158: =PROPER(CONCATENATE(F158," ",G158," ",H158," ",I158," ",J158)) -> Beard-Line Laser Hair Removal Price-Aed-120 | P158: </a> <br /> | Q158: =CONCATENATE(L158,M158,N158,O158,P158) -> <a target="_blank" href="laser.php?permanent=Beard-Line-Laser-Hair-Removal-Price-AED-120">Beard-Line Laser Hair Removal Price-Aed-120</a> <br />
A159: 160 | B159: AED | C159: Price | D159: =CONCATENATE($O$2,B159,$O$2,A159) -> -AED-160 | F159: Bikini | G159: Laser | H159: Hair | I159: Removal | J159: =CONCATENATE(C159,D159) -> Price-AED-160 | L159: <a target="_blank" href="laser.php?permanent= | M159: =CONCATENATE(F159,$O$2,G159,$O$2,H159,$O$2,I159,$O$2,J159) -> Bikini-Laser-Hair-Removal-Price-AED-160 | N159: "> | O159: =PROPER(CONCATENATE(F159," ",G159," ",H159," ",I159," ",J159)) -> Bikini Laser Hair Removal Price-Aed-160 | P159: </a> <br /> | Q159: =CONCATENATE(L159,M159,N159,O159,P159) -> <a target="_blank" href="laser.php?permanent=Bikini-Laser-Hair-Removal-Price-AED-160">Bikini Laser Hair Removal Price-Aed-160</a> <br />
A160: 160 | B160: AED | C160: Price | D160: =CONCATENATE($O$2,B160,$O$2,A160) -> -AED-160 | F160: Brazilian | G160: Laser | H160: Hair | I160: Removal | J160: =CONCATENATE(C160,D160) -> Price-AED-160 | L160: <a target="_blank" href="laser.php?permanent= | M160: =CONCATENATE(F160,$O$2,G160,$O$2,H160,$O$2,I160,$O$2,J160) -> Brazilian-Laser-Hair-Removal-Price-AED-160 | N160: "> | O160: =PROPER(CONCATENATE(F160," ",G160," ",H160," ",I160," ",J160)) -> Brazilian Laser Hair Removal Price-Aed-160 | P160: </a> <br /> | Q160: =CONCATENATE(L160,M160,N160,O160,P160) -> <a target="_blank" href="laser.php?permanent=Brazilian-Laser-Hair-Removal-Price-AED-160">Brazilian Laser Hair Removal Price-Aed-160</a> <br />
A161: 400 | B161: AED | C161: Price | D161: =CONCATENATE($O$2,B161,$O$2,A161) -> -AED-400 | F161: Breast | G161: Laser | H161: Hair | I161: Removal | J161: =CONCATENATE(C161,D161) -> Price-AED-400 | L161: <a target="_blank" href="laser.php?permanent= | M161: =CONCATENATE(F161,$O$2,G161,$O$2,H161,$O$2,I161,$O$2,J161) -> Breast-Laser-Hair-Removal-Price-AED-400 | N161: "> | O161: =PROPER(CONCATENATE(F161," ",G161," ",H161," ",I161," ",J161)) -> Breast Laser Hair Removal Price-Aed-400 | P161: </a> <br /> | Q161: =CONCATENATE(L161,M161,N161,O161,P161) -> <a target="_blank" href="laser.php?permanent=Breast-Laser-Hair-Removal-Price-AED-400">Breast Laser Hair Removal Price-Aed-400</a> <br />
A162: 400 | B162: AED | C162: Price | D162: =CONCATENATE($O$2,B162,$O$2,A162) -> -AED-400 | F162: Buttock | G162: Laser | H162: Hair | I162: Removal | J162: =CONCATENATE(C162,D162) -> Price-AED-400 | L162: <a target="_blank" href="laser.php?permanent= | M162: =CONCATENATE(F162,$O$2,G162,$O$2,H162,$O$2,I162,$O$2,J162) -> Buttock-Laser-Hair-Removal-Price-AED-400 | N162: "> | O162: =PROPER(CONCATENATE(F162," ",G162," ",H162," ",I162," ",J162)) -> Buttock Laser Hair Removal Price-Aed-400 | P162: </a> <br /> | Q162: =CONCATENATE(L162,M162,N162,O162,P162) -> <a target="_blank" href="laser.php?permanent=Buttock-Laser-Hair-Removal-Price-AED-400">Buttock Laser Hair Removal Price-Aed-400</a> <br />
... A248: 40 | B248: AED | C248: Package | D248: =CONCATENATE($O$2,B248,$O$2,A248) -> -AED-40 | F248: Upper-Lip | G248: Laser | H248: Hair | I248: Removal | J248: =CONCATENATE(C248,D248) -> Package-AED-40 | L248: <a target="_blank" href="laser.php?permanent= | M248: =CONCATENATE(F248,$O$2,G248,$O$2,H248,$O$2,I248,$O$2,J248) -> Upper-Lip-Laser-Hair-Removal-Package-AED-40 | N248: "> | O248: =PROPER(CONCATENATE(F248," ",G248," ",H248," ",I248," ",J248)) -> Upper-Lip Laser Hair Removal Package-Aed-40 | P248: </a> <br /> | Q248: =CONCATENATE(L248,M248,N248,O248,P248) -> <a target="_blank" href="laser.php?permanent=Upper-Lip-Laser-Hair-Removal-Package-AED-40">Upper-Lip Laser Hair Removal Package-Aed-40</a> <br />
A249: Dubai-Silicon-Oasis | B249: From | D249: =CONCATENATE(B249,$O$2,A249) -> From-Dubai-Silicon-Oasis | F249: Abdomen | G249: Laser | H249: Hair | I249: Removal | J249: =CONCATENATE(C249,D249) -> From-Dubai-Silicon-Oasis | L249: <a target="_blank" href="laser.php?permanent= | M249: =CONCATENATE(F249,$O$2,G249,$O$2,H249,$O$2,I249,$O$2,J249) -> Abdomen-Laser-Hair-Removal-From-Dubai-Silicon-Oasis | N249: "> | O249: =PROPER(CONCATENATE(F249," ",G249," ",H249," ",I249," ",J249)) -> Abdomen Laser Hair Removal From-Dubai-Silicon-Oasis | P249: </a> <br /> | Q249: =CONCATENATE(L249,M249,N249,O249,P249) -> <a target="_blank" href="laser.php?permanent=Abdomen-Laser-Hair-Removal-From-Dubai-Silicon-Oasis">Abdomen Laser Hair Removal From-Dubai-Silicon-Oasis</a> <br />
A250: Dubai-Academic-City | B250: From | D250: =CONCATENATE(B250,$O$2,A250) -> From-Dubai-Academic-City | F250: Areola | G250: Laser | H250: Hair | I250: Removal | J250: =CONCATENATE(C250,D250) -> From-Dubai-Academic-City | L250: <a target="_blank" href="laser.php?permanent= | M250: =CONCATENATE(F250,$O$2,G250,$O$2,H250,$O$2,I250,$O$2,J250) -> Areola-Laser-Hair-Removal-From-Dubai-Academic-City | N250: "> | O250: =PROPER(CONCATENATE(F250," ",G250," ",H250," ",I250," ",J250)) -> Areola Laser Hair Removal From-Dubai-Academic-City | P250: </a> <br /> | Q250: =CONCATENATE(L250,M250,N250,O250,P250) -> <a target="_blank" href="laser.php?permanent=Areola-Laser-Hair-Removal-From-Dubai-Academic-City">Areola Laser Hair Removal From-Dubai-Academic-City</a> <br />
A251: International-City | B251: From | D251: =CONCATENATE(B251,$O$2,A251) -> From-International-City | F251: Arm | G251: Laser | H251: Hair | I251: Removal | J251: =CONCATENATE(C251,D251) -> From-International-City | L251: <a target="_blank" href="laser.php?permanent= | M251: =CONCATENATE(F251,$O$2,G251,$O$2,H251,$O$2,I251,$O$2,J251) -> Arm-Laser-Hair-Removal-From-International-City | N251: "> | O251: =PROPER(CONCATENATE(F251," ",G251," ",H251," ",I251," ",J251)) -> Arm Laser Hair Removal From-International-City | P251: </a> <br /> | Q251: =CONCATENATE(L251,M251,N251,O251,P251) -> <a target="_blank" href="laser.php?permanent=Arm-Laser-Hair-Removal-From-International-City">Arm Laser Hair Removal From-International-City</a> <br />
A252: Al-Warqa | B252: From | D252: =CONCATENATE(B252,$O$2,A252) -> From-Al-Warqa | F252: Armpit | G252: Laser | H252: Hair | I252: Removal | J252: =CONCATENATE(C252,D252) -> From-Al-Warqa | L252: <a target="_blank" href="laser.php?permanent= | M252: =CONCATENATE(F252,$O$2,G252,$O$2,H252,$O$2,I252,$O$2,J252) -> Armpit-Laser-Hair-Removal-From-Al-Warqa | N252: "> | O252: =PROPER(CONCATENATE(F252," ",G252," ",H252," ",I252," ",J252)) -> Armpit Laser Hair Removal From-Al-Warqa | P252: </a> <br /> | Q252: =CONCATENATE(L252,M252,N252,O252,P252) -> <a target="_blank" href="laser.php?permanent=Armpit-Laser-Hair-Removal-From-Al-Warqa">Armpit Laser Hair Removal From-Al-Warqa</a> <br />
A253: Rashidiya | B253: From | D253: =CONCATENATE(B253,$O$2,A253) -> From-Rashidiya | F253: Back | G253: Laser | H253: Hair | I253: Removal | J253: =CONCATENATE(C253,D253) -> From-Rashidiya | L253: <a target="_blank" href="laser.php?permanent= | M253: =CONCATENATE(F253,$O$2,G253,$O$2,H253,$O$2,I253,$O$2,J253) -> Back-Laser-Hair-Removal-From-Rashidiya | N253: "> | O253: =PROPER(CONCATENATE(F253," ",G253," ",H253," ",I253," ",J253)) -> Back Laser Hair Removal From-Rashidiya | P253: </a> <br /> | Q253: =CONCATENATE(L253,M253,N253,O253,P253) -> <a target="_blank" href="laser.php?permanent=Back-Laser-Hair-Removal-From-Rashidiya">Back Laser Hair Removal From-Rashidiya</a> <br />
A254: Mirdif | B254: From | D254: =CONCATENATE(B254,$O$2,A254) -> From-Mirdif | F254: Back-Neck | G254: Laser | H254: Hair | I254: Removal | J254: =CONCATENATE(C254,D254) -> From-Mirdif | L254: <a target="_blank" href="laser.php?permanent= | M254: =CONCATENATE(F254,$O$2,G254,$O$2,H254,$O$2,I254,$O$2,J254) -> Back-Neck-Laser-Hair-Removal-From-Mirdif | N254: "> | O254: =PROPER(CONCATENATE(F254," ",G254," ",H254," ",I254," ",J254)) -> Back-Neck Laser Hair Removal From-Mirdif | P254: </a> <br /> | Q254: =CONCATENATE(L254,M254,N254,O254,P254) -> <a target="_blank" href="laser.php?permanent=Back-Neck-Laser-Hair-Removal-From-Mirdif">Back-Neck Laser Hair Removal From-Mirdif</a> <br />
A255: Deira | B255: From | D255: =CONCATENATE(B255,$O$2,A255) -> From-Deira | F255: Basic-Bikini | G255: Laser | H255: Hair | I255: Removal | J255: =CONCATENATE(C255,D255) -> From-Deira | L255: <a target="_blank" href="laser.php?permanent= | M255: =CONCATENATE(F255,$O$2,G255,$O$2,H255,$O$2,I255,$O$2,J255) -> Basic-Bikini-Laser-Hair-Removal-From-Deira | N255: "> | O255: =PROPER(CONCATENATE(F255," ",G255," ",H255," ",I255," ",J255)) -> Basic-Bikini Laser Hair Removal From-Deira | P255: </a> <br /> | Q255: =CONCATENATE(L255,M255,N255,O255,P255) -> <a target="_blank" href="laser.php?permanent=Basic-Bikini-Laser-Hair-Removal-From-Deira">Basic-Bikini Laser Hair Removal From-Deira</a> <br />
A256: Al-Garhood | B256: From | D256: =CONCATENATE(B256,$O$2,A256) -> From-Al-Garhood | F256: Beard-Line | G256: Laser | H256: Hair | I256: Removal | J256: =CONCATENATE(C256,D256) -> From-Al-Garhood | L256: <a target="_blank" href="laser.php?permanent= | M256: =CONCATENATE(F256,$O$2,G256,$O$2,H256,$O$2,I256,$O$2,J256) -> Beard-Line-Laser-Hair-Removal-From-Al-Garhood | N256: "> | O256: =PROPER(CONCATENATE(F256," ",G256," ",H256," ",I256," ",J256)) -> Beard-Line Laser Hair Removal From-Al-Garhood | P256: </a> <br /> | Q256: =CONCATENATE(L256,M256,N256,O256,P256) -> <a target="_blank" href="laser.php?permanent=Beard-Line-Laser-Hair-Removal-From-Al-Garhood">Beard-Line Laser Hair Removal From-Al-Garhood</a> <br />
A257: Dubai-Festival-City | B257: From | D257: =CONCATENATE(B257,$O$2,A257) -> From-Dubai-Festival-City | F257: Bikini | G257: Laser | H257: Hair | I257: Removal | J257: =CONCATENATE(C257,D257) -> From-Dubai-Festival-City | L257: <a target="_blank" href="laser.php?permanent= | M257: =CONCATENATE(F257,$O$2,G257,$O$2,H257,$O$2,I257,$O$2,J257) -> Bikini-Laser-Hair-Removal-From-Dubai-Festival-City | N257: "> | O257: =PROPER(CONCATENATE(F257," ",G257," ",H257," ",I257," ",J257)) -> Bikini Laser Hair Removal From-Dubai-Festival-City | P257: </a> <br /> | Q257: =CONCATENATE(L257,M257,N257,O257,P257) -> <a target="_blank" href="laser.php?permanent=Bikini-Laser-Hair-Removal-From-Dubai-Festival-City">Bikini Laser Hair Removal From-Dubai-Festival-City</a> <br />
A258: Al-Garhoud | B258: From | D258: =CONCATENATE(B258,$O$2,A258) -> From-Al-Garhoud | F258: Brazilian | G258: Laser | H258: Hair | I258: Removal | J258: =CONCATENATE(C258,D258) -> From-Al-Garhoud | L258: <a target="_blank" href="laser.php?permanent= | M258: =CONCATENATE(F258,$O$2,G258,$O$2,H258,$O$2,I258,$O$2,J258) -> Brazilian-Laser-Hair-Removal-From-Al-Garhoud | N258: "> | O258: =PROPER(CONCATENATE(F258," ",G258," ",H258," ",I258," ",J258)) -> Brazilian Laser Hair Removal From-Al-Garhoud | P258: </a> <br /> | Q258: =CONCATENATE(L258,M258,N258,O258,P258) -> <a target="_blank" href="laser.php?permanent=Brazilian-Laser-Hair-Removal-From-Al-Garhoud">Brazilian Laser Hair Removal From-Al-Garhoud</a> <br />
A259: Al-Qusais | B259: From | D259: =CONCATENATE(B259,$O$2,A259) -> From-Al-Qusais | F259: Breast | G259: Laser | H259: Hair | I259: Removal | J259: =CONCATENATE(C259,D259) -> From-Al-Qusais | L259: <a target="_blank" href="laser.php?permanent= | M259: =CONCATENATE(F259,$O$2,G259,$O$2,H259,$O$2,I259,$O$2,J259) -> Breast-Laser-Hair-Removal-From-Al-Qusais | N259: "> | O259: =PROPER(CONCATENATE(F259," ",G259," ",H259," ",I259," ",J259)) -> Breast Laser Hair Removal From-Al-Qusais | P259: </a> <br /> | Q259: =CONCATENATE(L259,M259,N259,O259,P259) -> <a target="_blank" href="laser.php?permanent=Breast-Laser-Hair-Removal-From-Al-Qusais">Breast Laser Hair Removal From-Al-Qusais</a> <br />
A260: Dubai-Airport | B260: From | D260: =CONCATENATE(B260,$O$2,A260) -> From-Dubai-Airport | F260: Buttock | G260: Laser | H260: Hair | I260: Removal | J260: =CONCATENATE(C260,D260) -> From-Dubai-Airport | L260: <a target="_blank" href="laser.php?permanent= | M260: =CONCATENATE(F260,$O$2,G260,$O$2,H260,$O$2,I260,$O$2,J260) -> Buttock-Laser-Hair-Removal-From-Dubai-Airport | N260: "> | O260: =PROPER(CONCATENATE(F260," ",G260," ",H260," ",I260," ",J260)) -> Buttock Laser Hair Removal From-Dubai-Airport | P260: </a> <br /> | Q260: =CONCATENATE(L260,M260,N260,O260,P260) -> <a target="_blank" href="laser.php?permanent=Buttock-Laser-Hair-Removal-From-Dubai-Airport">Buttock Laser Hair Removal From-Dubai-Airport</a> <br />
... A330: Kalba | B330: From | D330: =CONCATENATE(B330,$O$2,A330) -> From-Kalba | F330: Full-legs | G330: Laser | H330: Hair | I330: Removal | J330: =CONCATENATE(C330,D330) -> From-Kalba | L330: <a target="_blank" href="laser.php?permanent= | M330: =CONCATENATE(F330,$O$2,G330,$O$2,H330,$O$2,I330,$O$2,J330) -> Full-legs-Laser-Hair-Removal-From-Kalba | N330: "> | O330: =PROPER(CONCATENATE(F330," ",G330," ",H330," ",I330," ",J330)) -> Full-Legs Laser Hair Removal From-Kalba | P330: </a> <br /> | Q330: =CONCATENATE(L330,M330,N330,O330,P330) -> <a target="_blank" href="laser.php?permanent=Full-legs-Laser-Hair-Removal-From-Kalba">Full-Legs Laser Hair Removal From-Kalba</a> <br />

Sheet Laser Price
A3: Prices & Packages
B4: 1 Session 55% Discount (AED) | C4: 3 Sessions 60% Discount (AED) | D4: 6 Sessions 70% Discount (AED) | E4: Price Per Session On 6-Session Packages (AED) | F4: 0.1 | G4: 0.2
A5: Abdomen | B5: 200 | C5: =B5*3-J5 -> 540 | D5: =B5*6-K5 -> 960 | E5: =D5/6 -> 160 | F5: =B5/100*10 -> 20 | G5: =B5/100*20 -> 40 | J5: =F5*3 -> 60 | K5: =G5*6 -> 240
A6: Areola | B6: 200 | C6: =B6*3-J6 -> 540 | D6: =B6*6-K6 -> 960 | E6: =D6/6 -> 160 | F6: =B6/100*10 -> 20 | G6: =B6/100*20 -> 40 | J6: =F6*3 -> 60 | K6: =G6*6 -> 240
A7: Arm | B7: 400 | C7: =B7*3-J7 -> 1080 | D7: =B7*6-K7 -> 1920 | E7: =D7/6 -> 320 | F7: =B7/100*10 -> 40 | G7: =B7/100*20 -> 80 | J7: =F7*3 -> 120 | K7: =G7*6 -> 480
A8: Armpit | B8: 250 | C8: =B8*3-J8 -> 675 | D8: =B8*6-K8 -> 1200 | E8: =D8/6 -> 200 | F8: =B8/100*10 -> 25 | G8: =B8/100*20 -> 50 | J8: =F8*3 -> 75 | K8: =G8*6 -> 300
A9: Back | B9: 500 | C9: =B9*3-J9 -> 1350 | D9: =B9*6-K9 -> 2400 | E9: =D9/6 -> 400 | F9: =B9/100*10 -> 50 | G9: =B9/100*20 -> 100 | J9: =F9*3 -> 150 | K9: =G9*6 -> 600
A10: Back-Neck | B10: 160 | C10: =B10*3-J10 -> 432 | D10: =B10*6-K10 -> 768 | E10: =D10/6 -> 128 | F10: =B10/100*10 -> 16 | G10: =B10/100*20 -> 32 | J10: =F10*3 -> 48 | K10: =G10*6 -> 192
A11: Basic-Bikini | B11: 200 | C11: =B11*3-J11 -> 540 | D11: =B11*6-K11 -> 960 | E11: =D11/6 -> 160 | F11: =B11/100*10 -> 20 | G11: =B11/100*20 -> 40 | J11: =F11*3 -> 60 | K11: =G11*6 -> 240
A12: Beard-Line | B12: 100 | C12: =B12*3-J12 -> 270 | D12: =B12*6-K12 -> 480 | E12: =D12/6 -> 80 | F12: =B12/100*10 -> 10 | G12: =B12/100*20 -> 20 | J12: =F12*3 -> 30 | K12: =G12*6 -> 120
A13: Beard | B13: 150 | C13: =B13*3-J13 -> 405 | D13: =B13*6-K13 -> 720 | E13: =D13/6 -> 120 | F13: =B13/100*10 -> 15 | G13: =B13/100*20 -> 30 | J13: =F13*3 -> 45 | K13: =G13*6 -> 180
A14: Bikini | B14: 200 | C14: =B14*3-J14 -> 540 | D14: =B14*6-K14 -> 960 | E14: =D14/6 -> 160 | F14: =B14/100*10 -> 20 | G14: =B14/100*20 -> 40 | J14: =F14*3 -> 60 | K14: =G14*6 -> 240
A15: Brazilian | B15: 200 | C15: =B15*3-J15 -> 540 | D15: =B15*6-K15 -> 960 | E15: =D15/6 -> 160 | F15: =B15/100*10 -> 20 | G15: =B15/100*20 -> 40 | J15: =F15*3 -> 60 | K15: =G15*6 -> 240
A16: Breast | B16: 500 | C16: =B16*3-J16 -> 1350 | D16: =B16*6-K16 -> 2400 | E16: =D16/6 -> 400 | F16: =B16/100*10 -> 50 | G16: =B16/100*20 -> 100 | J16: =F16*3 -> 150 | K16: =G16*6 -> 600
... A54: Upper-Lip | B54: 50 | C54: =B54*3-J54 -> 135 | D54: =B54*6-K54 -> 240 | E54: =D54/6 -> 40 | F54: =B54/100*10 -> 5 | G54: =B54/100*20 -> 10 | J54: =F54*3 -> 15 | K54: =G54*6 -> 60

Sheet Laser Hair Removal  Backup
N1: blank
N2: - | O2: =LEN(N2) -> 1
F3: Iron Welding Works
A4: ='Laser Price'!E5 -> 160 | B4: AED | D4: =CONCATENATE($O$1,B4,$O$1,A4) -> AED 160 | F4: Laser | G4: Hair | H4: Removal | I4: For | J4: Abdomen | K4: <a target="_blank" href="laser.php?permanent= | L4: =CONCATENATE(F4,$N$2,G4,$N$2,H4,$N$2,I4,$N$2,J4) -> Laser-Hair-Removal-For-Abdomen | M4: "> | N4: =PROPER(CONCATENATE(F4," ",G4," ",H4," ",I4," ",J4,$O$1,D4)) -> Laser Hair Removal For Abdomen Aed 160 | O4: </a> <br /> | P4: =CONCATENATE(K4,L4,M4,N4,O4) -> <a target="_blank" href="laser.php?permanent=Laser-Hair-Removal-For-Abdomen">Laser Hair Removal For Abdomen Aed 160</a> <br />
A5: ='Laser Price'!E6 -> 160 | B5: AED | D5: =CONCATENATE($O$1,B5,$O$1,A5) -> AED 160 | F5: Laser | G5: Hair | H5: Removal | I5: For | J5: Areola | K5: <a target="_blank" href="laser.php?permanent= | L5: =CONCATENATE(F5,$N$2,G5,$N$2,H5,$N$2,I5,$N$2,J5) -> Laser-Hair-Removal-For-Areola | M5: "> | N5: =PROPER(CONCATENATE(F5," ",G5," ",H5," ",I5," ",J5,$O$1,D5)) -> Laser Hair Removal For Areola Aed 160 | O5: </a> <br /> | P5: =CONCATENATE(K5,L5,M5,N5,O5) -> <a target="_blank" href="laser.php?permanent=Laser-Hair-Removal-For-Areola">Laser Hair Removal For Areola Aed 160</a> <br />
A6: ='Laser Price'!E7 -> 320 | B6: AED | D6: =CONCATENATE($O$1,B6,$O$1,A6) -> AED 320 | F6: Laser | G6: Hair | H6: Removal | I6: For | J6: Arm | K6: <a target="_blank" href="laser.php?permanent= | L6: =CONCATENATE(F6,$N$2,G6,$N$2,H6,$N$2,I6,$N$2,J6) -> Laser-Hair-Removal-For-Arm | M6: "> | N6: =PROPER(CONCATENATE(F6," ",G6," ",H6," ",I6," ",J6,$O$1,D6)) -> Laser Hair Removal For Arm Aed 320 | O6: </a> <br /> | P6: =CONCATENATE(K6,L6,M6,N6,O6) -> <a target="_blank" href="laser.php?permanent=Laser-Hair-Removal-For-Arm">Laser Hair Removal For Arm Aed 320</a> <br />
A7: ='Laser Price'!E8 -> 200 | B7: AED | D7: =CONCATENATE($O$1,B7,$O$1,A7) -> AED 200 | F7: Laser | G7: Hair | H7: Removal | I7: For | J7: Armpit | K7: <a target="_blank" href="laser.php?permanent= | L7: =CONCATENATE(F7,$N$2,G7,$N$2,H7,$N$2,I7,$N$2,J7) -> Laser-Hair-Removal-For-Armpit | M7: "> | N7: =PROPER(CONCATENATE(F7," ",G7," ",H7," ",I7," ",J7,$O$1,D7)) -> Laser Hair Removal For Armpit Aed 200 | O7: </a> <br /> | P7: =CONCATENATE(K7,L7,M7,N7,O7) -> <a target="_blank" href="laser.php?permanent=Laser-Hair-Removal-For-Armpit">Laser Hair Removal For Armpit Aed 200</a> <br />
A8: ='Laser Price'!E9 -> 400 | B8: AED | D8: =CONCATENATE($O$1,B8,$O$1,A8) -> AED 400 | F8: Laser | G8: Hair | H8: Removal | I8: For | J8: Back | K8: <a target="_blank" href="laser.php?permanent= | L8: =CONCATENATE(F8,$N$2,G8,$N$2,H8,$N$2,I8,$N$2,J8) -> Laser-Hair-Removal-For-Back | M8: "> | N8: =PROPER(CONCATENATE(F8," ",G8," ",H8," ",I8," ",J8,$O$1,D8)) -> Laser Hair Removal For Back Aed 400 | O8: </a> <br /> | P8: =CONCATENATE(K8,L8,M8,N8,O8) -> <a target="_blank" href="laser.php?permanent=Laser-Hair-Removal-For-Back">Laser Hair Removal For Back Aed 400</a> <br />
A9: ='Laser Price'!E10 -> 128 | B9: AED | D9: =CONCATENATE($O$1,B9,$O$1,A9) -> AED 128 | F9: Laser | G9: Hair | H9: Removal | I9: For | J9: Back-Neck | K9: <a target="_blank" href="laser.php?permanent= | L9: =CONCATENATE(F9,$N$2,G9,$N$2,H9,$N$2,I9,$N$2,J9) -> Laser-Hair-Removal-For-Back-Neck | M9: "> | N9: =PROPER(CONCATENATE(F9," ",G9," ",H9," ",I9," ",J9,$O$1,D9)) -> Laser Hair Removal For Back-Neck Aed 128 | O9: </a> <br /> | P9: =CONCATENATE(K9,L9,M9,N9,O9) -> <a target="_blank" href="laser.php?permanent=Laser-Hair-Removal-For-Back-Neck">Laser Hair Removal For Back-Neck Aed 128</a> <br />
A10: ='Laser Price'!E11 -> 160 | B10: AED | D10: =CONCATENATE($O$1,B10,$O$1,A10) -> AED 160 | F10: Laser | G10: Hair | H10: Removal | I10: For | J10: Basic-Bikini | K10: <a target="_blank" href="laser.php?permanent= | L10: =CONCATENATE(F10,$N$2,G10,$N$2,H10,$N$2,I10,$N$2,J10) -> Laser-Hair-Removal-For-Basic-Bikini | M10: "> | N10: =PROPER(CONCATENATE(F10," ",G10," ",H10," ",I10," ",J10,$O$1,D10)) -> Laser Hair Removal For Basic-Bikini Aed 160 | O10: </a> <br /> | P10: =CONCATENATE(K10,L10,M10,N10,O10) -> <a target="_blank" href="laser.php?permanent=Laser-Hair-Removal-For-Basic-Bikini">Laser Hair Removal For Basic-Bikini Aed 160</a> <br />
A11: ='Laser Price'!E12 -> 80 | B11: AED | D11: =CONCATENATE($O$1,B11,$O$1,A11) -> AED 80 | F11: Laser | G11: Hair | H11: Removal | I11: For | J11: Beard-Line | K11: <a target="_blank" href="laser.php?permanent= | L11: =CONCATENATE(F11,$N$2,G11,$N$2,H11,$N$2,I11,$N$2,J11) -> Laser-Hair-Removal-For-Beard-Line | M11: "> | N11: =PROPER(CONCATENATE(F11," ",G11," ",H11," ",I11," ",J11,$O$1,D11)) -> Laser Hair Removal For Beard-Line Aed 80 | O11: </a> <br /> | P11: =CONCATENATE(K11,L11,M11,N11,O11) -> <a target="_blank" href="laser.php?permanent=Laser-Hair-Removal-For-Beard-Line">Laser Hair Removal For Beard-Line Aed 80</a> <br />
A12: ='Laser Price'!E14 -> 160 | B12: AED | D12: =CONCATENATE($O$1,B12,$O$1,A12) -> AED 160 | F12: Laser | G12: Hair | H12: Removal | I12: For | J12: Bikini | K12: <a target="_blank" href="laser.php?permanent= | L12: =CONCATENATE(F12,$N$2,G12,$N$2,H12,$N$2,I12,$N$2,J12) -> Laser-Hair-Removal-For-Bikini | M12: "> | N12: =PROPER(CONCATENATE(F12," ",G12," ",H12," ",I12," ",J12,$O$1,D12)) -> Laser Hair Removal For Bikini Aed 160 | O12: </a> <br /> | P12: =CONCATENATE(K12,L12,M12,N12,O12) -> <a target="_blank" href="laser.php?permanent=Laser-Hair-Removal-For-Bikini">Laser Hair Removal For Bikini Aed 160</a> <br />
A13: ='Laser Price'!E15 -> 160 | B13: AED | D13: =CONCATENATE($O$1,B13,$O$1,A13) -> AED 160 | F13: Laser | G13: Hair | H13: Removal | I13: For | J13: Brazilian | K13: <a target="_blank" href="laser.php?permanent= | L13: =CONCATENATE(F13,$N$2,G13,$N$2,H13,$N$2,I13,$N$2,J13) -> Laser-Hair-Removal-For-Brazilian | M13: "> | N13: =PROPER(CONCATENATE(F13," ",G13," ",H13," ",I13," ",J13,$O$1,D13)) -> Laser Hair Removal For Brazilian Aed 160 | O13: </a> <br /> | P13: =CONCATENATE(K13,L13,M13,N13,O13) -> <a target="_blank" href="laser.php?permanent=Laser-Hair-Removal-For-Brazilian">Laser Hair Removal For Brazilian Aed 160</a> <br />
A14: ='Laser Price'!E16 -> 400 | B14: AED | D14: =CONCATENATE($O$1,B14,$O$1,A14) -> AED 400 | F14: Laser | G14: Hair | H14: Removal | I14: For | J14: Breast | K14: <a target="_blank" href="laser.php?permanent= | L14: =CONCATENATE(F14,$N$2,G14,$N$2,H14,$N$2,I14,$N$2,J14) -> Laser-Hair-Removal-For-Breast | M14: "> | N14: =PROPER(CONCATENATE(F14," ",G14," ",H14," ",I14," ",J14,$O$1,D14)) -> Laser Hair Removal For Breast Aed 400 | O14: </a> <br /> | P14: =CONCATENATE(K14,L14,M14,N14,O14) -> <a target="_blank" href="laser.php?permanent=Laser-Hair-Removal-For-Breast">Laser Hair Removal For Breast Aed 400</a> <br />
A15: ='Laser Price'!E17 -> 400 | B15: AED | D15: =CONCATENATE($O$1,B15,$O$1,A15) -> AED 400 | F15: Laser | G15: Hair | H15: Removal | I15: For | J15: Buttock | K15: <a target="_blank" href="laser.php?permanent= | L15: =CONCATENATE(F15,$N$2,G15,$N$2,H15,$N$2,I15,$N$2,J15) -> Laser-Hair-Removal-For-Buttock | M15: "> | N15: =PROPER(CONCATENATE(F15," ",G15," ",H15," ",I15," ",J15,$O$1,D15)) -> Laser Hair Removal For Buttock Aed 400 | O15: </a> <br /> | P15: =CONCATENATE(K15,L15,M15,N15,O15) -> <a target="_blank" href="laser.php?permanent=Laser-Hair-Removal-For-Buttock">Laser Hair Removal For Buttock Aed 400</a> <br />
A16: ='Laser Price'!E18 -> 120 | B16: AED | D16: =CONCATENATE($O$1,B16,$O$1,A16) -> AED 120 | F16: Laser | G16: Hair | H16: Removal | I16: For | J16: Cheek | K16: <a target="_blank" href="laser.php?permanent= | L16: =CONCATENATE(F16,$N$2,G16,$N$2,H16,$N$2,I16,$N$2,J16) -> Laser-Hair-Removal-For-Cheek | M16: "> | N16: =PROPER(CONCATENATE(F16," ",G16," ",H16," ",I16," ",J16,$O$1,D16)) -> Laser Hair Removal For Cheek Aed 120 | O16: </a> <br /> | P16: =CONCATENATE(K16,L16,M16,N16,O16) -> <a target="_blank" href="laser.php?permanent=Laser-Hair-Removal-For-Cheek">Laser Hair Removal For Cheek Aed 120</a> <br />
A17: ='Laser Price'!E19 -> 400 | B17: AED | D17: =CONCATENATE($O$1,B17,$O$1,A17) -> AED 400 | F17: Laser | G17: Hair | H17: Removal | I17: For | J17: Chest | K17: <a target="_blank" href="laser.php?permanent= | L17: =CONCATENATE(F17,$N$2,G17,$N$2,H17,$N$2,I17,$N$2,J17) -> Laser-Hair-Removal-For-Chest | M17: "> | N17: =PROPER(CONCATENATE(F17," ",G17," ",H17," ",I17," ",J17,$O$1,D17)) -> Laser Hair Removal For Chest Aed 400 | O17: </a> <br /> | P17: =CONCATENATE(K17,L17,M17,N17,O17) -> <a target="_blank" href="laser.php?permanent=Laser-Hair-Removal-For-Chest">Laser Hair Removal For Chest Aed 400</a> <br />
A18: ='Laser Price'!E20 -> 40 | B18: AED | D18: =CONCATENATE($O$1,B18,$O$1,A18) -> AED 40 | F18: Laser | G18: Hair | H18: Removal | I18: For | J18: Chin | K18: <a target="_blank" href="laser.php?permanent= | L18: =CONCATENATE(F18,$N$2,G18,$N$2,H18,$N$2,I18,$N$2,J18) -> Laser-Hair-Removal-For-Chin | M18: "> | N18: =PROPER(CONCATENATE(F18," ",G18," ",H18," ",I18," ",J18,$O$1,D18)) -> Laser Hair Removal For Chin Aed 40 | O18: </a> <br /> | P18: =CONCATENATE(K18,L18,M18,N18,O18) -> <a target="_blank" href="laser.php?permanent=Laser-Hair-Removal-For-Chin">Laser Hair Removal For Chin Aed 40</a> <br />
A19: ='Laser Price'!E21 -> 40 | B19: AED | D19: =CONCATENATE($O$1,B19,$O$1,A19) -> AED 40 | F19: Laser | G19: Hair | H19: Removal | I19: For | J19: Ear | K19: <a target="_blank" href="laser.php?permanent= | L19: =CONCATENATE(F19,$N$2,G19,$N$2,H19,$N$2,I19,$N$2,J19) -> Laser-Hair-Removal-For-Ear | M19: "> | N19: =PROPER(CONCATENATE(F19," ",G19," ",H19," ",I19," ",J19,$O$1,D19)) -> Laser Hair Removal For Ear Aed 40 | O19: </a> <br /> | P19: =CONCATENATE(K19,L19,M19,N19,O19) -> <a target="_blank" href="laser.php?permanent=Laser-Hair-Removal-For-Ear">Laser Hair Removal For Ear Aed 40</a> <br />
A20: ='Laser Price'!E22 -> 160 | B20: AED | D20: =CONCATENATE($O$1,B20,$O$1,A20) -> AED 160 | F20: Laser | G20: Hair | H20: Removal | I20: For | J20: Elbow | K20: <a target="_blank" href="laser.php?permanent= | L20: =CONCATENATE(F20,$N$2,G20,$N$2,H20,$N$2,I20,$N$2,J20) -> Laser-Hair-Removal-For-Elbow | M20: "> | N20: =PROPER(CONCATENATE(F20," ",G20," ",H20," ",I20," ",J20,$O$1,D20)) -> Laser Hair Removal For Elbow Aed 160 | O20: </a> <br /> | P20: =CONCATENATE(K20,L20,M20,N20,O20) -> <a target="_blank" href="laser.php?permanent=Laser-Hair-Removal-For-Elbow">Laser Hair Removal For Elbow Aed 160</a> <br />
A21: ='Laser Price'!E23 -> 120 | B21: AED | D21: =CONCATENATE($O$1,B21,$O$1,A21) -> AED 120 | F21: Laser | G21: Hair | H21: Removal | I21: For | J21: Eyebrow | K21: <a target="_blank" href="laser.php?permanent= | L21: =CONCATENATE(F21,$N$2,G21,$N$2,H21,$N$2,I21,$N$2,J21) -> Laser-Hair-Removal-For-Eyebrow | M21: "> | N21: =PROPER(CONCATENATE(F21," ",G21," ",H21," ",I21," ",J21,$O$1,D21)) -> Laser Hair Removal For Eyebrow Aed 120 | O21: </a> <br /> | P21: =CONCATENATE(K21,L21,M21,N21,O21) -> <a target="_blank" href="laser.php?permanent=Laser-Hair-Removal-For-Eyebrow">Laser Hair Removal For Eyebrow Aed 120</a> <br />
A22: ='Laser Price'!E24 -> 80 | B22: AED | D22: =CONCATENATE($O$1,B22,$O$1,A22) -> AED 80 | F22: Laser | G22: Hair | H22: Removal | I22: For | J22: Face | K22: <a target="_blank" href="laser.php?permanent= | L22: =CONCATENATE(F22,$N$2,G22,$N$2,H22,$N$2,I22,$N$2,J22) -> Laser-Hair-Removal-For-Face | M22: "> | N22: =PROPER(CONCATENATE(F22," ",G22," ",H22," ",I22," ",J22,$O$1,D22)) -> Laser Hair Removal For Face Aed 80 | O22: </a> <br /> | P22: =CONCATENATE(K22,L22,M22,N22,O22) -> <a target="_blank" href="laser.php?permanent=Laser-Hair-Removal-For-Face">Laser Hair Removal For Face Aed 80</a> <br />
A23: ='Laser Price'!E25 -> 80 | B23: AED | D23: =CONCATENATE($O$1,B23,$O$1,A23) -> AED 80 | F23: Laser | G23: Hair | H23: Removal | I23: For | J23: Feet | K23: <a target="_blank" href="laser.php?permanent= | L23: =CONCATENATE(F23,$N$2,G23,$N$2,H23,$N$2,I23,$N$2,J23) -> Laser-Hair-Removal-For-Feet | M23: "> | N23: =PROPER(CONCATENATE(F23," ",G23," ",H23," ",I23," ",J23,$O$1,D23)) -> Laser Hair Removal For Feet Aed 80 | O23: </a> <br /> | P23: =CONCATENATE(K23,L23,M23,N23,O23) -> <a target="_blank" href="laser.php?permanent=Laser-Hair-Removal-For-Feet">Laser Hair Removal For Feet Aed 80</a> <br />
... A52: ='Laser Price'!E54 -> 40 | B52: AED | D52: =CONCATENATE($O$1,B52,$O$1,A52) -> AED 40 | F52: Laser | G52: Hair | H52: Removal | I52: For | J52: Upper-Lip | K52: <a target="_blank" href="laser.php?permanent= | L52: =CONCATENATE(F52,$N$2,G52,$N$2,H52,$N$2,I52,$N$2,J52) -> Laser-Hair-Removal-For-Upper-Lip | M52: "> | N52: =PROPER(CONCATENATE(F52," ",G52," ",H52," ",I52," ",J52,$O$1,D52)) -> Laser Hair Removal For Upper-Lip Aed 40 | O52: </a> <br /> | P52: =CONCATENATE(K52,L52,M52,N52,O52) -> <a target="_blank" href="laser.php?permanent=Laser-Hair-Removal-For-Upper-Lip">Laser Hair Removal For Upper-Lip Aed 40</a> <br />
A53: 160 | B53: AED | D53: =CONCATENATE($O$1,B53,$O$1,A53) -> AED 160 | F53: Men | G53: Laser | H53: Hair | I53: Removal | J53: Abdomen | K53: <a target="_blank" href="laser.php?permanent= | L53: =CONCATENATE(F53,$N$2,G53,$N$2,H53,$N$2,I53,$N$2,J53) -> Men-Laser-Hair-Removal-Abdomen | M53: "> | N53: =PROPER(CONCATENATE(F53," ",G53," ",H53," ",I53," ",J53,$O$1,D53)) -> Men Laser Hair Removal Abdomen Aed 160 | O53: </a> <br /> | P53: =CONCATENATE(K53,L53,M53,N53,O53) -> <a target="_blank" href="laser.php?permanent=Men-Laser-Hair-Removal-Abdomen">Men Laser Hair Removal Abdomen Aed 160</a> <br />
A54: 160 | B54: AED | D54: =CONCATENATE($O$1,B54,$O$1,A54) -> AED 160 | F54: Men | G54: Laser | H54: Hair | I54: Removal | J54: Areola | K54: <a target="_blank" href="laser.php?permanent= | L54: =CONCATENATE(F54,$N$2,G54,$N$2,H54,$N$2,I54,$N$2,J54) -> Men-Laser-Hair-Removal-Areola | M54: "> | N54: =PROPER(CONCATENATE(F54," ",G54," ",H54," ",I54," ",J54,$O$1,D54)) -> Men Laser Hair Removal Areola Aed 160 | O54: </a> <br /> | P54: =CONCATENATE(K54,L54,M54,N54,O54) -> <a target="_blank" href="laser.php?permanent=Men-Laser-Hair-Removal-Areola">Men Laser Hair Removal Areola Aed 160</a> <br />
A55: 320 | B55: AED | D55: =CONCATENATE($O$1,B55,$O$1,A55) -> AED 320 | F55: Men | G55: Laser | H55: Hair | I55: Removal | J55: Arm | K55: <a target="_blank" href="laser.php?permanent= | L55: =CONCATENATE(F55,$N$2,G55,$N$2,H55,$N$2,I55,$N$2,J55) -> Men-Laser-Hair-Removal-Arm | M55: "> | N55: =PROPER(CONCATENATE(F55," ",G55," ",H55," ",I55," ",J55,$O$1,D55)) -> Men Laser Hair Removal Arm Aed 320 | O55: </a> <br /> | P55: =CONCATENATE(K55,L55,M55,N55,O55) -> <a target="_blank" href="laser.php?permanent=Men-Laser-Hair-Removal-Arm">Men Laser Hair Removal Arm Aed 320</a> <br />
A56: 200 | B56: AED | D56: =CONCATENATE($O$1,B56,$O$1,A56) -> AED 200 | F56: Men | G56: Laser | H56: Hair | I56: Removal | J56: Armpit | K56: <a target="_blank" href="laser.php?permanent= | L56: =CONCATENATE(F56,$N$2,G56,$N$2,H56,$N$2,I56,$N$2,J56) -> Men-Laser-Hair-Removal-Armpit | M56: "> | N56: =PROPER(CONCATENATE(F56," ",G56," ",H56," ",I56," ",J56,$O$1,D56)) -> Men Laser Hair Removal Armpit Aed 200 | O56: </a> <br /> | P56: =CONCATENATE(K56,L56,M56,N56,O56) -> <a target="_blank" href="laser.php?permanent=Men-Laser-Hair-Removal-Armpit">Men Laser Hair Removal Armpit Aed 200</a> <br />
A57: 400 | B57: AED | D57: =CONCATENATE($O$1,B57,$O$1,A57) -> AED 400 | F57: Men | G57: Laser | H57: Hair | I57: Removal | J57: Back | K57: <a target="_blank" href="laser.php?permanent= | L57: =CONCATENATE(F57,$N$2,G57,$N$2,H57,$N$2,I57,$N$2,J57) -> Men-Laser-Hair-Removal-Back | M57: "> | N57: =PROPER(CONCATENATE(F57," ",G57," ",H57," ",I57," ",J57,$O$1,D57)) -> Men Laser Hair Removal Back Aed 400 | O57: </a> <br /> | P57: =CONCATENATE(K57,L57,M57,N57,O57) -> <a target="_blank" href="laser.php?permanent=Men-Laser-Hair-Removal-Back">Men Laser Hair Removal Back Aed 400</a> <br />
A58: 128 | B58: AED | D58: =CONCATENATE($O$1,B58,$O$1,A58) -> AED 128 | F58: Men | G58: Laser | H58: Hair | I58: Removal | J58: Back-Neck | K58: <a target="_blank" href="laser.php?permanent= | L58: =CONCATENATE(F58,$N$2,G58,$N$2,H58,$N$2,I58,$N$2,J58) -> Men-Laser-Hair-Removal-Back-Neck | M58: "> | N58: =PROPER(CONCATENATE(F58," ",G58," ",H58," ",I58," ",J58,$O$1,D58)) -> Men Laser Hair Removal Back-Neck Aed 128 | O58: </a> <br /> | P58: =CONCATENATE(K58,L58,M58,N58,O58) -> <a target="_blank" href="laser.php?permanent=Men-Laser-Hair-Removal-Back-Neck">Men Laser Hair Removal Back-Neck Aed 128</a> <br />
A59: 160 | B59: AED | D59: =CONCATENATE($O$1,B59,$O$1,A59) -> AED 160 | F59: Men | G59: Laser | H59: Hair | I59: Removal | J59: Basic-Bikini | K59: <a target="_blank" href="laser.php?permanent= | L59: =CONCATENATE(F59,$N$2,G59,$N$2,H59,$N$2,I59,$N$2,J59) -> Men-Laser-Hair-Removal-Basic-Bikini | M59: "> | N59: =PROPER(CONCATENATE(F59," ",G59," ",H59," ",I59," ",J59,$O$1,D59)) -> Men Laser Hair Removal Basic-Bikini Aed 160 | O59: </a> <br /> | P59: =CONCATENATE(K59,L59,M59,N59,O59) -> <a target="_blank" href="laser.php?permanent=Men-Laser-Hair-Removal-Basic-Bikini">Men Laser Hair Removal Basic-Bikini Aed 160</a> <br />
A60: 120 | B60: AED | D60: =CONCATENATE($O$1,B60,$O$1,A60) -> AED 120 | F60: Men | G60: Laser | H60: Hair | I60: Removal | J60: Beard-Line | K60: <a target="_blank" href="laser.php?permanent= | L60: =CONCATENATE(F60,$N$2,G60,$N$2,H60,$N$2,I60,$N$2,J60) -> Men-Laser-Hair-Removal-Beard-Line | M60: "> | N60: =PROPER(CONCATENATE(F60," ",G60," ",H60," ",I60," ",J60,$O$1,D60)) -> Men Laser Hair Removal Beard-Line Aed 120 | O60: </a> <br /> | P60: =CONCATENATE(K60,L60,M60,N60,O60) -> <a target="_blank" href="laser.php?permanent=Men-Laser-Hair-Removal-Beard-Line">Men Laser Hair Removal Beard-Line Aed 120</a> <br />
A61: 160 | B61: AED | D61: =CONCATENATE($O$1,B61,$O$1,A61) -> AED 160 | F61: Men | G61: Laser | H61: Hair | I61: Removal | J61: Bikini | K61: <a target="_blank" href="laser.php?permanent= | L61: =CONCATENATE(F61,$N$2,G61,$N$2,H61,$N$2,I61,$N$2,J61) -> Men-Laser-Hair-Removal-Bikini | M61: "> | N61: =PROPER(CONCATENATE(F61," ",G61," ",H61," ",I61," ",J61,$O$1,D61)) -> Men Laser Hair Removal Bikini Aed 160 | O61: </a> <br /> | P61: =CONCATENATE(K61,L61,M61,N61,O61) -> <a target="_blank" href="laser.php?permanent=Men-Laser-Hair-Removal-Bikini">Men Laser Hair Removal Bikini Aed 160</a> <br />
A62: 160 | B62: AED | D62: =CONCATENATE($O$1,B62,$O$1,A62) -> AED 160 | F62: Men | G62: Laser | H62: Hair | I62: Removal | J62: Brazilian | K62: <a target="_blank" href="laser.php?permanent= | L62: =CONCATENATE(F62,$N$2,G62,$N$2,H62,$N$2,I62,$N$2,J62) -> Men-Laser-Hair-Removal-Brazilian | M62: "> | N62: =PROPER(CONCATENATE(F62," ",G62," ",H62," ",I62," ",J62,$O$1,D62)) -> Men Laser Hair Removal Brazilian Aed 160 | O62: </a> <br /> | P62: =CONCATENATE(K62,L62,M62,N62,O62) -> <a target="_blank" href="laser.php?permanent=Men-Laser-Hair-Removal-Brazilian">Men Laser Hair Removal Brazilian Aed 160</a> <br />
A63: 400 | B63: AED | D63: =CONCATENATE($O$1,B63,$O$1,A63) -> AED 400 | F63: Men | G63: Laser | H63: Hair | I63: Removal | J63: Breast | K63: <a target="_blank" href="laser.php?permanent= | L63: =CONCATENATE(F63,$N$2,G63,$N$2,H63,$N$2,I63,$N$2,J63) -> Men-Laser-Hair-Removal-Breast | M63: "> | N63: =PROPER(CONCATENATE(F63," ",G63," ",H63," ",I63," ",J63,$O$1,D63)) -> Men Laser Hair Removal Breast Aed 400 | O63: </a> <br /> | P63: =CONCATENATE(K63,L63,M63,N63,O63) -> <a target="_blank" href="laser.php?permanent=Men-Laser-Hair-Removal-Breast">Men Laser Hair Removal Breast Aed 400</a> <br />
A64: 400 | B64: AED | D64: =CONCATENATE($O$1,B64,$O$1,A64) -> AED 400 | F64: Men | G64: Laser | H64: Hair | I64: Removal | J64: Buttock | K64: <a target="_blank" href="laser.php?permanent= | L64: =CONCATENATE(F64,$N$2,G64,$N$2,H64,$N$2,I64,$N$2,J64) -> Men-Laser-Hair-Removal-Buttock | M64: "> | N64: =PROPER(CONCATENATE(F64," ",G64," ",H64," ",I64," ",J64,$O$1,D64)) -> Men Laser Hair Removal Buttock Aed 400 | O64: </a> <br /> | P64: =CONCATENATE(K64,L64,M64,N64,O64) -> <a target="_blank" href="laser.php?permanent=Men-Laser-Hair-Removal-Buttock">Men Laser Hair Removal Buttock Aed 400</a> <br />
... A199: 40 | B199: AED | D199: =CONCATENATE($O$1,B199,$O$1,A199) -> AED 40 | F199: Upper-Lip | G199: Laser | H199: Hair | I199: Removal | J199: Price | K199: <a target="_blank" href="laser.php?permanent= | L199: =CONCATENATE(F199,$N$2,G199,$N$2,H199,$N$2,I199,$N$2,J199) -> Upper-Lip-Laser-Hair-Removal-Price | M199: "> | N199: =PROPER(CONCATENATE(F199," ",G199," ",H199," ",I199," ",J199,$O$1,D199)) -> Upper-Lip Laser Hair Removal Price Aed 40 | O199: </a> <br /> | P199: =CONCATENATE(K199,L199,M199,N199,O199) -> <a target="_blank" href="laser.php?permanent=Upper-Lip-Laser-Hair-Removal-Price">Upper-Lip Laser Hair Removal Price Aed 40</a> <br />

Sheet laser hair removal arabic
N1: blank
N2: - | O2: =LEN(N2) -> 1
F3: Keywords
A4: ازالة-الشعر-بالليزر-في-مصر-التكلفة-وال | B4: ازالة-الشعر-بالليزر-في-مصر-التكلفة-وال | C4: =SUBSTITUTE(B4,"-"," ") -> ازالة الشعر بالليزر في مصر التكلفة وال | F4: =B4 -> ازالة-الشعر-بالليزر-في-مصر-التكلفة-وال | K4: <a target="_blank" href="dubai.php?search= | L4: =PROPER(F4) -> ازالة-الشعر-بالليزر-في-مصر-التكلفة-وال | M4: "> | N4: =C4 -> ازالة الشعر بالليزر في مصر التكلفة وال | O4: </a> <br /> | P4: =CONCATENATE(K4,L4,M4,N4,O4) -> <a target="_blank" href="dubai.php?search=ازالة-الشعر-بالليزر-في-مصر-التكلفة-وال">ازالة الشعر بالليزر في مصر التكلفة وال</a> <br />
A5: 1 day trip in dubai | B5: 1-day-trip-in-dubai | F5: =B5 -> 1-day-trip-in-dubai | K5: <a target="_blank" href="dubai.php?search= | L5: =PROPER(F5) -> 1-Day-Trip-In-Dubai | M5: "> | N5: =PROPER(CONCATENATE(F5," ",G5," ",H5," ",I5," ",J5)) -> 1-Day-Trip-In-Dubai | O5: </a> <br /> | P5: =CONCATENATE(K5,L5,M5,N5,O5) -> <a target="_blank" href="dubai.php?search=1-Day-Trip-In-Dubai">1-Day-Trip-In-Dubai </a> <br />
A6: 1 hour limo ride dubai | B6: 1-hour-limo-ride-dubai | F6: =B6 -> 1-hour-limo-ride-dubai | K6: <a target="_blank" href="dubai.php?search= | L6: =PROPER(F6) -> 1-Hour-Limo-Ride-Dubai | M6: "> | N6: =PROPER(CONCATENATE(F6," ",G6," ",H6," ",I6," ",J6)) -> 1-Hour-Limo-Ride-Dubai | O6: </a> <br /> | P6: =CONCATENATE(K6,L6,M6,N6,O6) -> <a target="_blank" href="dubai.php?search=1-Hour-Limo-Ride-Dubai">1-Hour-Limo-Ride-Dubai </a> <br />
A7: 1 hour yacht ride dubai | B7: 1-hour-yacht-ride-dubai | F7: =B7 -> 1-hour-yacht-ride-dubai | K7: <a target="_blank" href="dubai.php?search= | L7: =PROPER(F7) -> 1-Hour-Yacht-Ride-Dubai | M7: "> | N7: =PROPER(CONCATENATE(F7," ",G7," ",H7," ",I7," ",J7)) -> 1-Hour-Yacht-Ride-Dubai | O7: </a> <br /> | P7: =CONCATENATE(K7,L7,M7,N7,O7) -> <a target="_blank" href="dubai.php?search=1-Hour-Yacht-Ride-Dubai">1-Hour-Yacht-Ride-Dubai </a> <br />
A8: 2 day dubai tour packages | B8: 2-day-dubai-tour-packages | F8: =B8 -> 2-day-dubai-tour-packages | K8: <a target="_blank" href="dubai.php?search= | L8: =PROPER(F8) -> 2-Day-Dubai-Tour-Packages | M8: "> | N8: =PROPER(CONCATENATE(F8," ",G8," ",H8," ",I8," ",J8)) -> 2-Day-Dubai-Tour-Packages | O8: </a> <br /> | P8: =CONCATENATE(K8,L8,M8,N8,O8) -> <a target="_blank" href="dubai.php?search=2-Day-Dubai-Tour-Packages">2-Day-Dubai-Tour-Packages </a> <br />
A9: 2 days trip from dubai | B9: 2-days-trip-from-dubai | F9: =B9 -> 2-days-trip-from-dubai | K9: <a target="_blank" href="dubai.php?search= | L9: =PROPER(F9) -> 2-Days-Trip-From-Dubai | M9: "> | N9: =PROPER(CONCATENATE(F9," ",G9," ",H9," ",I9," ",J9)) -> 2-Days-Trip-From-Dubai | O9: </a> <br /> | P9: =CONCATENATE(K9,L9,M9,N9,O9) -> <a target="_blank" href="dubai.php?search=2-Days-Trip-From-Dubai">2-Days-Trip-From-Dubai </a> <br />
A10: 3 day trip to dubai cost | B10: 3-day-trip-to-dubai-cost | F10: =B10 -> 3-day-trip-to-dubai-cost | K10: <a target="_blank" href="dubai.php?search= | L10: =PROPER(F10) -> 3-Day-Trip-To-Dubai-Cost | M10: "> | N10: =PROPER(CONCATENATE(F10," ",G10," ",H10," ",I10," ",J10)) -> 3-Day-Trip-To-Dubai-Cost | O10: </a> <br /> | P10: =CONCATENATE(K10,L10,M10,N10,O10) -> <a target="_blank" href="dubai.php?search=3-Day-Trip-To-Dubai-Cost">3-Day-Trip-To-Dubai-Cost </a> <br />
A11: 3 days 2 nights package tour dubai | B11: 3-days-2-nights-package-tour-dubai | F11: =B11 -> 3-days-2-nights-package-tour-dubai | K11: <a target="_blank" href="dubai.php?search= | L11: =PROPER(F11) -> 3-Days-2-Nights-Package-Tour-Dubai | M11: "> | N11: =PROPER(CONCATENATE(F11," ",G11," ",H11," ",I11," ",J11)) -> 3-Days-2-Nights-Package-Tour-Dubai | O11: </a> <br /> | P11: =CONCATENATE(K11,L11,M11,N11,O11) -> <a target="_blank" href="dubai.php?search=3-Days-2-Nights-Package-Tour-Dubai">3-Days-2-Nights-Package-Tour-Dubai </a> <br />
A12: 3 days trip from dubai | B12: 3-days-trip-from-dubai | F12: =B12 -> 3-days-trip-from-dubai | K12: <a target="_blank" href="dubai.php?search= | L12: =PROPER(F12) -> 3-Days-Trip-From-Dubai | M12: "> | N12: =PROPER(CONCATENATE(F12," ",G12," ",H12," ",I12," ",J12)) -> 3-Days-Trip-From-Dubai | O12: </a> <br /> | P12: =CONCATENATE(K12,L12,M12,N12,O12) -> <a target="_blank" href="dubai.php?search=3-Days-Trip-From-Dubai">3-Days-Trip-From-Dubai </a> <br />
A13: 4 day trip to dubai | B13: 4-day-trip-to-dubai | F13: =B13 -> 4-day-trip-to-dubai | K13: <a target="_blank" href="dubai.php?search= | L13: =PROPER(F13) -> 4-Day-Trip-To-Dubai | M13: "> | N13: =PROPER(CONCATENATE(F13," ",G13," ",H13," ",I13," ",J13)) -> 4-Day-Trip-To-Dubai | O13: </a> <br /> | P13: =CONCATENATE(K13,L13,M13,N13,O13) -> <a target="_blank" href="dubai.php?search=4-Day-Trip-To-Dubai">4-Day-Trip-To-Dubai </a> <br />
A14: 4 days in dubai | B14: 4-days-in-dubai | F14: =B14 -> 4-days-in-dubai | K14: <a target="_blank" href="dubai.php?search= | L14: =PROPER(F14) -> 4-Days-In-Dubai | M14: "> | N14: =PROPER(CONCATENATE(F14," ",G14," ",H14," ",I14," ",J14)) -> 4-Days-In-Dubai | O14: </a> <br /> | P14: =CONCATENATE(K14,L14,M14,N14,O14) -> <a target="_blank" href="dubai.php?search=4-Days-In-Dubai">4-Days-In-Dubai </a> <br />
A15: 4 days in dubai cost | B15: 4-days-in-dubai-cost | F15: =B15 -> 4-days-in-dubai-cost | K15: <a target="_blank" href="dubai.php?search= | L15: =PROPER(F15) -> 4-Days-In-Dubai-Cost | M15: "> | N15: =PROPER(CONCATENATE(F15," ",G15," ",H15," ",I15," ",J15)) -> 4-Days-In-Dubai-Cost | O15: </a> <br /> | P15: =CONCATENATE(K15,L15,M15,N15,O15) -> <a target="_blank" href="dubai.php?search=4-Days-In-Dubai-Cost">4-Days-In-Dubai-Cost </a> <br />
A16: 4 days trip from dubai | B16: 4-days-trip-from-dubai | F16: =B16 -> 4-days-trip-from-dubai | K16: <a target="_blank" href="dubai.php?search= | L16: =PROPER(F16) -> 4-Days-Trip-From-Dubai | M16: "> | N16: =PROPER(CONCATENATE(F16," ",G16," ",H16," ",I16," ",J16)) -> 4-Days-Trip-From-Dubai | O16: </a> <br /> | P16: =CONCATENATE(K16,L16,M16,N16,O16) -> <a target="_blank" href="dubai.php?search=4-Days-Trip-From-Dubai">4-Days-Trip-From-Dubai </a> <br />
... A1053: yellow boats dubai marina | B1053: yellow-boats-dubai-marina | F1053: =B1053 -> yellow-boats-dubai-marina | K1053: <a target="_blank" href="dubai.php?search= | L1053: =PROPER(F1053) -> Yellow-Boats-Dubai-Marina | M1053: "> | N1053: =PROPER(CONCATENATE(F1053," ",G1053," ",H1053," ",I1053," ",J1053)) -> Yellow-Boats-Dubai-Marina | O1053: </a> <br /> | P1053: =CONCATENATE(K1053,L1053,M1053,N1053,O1053) -> <a target="_blank" href="dubai.php?search=Yellow-Boats-Dubai-Marina">Yellow-Boats-Dubai-Marina </a> <br />

Sheet MOLE removal arabic
N1: blank
N2: - | O2: =LEN(N2) -> 1
F3: Keywords
A4: body | B4: جسم | C4: =SUBSTITUTE(B4,"-"," ") -> جسم | F4: =B4 -> جسم | K4: <a target="_blank" href="dubai.php?search= | L4: =PROPER(F4) -> جسم | M4: "> | N4: =C4 -> جسم | O4: </a> <br /> | P4: =CONCATENATE(K4,L4,M4,N4,O4) -> <a target="_blank" href="dubai.php?search=جسم">جسم</a> <br />
A5: skin | B5: جلد | F5: =B5 -> جلد | K5: <a target="_blank" href="dubai.php?search= | L5: =PROPER(F5) -> جلد | M5: "> | N5: =PROPER(CONCATENATE(F5," ",G5," ",H5," ",I5," ",J5)) -> جلد | O5: </a> <br /> | P5: =CONCATENATE(K5,L5,M5,N5,O5) -> <a target="_blank" href="dubai.php?search=جلد">جلد </a> <br />
A6: head | B6: رأس | F6: =B6 -> رأس | K6: <a target="_blank" href="dubai.php?search= | L6: =PROPER(F6) -> رأس | M6: "> | N6: =PROPER(CONCATENATE(F6," ",G6," ",H6," ",I6," ",J6)) -> رأس | O6: </a> <br /> | P6: =CONCATENATE(K6,L6,M6,N6,O6) -> <a target="_blank" href="dubai.php?search=رأس">رأس </a> <br />
A7: hair | B7: شَعر | F7: =B7 -> شَعر | K7: <a target="_blank" href="dubai.php?search= | L7: =PROPER(F7) -> شَعر | M7: "> | N7: =PROPER(CONCATENATE(F7," ",G7," ",H7," ",I7," ",J7)) -> شَعر | O7: </a> <br /> | P7: =CONCATENATE(K7,L7,M7,N7,O7) -> <a target="_blank" href="dubai.php?search=شَعر">شَعر </a> <br />
A8: face | B8: وجه | F8: =B8 -> وجه | K8: <a target="_blank" href="dubai.php?search= | L8: =PROPER(F8) -> وجه | M8: "> | N8: =PROPER(CONCATENATE(F8," ",G8," ",H8," ",I8," ",J8)) -> وجه | O8: </a> <br /> | P8: =CONCATENATE(K8,L8,M8,N8,O8) -> <a target="_blank" href="dubai.php?search=وجه">وجه </a> <br />
A9: forehead | B9: جبين | F9: =B9 -> جبين | K9: <a target="_blank" href="dubai.php?search= | L9: =PROPER(F9) -> جبين | M9: "> | N9: =PROPER(CONCATENATE(F9," ",G9," ",H9," ",I9," ",J9)) -> جبين | O9: </a> <br /> | P9: =CONCATENATE(K9,L9,M9,N9,O9) -> <a target="_blank" href="dubai.php?search=جبين">جبين </a> <br />
A10: temple | B10: صدغ | F10: =B10 -> صدغ | K10: <a target="_blank" href="dubai.php?search= | L10: =PROPER(F10) -> صدغ | M10: "> | N10: =PROPER(CONCATENATE(F10," ",G10," ",H10," ",I10," ",J10)) -> صدغ | O10: </a> <br /> | P10: =CONCATENATE(K10,L10,M10,N10,O10) -> <a target="_blank" href="dubai.php?search=صدغ">صدغ </a> <br />
A11: cheek | B11: خد | F11: =B11 -> خد | K11: <a target="_blank" href="dubai.php?search= | L11: =PROPER(F11) -> خد | M11: "> | N11: =PROPER(CONCATENATE(F11," ",G11," ",H11," ",I11," ",J11)) -> خد | O11: </a> <br /> | P11: =CONCATENATE(K11,L11,M11,N11,O11) -> <a target="_blank" href="dubai.php?search=خد">خد </a> <br />
A12: eyebrow | B12: حاجب | F12: =B12 -> حاجب | K12: <a target="_blank" href="dubai.php?search= | L12: =PROPER(F12) -> حاجب | M12: "> | N12: =PROPER(CONCATENATE(F12," ",G12," ",H12," ",I12," ",J12)) -> حاجب | O12: </a> <br /> | P12: =CONCATENATE(K12,L12,M12,N12,O12) -> <a target="_blank" href="dubai.php?search=حاجب">حاجب </a> <br />
A13: ear | B13: اذن | F13: =B13 -> اذن | K13: <a target="_blank" href="dubai.php?search= | L13: =PROPER(F13) -> اذن | M13: "> | N13: =PROPER(CONCATENATE(F13," ",G13," ",H13," ",I13," ",J13)) -> اذن | O13: </a> <br /> | P13: =CONCATENATE(K13,L13,M13,N13,O13) -> <a target="_blank" href="dubai.php?search=اذن">اذن </a> <br />
A14: nose | B14: أنف | F14: =B14 -> أنف | K14: <a target="_blank" href="dubai.php?search= | L14: =PROPER(F14) -> أنف | M14: "> | N14: =PROPER(CONCATENATE(F14," ",G14," ",H14," ",I14," ",J14)) -> أنف | O14: </a> <br /> | P14: =CONCATENATE(K14,L14,M14,N14,O14) -> <a target="_blank" href="dubai.php?search=أنف">أنف </a> <br />
A15: upper | B15: علوي | F15: =B15 -> علوي | K15: <a target="_blank" href="dubai.php?search= | L15: =PROPER(F15) -> علوي | M15: "> | N15: =PROPER(CONCATENATE(F15," ",G15," ",H15," ",I15," ",J15)) -> علوي | O15: </a> <br /> | P15: =CONCATENATE(K15,L15,M15,N15,O15) -> <a target="_blank" href="dubai.php?search=علوي">علوي </a> <br />
A16: lip | B16: شفة | F16: =B16 -> شفة | K16: <a target="_blank" href="dubai.php?search= | L16: =PROPER(F16) -> شفة | M16: "> | N16: =PROPER(CONCATENATE(F16," ",G16," ",H16," ",I16," ",J16)) -> شفة | O16: </a> <br /> | P16: =CONCATENATE(K16,L16,M16,N16,O16) -> <a target="_blank" href="dubai.php?search=شفة">شفة </a> <br />
... A33: Knee | B33: ركبة | F33: =B33 -> ركبة | K33: <a target="_blank" href="dubai.php?search= | L33: =PROPER(F33) -> ركبة | M33: "> | N33: =PROPER(CONCATENATE(F33," ",G33," ",H33," ",I33," ",J33)) -> ركبة | O33: </a> <br /> | P33: =CONCATENATE(K33,L33,M33,N33,O33) -> <a target="_blank" href="dubai.php?search=ركبة">ركبة </a> <br />
F34: =B34 -> 0 | K34: <a target="_blank" href="dubai.php?search= | L34: =PROPER(F34) -> 0 | M34: "> | N34: =PROPER(CONCATENATE(F34," ",G34," ",H34," ",I34," ",J34)) -> 0 | O34: </a> <br /> | P34: =CONCATENATE(K34,L34,M34,N34,O34) -> <a target="_blank" href="dubai.php?search=0">0 </a> <br />
F35: =B35 -> 0 | K35: <a target="_blank" href="dubai.php?search= | L35: =PROPER(F35) -> 0 | M35: "> | N35: =PROPER(CONCATENATE(F35," ",G35," ",H35," ",I35," ",J35)) -> 0 | O35: </a> <br /> | P35: =CONCATENATE(K35,L35,M35,N35,O35) -> <a target="_blank" href="dubai.php?search=0">0 </a> <br />
F36: =B36 -> 0 | K36: <a target="_blank" href="dubai.php?search= | L36: =PROPER(F36) -> 0 | M36: "> | N36: =PROPER(CONCATENATE(F36," ",G36," ",H36," ",I36," ",J36)) -> 0 | O36: </a> <br /> | P36: =CONCATENATE(K36,L36,M36,N36,O36) -> <a target="_blank" href="dubai.php?search=0">0 </a> <br />
A37: 44079 | F37: =B37 -> 0 | K37: <a target="_blank" href="dubai.php?search= | L37: =PROPER(F37) -> 0 | M37: "> | N37: =PROPER(CONCATENATE(F37," ",G37," ",H37," ",I37," ",J37)) -> 0 | O37: </a> <br /> | P37: =CONCATENATE(K37,L37,M37,N37,O37) -> <a target="_blank" href="dubai.php?search=0">0 </a> <br />
A38: 44191 | F38: =B38 -> 0 | K38: <a target="_blank" href="dubai.php?search= | L38: =PROPER(F38) -> 0 | M38: "> | N38: =PROPER(CONCATENATE(F38," ",G38," ",H38," ",I38," ",J38)) -> 0 | O38: </a> <br /> | P38: =CONCATENATE(K38,L38,M38,N38,O38) -> <a target="_blank" href="dubai.php?search=0">0 </a> <br />
A39: 44073 | F39: =B39 -> 0 | K39: <a target="_blank" href="dubai.php?search= | L39: =PROPER(F39) -> 0 | M39: "> | N39: =PROPER(CONCATENATE(F39," ",G39," ",H39," ",I39," ",J39)) -> 0 | O39: </a> <br /> | P39: =CONCATENATE(K39,L39,M39,N39,O39) -> <a target="_blank" href="dubai.php?search=0">0 </a> <br />
A40: 44074 | F40: =B40 -> 0 | K40: <a target="_blank" href="dubai.php?search= | L40: =PROPER(F40) -> 0 | M40: "> | N40: =PROPER(CONCATENATE(F40," ",G40," ",H40," ",I40," ",J40)) -> 0 | O40: </a> <br /> | P40: =CONCATENATE(K40,L40,M40,N40,O40) -> <a target="_blank" href="dubai.php?search=0">0 </a> <br />
F41: =B41 -> 0 | K41: <a target="_blank" href="dubai.php?search= | L41: =PROPER(F41) -> 0 | M41: "> | N41: =PROPER(CONCATENATE(F41," ",G41," ",H41," ",I41," ",J41)) -> 0 | O41: </a> <br /> | P41: =CONCATENATE(K41,L41,M41,N41,O41) -> <a target="_blank" href="dubai.php?search=0">0 </a> <br />
F42: =B42 -> 0 | K42: <a target="_blank" href="dubai.php?search= | L42: =PROPER(F42) -> 0 | M42: "> | N42: =PROPER(CONCATENATE(F42," ",G42," ",H42," ",I42," ",J42)) -> 0 | O42: </a> <br /> | P42: =CONCATENATE(K42,L42,M42,N42,O42) -> <a target="_blank" href="dubai.php?search=0">0 </a> <br />
F43: =B43 -> 0 | K43: <a target="_blank" href="dubai.php?search= | L43: =PROPER(F43) -> 0 | M43: "> | N43: =PROPER(CONCATENATE(F43," ",G43," ",H43," ",I43," ",J43)) -> 0 | O43: </a> <br /> | P43: =CONCATENATE(K43,L43,M43,N43,O43) -> <a target="_blank" href="dubai.php?search=0">0 </a> <br />
F44: =B44 -> 0 | K44: <a target="_blank" href="dubai.php?search= | L44: =PROPER(F44) -> 0 | M44: "> | N44: =PROPER(CONCATENATE(F44," ",G44," ",H44," ",I44," ",J44)) -> 0 | O44: </a> <br /> | P44: =CONCATENATE(K44,L44,M44,N44,O44) -> <a target="_blank" href="dubai.php?search=0">0 </a> <br />
F45: =B45 -> 0 | K45: <a target="_blank" href="dubai.php?search= | L45: =PROPER(F45) -> 0 | M45: "> | N45: =PROPER(CONCATENATE(F45," ",G45," ",H45," ",I45," ",J45)) -> 0 | O45: </a> <br /> | P45: =CONCATENATE(K45,L45,M45,N45,O45) -> <a target="_blank" href="dubai.php?search=0">0 </a> <br />
F46: =B46 -> 0 | K46: <a target="_blank" href="dubai.php?search= | L46: =PROPER(F46) -> 0 | M46: "> | N46: =PROPER(CONCATENATE(F46," ",G46," ",H46," ",I46," ",J46)) -> 0 | O46: </a> <br /> | P46: =CONCATENATE(K46,L46,M46,N46,O46) -> <a target="_blank" href="dubai.php?search=0">0 </a> <br />
F47: =B47 -> 0 | K47: <a target="_blank" href="dubai.php?search= | L47: =PROPER(F47) -> 0 | M47: "> | N47: =PROPER(CONCATENATE(F47," ",G47," ",H47," ",I47," ",J47)) -> 0 | O47: </a> <br /> | P47: =CONCATENATE(K47,L47,M47,N47,O47) -> <a target="_blank" href="dubai.php?search=0">0 </a> <br />
F48: =B48 -> 0 | K48: <a target="_blank" href="dubai.php?search= | L48: =PROPER(F48) -> 0 | M48: "> | N48: =PROPER(CONCATENATE(F48," ",G48," ",H48," ",I48," ",J48)) -> 0 | O48: </a> <br /> | P48: =CONCATENATE(K48,L48,M48,N48,O48) -> <a target="_blank" href="dubai.php?search=0">0 </a> <br />
F49: =B49 -> 0 | K49: <a target="_blank" href="dubai.php?search= | L49: =PROPER(F49) -> 0 | M49: "> | N49: =PROPER(CONCATENATE(F49," ",G49," ",H49," ",I49," ",J49)) -> 0 | O49: </a> <br /> | P49: =CONCATENATE(K49,L49,M49,N49,O49) -> <a target="_blank" href="dubai.php?search=0">0 </a> <br />
F50: =B50 -> 0 | K50: <a target="_blank" href="dubai.php?search= | L50: =PROPER(F50) -> 0 | M50: "> | N50: =PROPER(CONCATENATE(F50," ",G50," ",H50," ",I50," ",J50)) -> 0 | O50: </a> <br /> | P50: =CONCATENATE(K50,L50,M50,N50,O50) -> <a target="_blank" href="dubai.php?search=0">0 </a> <br />
F51: =B51 -> 0 | K51: <a target="_blank" href="dubai.php?search= | L51: =PROPER(F51) -> 0 | M51: "> | N51: =PROPER(CONCATENATE(F51," ",G51," ",H51," ",I51," ",J51)) -> 0 | O51: </a> <br /> | P51: =CONCATENATE(K51,L51,M51,N51,O51) -> <a target="_blank" href="dubai.php?search=0">0 </a> <br />
F52: =B52 -> 0 | K52: <a target="_blank" href="dubai.php?search= | L52: =PROPER(F52) -> 0 | M52: "> | N52: =PROPER(CONCATENATE(F52," ",G52," ",H52," ",I52," ",J52)) -> 0 | O52: </a> <br /> | P52: =CONCATENATE(K52,L52,M52,N52,O52) -> <a target="_blank" href="dubai.php?search=0">0 </a> <br />
... F1053: =B1053 -> 0 | K1053: <a target="_blank" href="dubai.php?search= | L1053: =PROPER(F1053) -> 0 | M1053: "> | N1053: =PROPER(CONCATENATE(F1053," ",G1053," ",H1053," ",I1053," ",J1053)) -> 0 | O1053: </a> <br /> | P1053: =CONCATENATE(K1053,L1053,M1053,N1053,O1053) -> <a target="_blank" href="dubai.php?search=0">0 </a> <br />

Sheet Botox
N1: blank
N2: - | O2: =LEN(N2) -> 1
A4: ='Laser Price'!E5 -> 160 | B4: AED | D4: =CONCATENATE($O$1,B4,$O$1,A4) -> AED 160 | F4: Botulinum | G4: Toxin | H4: Injections | I4: For | J4: Abdomen | K4: <a target="_blank" href="botox.php?botox= | L4: =CONCATENATE(F4,$N$2,G4,$N$2,H4,$N$2,I4,$N$2,J4) -> Botulinum-Toxin-Injections-For-Abdomen | M4: "> | N4: =PROPER(CONCATENATE(F4," ",G4," ",H4," ",I4," ",J4)) -> Botulinum Toxin Injections For Abdomen | O4: </a> <br /> | P4: =CONCATENATE(K4,L4,M4,N4,O4) -> <a target="_blank" href="botox.php?botox=Botulinum-Toxin-Injections-For-Abdomen">Botulinum Toxin Injections For Abdomen</a> <br />
A5: ='Laser Price'!E6 -> 160 | B5: AED | D5: =CONCATENATE($O$1,B5,$O$1,A5) -> AED 160 | F5: Botulinum | G5: Toxin | H5: Injections | I5: For | J5: Areola | K5: <a target="_blank" href="botox.php?botox= | L5: =CONCATENATE(F5,$N$2,G5,$N$2,H5,$N$2,I5,$N$2,J5) -> Botulinum-Toxin-Injections-For-Areola | M5: "> | N5: =PROPER(CONCATENATE(F5," ",G5," ",H5," ",I5," ",J5)) -> Botulinum Toxin Injections For Areola | O5: </a> <br /> | P5: =CONCATENATE(K5,L5,M5,N5,O5) -> <a target="_blank" href="botox.php?botox=Botulinum-Toxin-Injections-For-Areola">Botulinum Toxin Injections For Areola</a> <br />
A6: ='Laser Price'!E7 -> 320 | B6: AED | D6: =CONCATENATE($O$1,B6,$O$1,A6) -> AED 320 | F6: Botulinum | G6: Toxin | H6: Injections | I6: For | J6: Arm | K6: <a target="_blank" href="botox.php?botox= | L6: =CONCATENATE(F6,$N$2,G6,$N$2,H6,$N$2,I6,$N$2,J6) -> Botulinum-Toxin-Injections-For-Arm | M6: "> | N6: =PROPER(CONCATENATE(F6," ",G6," ",H6," ",I6," ",J6)) -> Botulinum Toxin Injections For Arm | O6: </a> <br /> | P6: =CONCATENATE(K6,L6,M6,N6,O6) -> <a target="_blank" href="botox.php?botox=Botulinum-Toxin-Injections-For-Arm">Botulinum Toxin Injections For Arm</a> <br />
A7: ='Laser Price'!E8 -> 200 | B7: AED | D7: =CONCATENATE($O$1,B7,$O$1,A7) -> AED 200 | F7: Botulinum | G7: Toxin | H7: Injections | I7: For | J7: Armpit | K7: <a target="_blank" href="botox.php?botox= | L7: =CONCATENATE(F7,$N$2,G7,$N$2,H7,$N$2,I7,$N$2,J7) -> Botulinum-Toxin-Injections-For-Armpit | M7: "> | N7: =PROPER(CONCATENATE(F7," ",G7," ",H7," ",I7," ",J7)) -> Botulinum Toxin Injections For Armpit | O7: </a> <br /> | P7: =CONCATENATE(K7,L7,M7,N7,O7) -> <a target="_blank" href="botox.php?botox=Botulinum-Toxin-Injections-For-Armpit">Botulinum Toxin Injections For Armpit</a> <br />
A8: ='Laser Price'!E9 -> 400 | B8: AED | D8: =CONCATENATE($O$1,B8,$O$1,A8) -> AED 400 | F8: Botulinum | G8: Toxin | H8: Injections | I8: For | J8: Back | K8: <a target="_blank" href="botox.php?botox= | L8: =CONCATENATE(F8,$N$2,G8,$N$2,H8,$N$2,I8,$N$2,J8) -> Botulinum-Toxin-Injections-For-Back | M8: "> | N8: =PROPER(CONCATENATE(F8," ",G8," ",H8," ",I8," ",J8)) -> Botulinum Toxin Injections For Back | O8: </a> <br /> | P8: =CONCATENATE(K8,L8,M8,N8,O8) -> <a target="_blank" href="botox.php?botox=Botulinum-Toxin-Injections-For-Back">Botulinum Toxin Injections For Back</a> <br />
A9: ='Laser Price'!E10 -> 128 | B9: AED | D9: =CONCATENATE($O$1,B9,$O$1,A9) -> AED 128 | F9: Botulinum | G9: Toxin | H9: Injections | I9: For | J9: Back-Neck | K9: <a target="_blank" href="botox.php?botox= | L9: =CONCATENATE(F9,$N$2,G9,$N$2,H9,$N$2,I9,$N$2,J9) -> Botulinum-Toxin-Injections-For-Back-Neck | M9: "> | N9: =PROPER(CONCATENATE(F9," ",G9," ",H9," ",I9," ",J9)) -> Botulinum Toxin Injections For Back-Neck | O9: </a> <br /> | P9: =CONCATENATE(K9,L9,M9,N9,O9) -> <a target="_blank" href="botox.php?botox=Botulinum-Toxin-Injections-For-Back-Neck">Botulinum Toxin Injections For Back-Neck</a> <br />
A10: ='Laser Price'!E11 -> 160 | B10: AED | D10: =CONCATENATE($O$1,B10,$O$1,A10) -> AED 160 | F10: Botulinum | G10: Toxin | H10: Injections | I10: For | J10: Skin | K10: <a target="_blank" href="botox.php?botox= | L10: =CONCATENATE(F10,$N$2,G10,$N$2,H10,$N$2,I10,$N$2,J10) -> Botulinum-Toxin-Injections-For-Skin | M10: "> | N10: =PROPER(CONCATENATE(F10," ",G10," ",H10," ",I10," ",J10)) -> Botulinum Toxin Injections For Skin | O10: </a> <br /> | P10: =CONCATENATE(K10,L10,M10,N10,O10) -> <a target="_blank" href="botox.php?botox=Botulinum-Toxin-Injections-For-Skin">Botulinum Toxin Injections For Skin</a> <br />
A11: ='Laser Price'!E12 -> 80 | B11: AED | D11: =CONCATENATE($O$1,B11,$O$1,A11) -> AED 80 | F11: Botulinum | G11: Toxin | H11: Injections | I11: For | J11: Jawline | K11: <a target="_blank" href="botox.php?botox= | L11: =CONCATENATE(F11,$N$2,G11,$N$2,H11,$N$2,I11,$N$2,J11) -> Botulinum-Toxin-Injections-For-Jawline | M11: "> | N11: =PROPER(CONCATENATE(F11," ",G11," ",H11," ",I11," ",J11)) -> Botulinum Toxin Injections For Jawline | O11: </a> <br /> | P11: =CONCATENATE(K11,L11,M11,N11,O11) -> <a target="_blank" href="botox.php?botox=Botulinum-Toxin-Injections-For-Jawline">Botulinum Toxin Injections For Jawline</a> <br />
A12: ='Laser Price'!E16 -> 400 | B12: AED | D12: =CONCATENATE($O$1,B12,$O$1,A12) -> AED 400 | F12: Botulinum | G12: Toxin | H12: Injections | I12: For | J12: Breast | K12: <a target="_blank" href="botox.php?botox= | L12: =CONCATENATE(F12,$N$2,G12,$N$2,H12,$N$2,I12,$N$2,J12) -> Botulinum-Toxin-Injections-For-Breast | M12: "> | N12: =PROPER(CONCATENATE(F12," ",G12," ",H12," ",I12," ",J12)) -> Botulinum Toxin Injections For Breast | O12: </a> <br /> | P12: =CONCATENATE(K12,L12,M12,N12,O12) -> <a target="_blank" href="botox.php?botox=Botulinum-Toxin-Injections-For-Breast">Botulinum Toxin Injections For Breast</a> <br />
A13: ='Laser Price'!E17 -> 400 | B13: AED | D13: =CONCATENATE($O$1,B13,$O$1,A13) -> AED 400 | F13: Botulinum | G13: Toxin | H13: Injections | I13: For | J13: Buttock | K13: <a target="_blank" href="botox.php?botox= | L13: =CONCATENATE(F13,$N$2,G13,$N$2,H13,$N$2,I13,$N$2,J13) -> Botulinum-Toxin-Injections-For-Buttock | M13: "> | N13: =PROPER(CONCATENATE(F13," ",G13," ",H13," ",I13," ",J13)) -> Botulinum Toxin Injections For Buttock | O13: </a> <br /> | P13: =CONCATENATE(K13,L13,M13,N13,O13) -> <a target="_blank" href="botox.php?botox=Botulinum-Toxin-Injections-For-Buttock">Botulinum Toxin Injections For Buttock</a> <br />
A14: ='Laser Price'!E18 -> 120 | B14: AED | D14: =CONCATENATE($O$1,B14,$O$1,A14) -> AED 120 | F14: Botulinum | G14: Toxin | H14: Injections | I14: For | J14: Cheek | K14: <a target="_blank" href="botox.php?botox= | L14: =CONCATENATE(F14,$N$2,G14,$N$2,H14,$N$2,I14,$N$2,J14) -> Botulinum-Toxin-Injections-For-Cheek | M14: "> | N14: =PROPER(CONCATENATE(F14," ",G14," ",H14," ",I14," ",J14)) -> Botulinum Toxin Injections For Cheek | O14: </a> <br /> | P14: =CONCATENATE(K14,L14,M14,N14,O14) -> <a target="_blank" href="botox.php?botox=Botulinum-Toxin-Injections-For-Cheek">Botulinum Toxin Injections For Cheek</a> <br />
A15: ='Laser Price'!E19 -> 400 | B15: AED | D15: =CONCATENATE($O$1,B15,$O$1,A15) -> AED 400 | F15: Botulinum | G15: Toxin | H15: Injections | I15: For | J15: Chest | K15: <a target="_blank" href="botox.php?botox= | L15: =CONCATENATE(F15,$N$2,G15,$N$2,H15,$N$2,I15,$N$2,J15) -> Botulinum-Toxin-Injections-For-Chest | M15: "> | N15: =PROPER(CONCATENATE(F15," ",G15," ",H15," ",I15," ",J15)) -> Botulinum Toxin Injections For Chest | O15: </a> <br /> | P15: =CONCATENATE(K15,L15,M15,N15,O15) -> <a target="_blank" href="botox.php?botox=Botulinum-Toxin-Injections-For-Chest">Botulinum Toxin Injections For Chest</a> <br />
A16: ='Laser Price'!E20 -> 40 | B16: AED | D16: =CONCATENATE($O$1,B16,$O$1,A16) -> AED 40 | F16: Botulinum | G16: Toxin | H16: Injections | I16: For | J16: Chin | K16: <a target="_blank" href="botox.php?botox= | L16: =CONCATENATE(F16,$N$2,G16,$N$2,H16,$N$2,I16,$N$2,J16) -> Botulinum-Toxin-Injections-For-Chin | M16: "> | N16: =PROPER(CONCATENATE(F16," ",G16," ",H16," ",I16," ",J16)) -> Botulinum Toxin Injections For Chin | O16: </a> <br /> | P16: =CONCATENATE(K16,L16,M16,N16,O16) -> <a target="_blank" href="botox.php?botox=Botulinum-Toxin-Injections-For-Chin">Botulinum Toxin Injections For Chin</a> <br />
A17: ='Laser Price'!E21 -> 40 | B17: AED | D17: =CONCATENATE($O$1,B17,$O$1,A17) -> AED 40 | F17: Botulinum | G17: Toxin | H17: Injections | I17: For | J17: Ear | K17: <a target="_blank" href="botox.php?botox= | L17: =CONCATENATE(F17,$N$2,G17,$N$2,H17,$N$2,I17,$N$2,J17) -> Botulinum-Toxin-Injections-For-Ear | M17: "> | N17: =PROPER(CONCATENATE(F17," ",G17," ",H17," ",I17," ",J17)) -> Botulinum Toxin Injections For Ear | O17: </a> <br /> | P17: =CONCATENATE(K17,L17,M17,N17,O17) -> <a target="_blank" href="botox.php?botox=Botulinum-Toxin-Injections-For-Ear">Botulinum Toxin Injections For Ear</a> <br />
A18: ='Laser Price'!E22 -> 160 | B18: AED | D18: =CONCATENATE($O$1,B18,$O$1,A18) -> AED 160 | F18: Botulinum | G18: Toxin | H18: Injections | I18: For | J18: Mouth | K18: <a target="_blank" href="botox.php?botox= | L18: =CONCATENATE(F18,$N$2,G18,$N$2,H18,$N$2,I18,$N$2,J18) -> Botulinum-Toxin-Injections-For-Mouth | M18: "> | N18: =PROPER(CONCATENATE(F18," ",G18," ",H18," ",I18," ",J18)) -> Botulinum Toxin Injections For Mouth | O18: </a> <br /> | P18: =CONCATENATE(K18,L18,M18,N18,O18) -> <a target="_blank" href="botox.php?botox=Botulinum-Toxin-Injections-For-Mouth">Botulinum Toxin Injections For Mouth</a> <br />
A19: ='Laser Price'!E23 -> 120 | B19: AED | D19: =CONCATENATE($O$1,B19,$O$1,A19) -> AED 120 | F19: Botulinum | G19: Toxin | H19: Injections | I19: For | J19: Eyebrow | K19: <a target="_blank" href="botox.php?botox= | L19: =CONCATENATE(F19,$N$2,G19,$N$2,H19,$N$2,I19,$N$2,J19) -> Botulinum-Toxin-Injections-For-Eyebrow | M19: "> | N19: =PROPER(CONCATENATE(F19," ",G19," ",H19," ",I19," ",J19)) -> Botulinum Toxin Injections For Eyebrow | O19: </a> <br /> | P19: =CONCATENATE(K19,L19,M19,N19,O19) -> <a target="_blank" href="botox.php?botox=Botulinum-Toxin-Injections-For-Eyebrow">Botulinum Toxin Injections For Eyebrow</a> <br />
A20: ='Laser Price'!E24 -> 80 | B20: AED | D20: =CONCATENATE($O$1,B20,$O$1,A20) -> AED 80 | F20: Botulinum | G20: Toxin | H20: Injections | I20: For | J20: Face | K20: <a target="_blank" href="botox.php?botox= | L20: =CONCATENATE(F20,$N$2,G20,$N$2,H20,$N$2,I20,$N$2,J20) -> Botulinum-Toxin-Injections-For-Face | M20: "> | N20: =PROPER(CONCATENATE(F20," ",G20," ",H20," ",I20," ",J20)) -> Botulinum Toxin Injections For Face | O20: </a> <br /> | P20: =CONCATENATE(K20,L20,M20,N20,O20) -> <a target="_blank" href="botox.php?botox=Botulinum-Toxin-Injections-For-Face">Botulinum Toxin Injections For Face</a> <br />
A21: ='Laser Price'!E25 -> 80 | B21: AED | D21: =CONCATENATE($O$1,B21,$O$1,A21) -> AED 80 | F21: Botulinum | G21: Toxin | H21: Injections | I21: For | J21: Feet | K21: <a target="_blank" href="botox.php?botox= | L21: =CONCATENATE(F21,$N$2,G21,$N$2,H21,$N$2,I21,$N$2,J21) -> Botulinum-Toxin-Injections-For-Feet | M21: "> | N21: =PROPER(CONCATENATE(F21," ",G21," ",H21," ",I21," ",J21)) -> Botulinum Toxin Injections For Feet | O21: </a> <br /> | P21: =CONCATENATE(K21,L21,M21,N21,O21) -> <a target="_blank" href="botox.php?botox=Botulinum-Toxin-Injections-For-Feet">Botulinum Toxin Injections For Feet</a> <br />
A22: ='Laser Price'!E26 -> 200 | B22: AED | D22: =CONCATENATE($O$1,B22,$O$1,A22) -> AED 200 | F22: Botulinum | G22: Toxin | H22: Injections | I22: For | J22: Wrinkles | K22: <a target="_blank" href="botox.php?botox= | L22: =CONCATENATE(F22,$N$2,G22,$N$2,H22,$N$2,I22,$N$2,J22) -> Botulinum-Toxin-Injections-For-Wrinkles | M22: "> | N22: =PROPER(CONCATENATE(F22," ",G22," ",H22," ",I22," ",J22)) -> Botulinum Toxin Injections For Wrinkles | O22: </a> <br /> | P22: =CONCATENATE(K22,L22,M22,N22,O22) -> <a target="_blank" href="botox.php?botox=Botulinum-Toxin-Injections-For-Wrinkles">Botulinum Toxin Injections For Wrinkles</a> <br />
A23: ='Laser Price'!E27 -> 120 | B23: AED | D23: =CONCATENATE($O$1,B23,$O$1,A23) -> AED 120 | F23: Botulinum | G23: Toxin | H23: Injections | I23: For | J23: Forehead | K23: <a target="_blank" href="botox.php?botox= | L23: =CONCATENATE(F23,$N$2,G23,$N$2,H23,$N$2,I23,$N$2,J23) -> Botulinum-Toxin-Injections-For-Forehead | M23: "> | N23: =PROPER(CONCATENATE(F23," ",G23," ",H23," ",I23," ",J23)) -> Botulinum Toxin Injections For Forehead | O23: </a> <br /> | P23: =CONCATENATE(K23,L23,M23,N23,O23) -> <a target="_blank" href="botox.php?botox=Botulinum-Toxin-Injections-For-Forehead">Botulinum Toxin Injections For Forehead</a> <br />
... A48: ='Laser Price'!E52 -> 240 | B48: AED | D48: =CONCATENATE($O$1,B48,$O$1,A48) -> AED 240 | F48: Botulinum | G48: Toxin | H48: Injections | I48: For | J48: Upper-Back | K48: <a target="_blank" href="botox.php?botox= | L48: =CONCATENATE(F48,$N$2,G48,$N$2,H48,$N$2,I48,$N$2,J48) -> Botulinum-Toxin-Injections-For-Upper-Back | M48: "> | N48: =PROPER(CONCATENATE(F48," ",G48," ",H48," ",I48," ",J48)) -> Botulinum Toxin Injections For Upper-Back | O48: </a> <br /> | P48: =CONCATENATE(K48,L48,M48,N48,O48) -> <a target="_blank" href="botox.php?botox=Botulinum-Toxin-Injections-For-Upper-Back">Botulinum Toxin Injections For Upper-Back</a> <br />
A49: ='Laser Price'!E54 -> 40 | B49: AED | D49: =CONCATENATE($O$1,B49,$O$1,A49) -> AED 40 | F49: Botulinum | G49: Toxin | H49: Injections | I49: For | J49: Upper-Lip | K49: <a target="_blank" href="botox.php?botox= | L49: =CONCATENATE(F49,$N$2,G49,$N$2,H49,$N$2,I49,$N$2,J49) -> Botulinum-Toxin-Injections-For-Upper-Lip | M49: "> | N49: =PROPER(CONCATENATE(F49," ",G49," ",H49," ",I49," ",J49)) -> Botulinum Toxin Injections For Upper-Lip | O49: </a> <br /> | P49: =CONCATENATE(K49,L49,M49,N49,O49) -> <a target="_blank" href="botox.php?botox=Botulinum-Toxin-Injections-For-Upper-Lip">Botulinum Toxin Injections For Upper-Lip</a> <br />
A50: 160 | B50: AED | D50: =CONCATENATE($O$1,B50,$O$1,A50) -> AED 160 | E50: botox juvederm | F50: Botulinum | G50: Toxin | H50: Injections | I50: For | J50: Bunny-Lines | K50: <a target="_blank" href="botox.php?botox= | L50: =CONCATENATE(F50,$N$2,G50,$N$2,H50,$N$2,I50,$N$2,J50) -> Botulinum-Toxin-Injections-For-Bunny-Lines | M50: "> | N50: =PROPER(CONCATENATE(F50," ",G50," ",H50," ",I50," ",J50)) -> Botulinum Toxin Injections For Bunny-Lines | O50: </a> <br /> | P50: =CONCATENATE(K50,L50,M50,N50,O50) -> <a target="_blank" href="botox.php?botox=Botulinum-Toxin-Injections-For-Bunny-Lines">Botulinum Toxin Injections For Bunny-Lines</a> <br />
A51: 160 | B51: AED | D51: =CONCATENATE($O$1,B51,$O$1,A51) -> AED 160 | E51: Fillers | F51: Botulinum | G51: Toxin | H51: Injections | I51: For | J51: Migraines | K51: <a target="_blank" href="botox.php?botox= | L51: =CONCATENATE(F51,$N$2,G51,$N$2,H51,$N$2,I51,$N$2,J51) -> Botulinum-Toxin-Injections-For-Migraines | M51: "> | N51: =PROPER(CONCATENATE(F51," ",G51," ",H51," ",I51," ",J51)) -> Botulinum Toxin Injections For Migraines | O51: </a> <br /> | P51: =CONCATENATE(K51,L51,M51,N51,O51) -> <a target="_blank" href="botox.php?botox=Botulinum-Toxin-Injections-For-Migraines">Botulinum Toxin Injections For Migraines</a> <br />
A52: 320 | B52: AED | D52: =CONCATENATE($O$1,B52,$O$1,A52) -> AED 320 | E52: Price | F52: Botulinum | G52: Toxin | H52: Injections | I52: For | J52: Dark-Circles | K52: <a target="_blank" href="botox.php?botox= | L52: =CONCATENATE(F52,$N$2,G52,$N$2,H52,$N$2,I52,$N$2,J52) -> Botulinum-Toxin-Injections-For-Dark-Circles | M52: "> | N52: =PROPER(CONCATENATE(F52," ",G52," ",H52," ",I52," ",J52)) -> Botulinum Toxin Injections For Dark-Circles | O52: </a> <br /> | P52: =CONCATENATE(K52,L52,M52,N52,O52) -> <a target="_blank" href="botox.php?botox=Botulinum-Toxin-Injections-For-Dark-Circles">Botulinum Toxin Injections For Dark-Circles</a> <br />
A53: 200 | B53: AED | D53: =CONCATENATE($O$1,B53,$O$1,A53) -> AED 200 | E53: botox juvederm | F53: Botulinum | G53: Toxin | H53: Injections | I53: For | J53: Sweaty-Hands | K53: <a target="_blank" href="botox.php?botox= | L53: =CONCATENATE(F53,$N$2,G53,$N$2,H53,$N$2,I53,$N$2,J53) -> Botulinum-Toxin-Injections-For-Sweaty-Hands | M53: "> | N53: =PROPER(CONCATENATE(F53," ",G53," ",H53," ",I53," ",J53)) -> Botulinum Toxin Injections For Sweaty-Hands | O53: </a> <br /> | P53: =CONCATENATE(K53,L53,M53,N53,O53) -> <a target="_blank" href="botox.php?botox=Botulinum-Toxin-Injections-For-Sweaty-Hands">Botulinum Toxin Injections For Sweaty-Hands</a> <br />
A54: 400 | B54: AED | D54: =CONCATENATE($O$1,B54,$O$1,A54) -> AED 400 | E54: treatment | F54: Botulinum | G54: Toxin | H54: Injections | I54: For | J54: TMJ | K54: <a target="_blank" href="botox.php?botox= | L54: =CONCATENATE(F54,$N$2,G54,$N$2,H54,$N$2,I54,$N$2,J54) -> Botulinum-Toxin-Injections-For-TMJ | M54: "> | N54: =PROPER(CONCATENATE(F54," ",G54," ",H54," ",I54," ",J54)) -> Botulinum Toxin Injections For Tmj | O54: </a> <br /> | P54: =CONCATENATE(K54,L54,M54,N54,O54) -> <a target="_blank" href="botox.php?botox=Botulinum-Toxin-Injections-For-TMJ">Botulinum Toxin Injections For Tmj</a> <br />
A55: 128 | B55: AED | D55: =CONCATENATE($O$1,B55,$O$1,A55) -> AED 128 | F55: Botulinum | G55: Toxin | H55: Injections | I55: For | J55: Glabellar-Lines | K55: <a target="_blank" href="botox.php?botox= | L55: =CONCATENATE(F55,$N$2,G55,$N$2,H55,$N$2,I55,$N$2,J55) -> Botulinum-Toxin-Injections-For-Glabellar-Lines | M55: "> | N55: =PROPER(CONCATENATE(F55," ",G55," ",H55," ",I55," ",J55)) -> Botulinum Toxin Injections For Glabellar-Lines | O55: </a> <br /> | P55: =CONCATENATE(K55,L55,M55,N55,O55) -> <a target="_blank" href="botox.php?botox=Botulinum-Toxin-Injections-For-Glabellar-Lines">Botulinum Toxin Injections For Glabellar-Lines</a> <br />
A56: 160 | B56: AED | D56: =CONCATENATE($O$1,B56,$O$1,A56) -> AED 160 | F56: Botulinum | G56: Toxin | H56: Injections | I56: For | J56: Scars | K56: <a target="_blank" href="botox.php?botox= | L56: =CONCATENATE(F56,$N$2,G56,$N$2,H56,$N$2,I56,$N$2,J56) -> Botulinum-Toxin-Injections-For-Scars | M56: "> | N56: =PROPER(CONCATENATE(F56," ",G56," ",H56," ",I56," ",J56)) -> Botulinum Toxin Injections For Scars | O56: </a> <br /> | P56: =CONCATENATE(K56,L56,M56,N56,O56) -> <a target="_blank" href="botox.php?botox=Botulinum-Toxin-Injections-For-Scars">Botulinum Toxin Injections For Scars</a> <br />
A57: 120 | B57: AED | D57: =CONCATENATE($O$1,B57,$O$1,A57) -> AED 120 | F57: Botulinum | G57: Toxin | H57: Injections | I57: For | J57: Anti-Aging | K57: <a target="_blank" href="botox.php?botox= | L57: =CONCATENATE(F57,$N$2,G57,$N$2,H57,$N$2,I57,$N$2,J57) -> Botulinum-Toxin-Injections-For-Anti-Aging | M57: "> | N57: =PROPER(CONCATENATE(F57," ",G57," ",H57," ",I57," ",J57)) -> Botulinum Toxin Injections For Anti-Aging | O57: </a> <br /> | P57: =CONCATENATE(K57,L57,M57,N57,O57) -> <a target="_blank" href="botox.php?botox=Botulinum-Toxin-Injections-For-Anti-Aging">Botulinum Toxin Injections For Anti-Aging</a> <br />
A58: 160 | B58: AED | D58: =CONCATENATE($O$1,B58,$O$1,A58) -> AED 160 | F58: Botulinum | G58: Toxin | H58: Injections | I58: For | J58: Acne | K58: <a target="_blank" href="botox.php?botox= | L58: =CONCATENATE(F58,$N$2,G58,$N$2,H58,$N$2,I58,$N$2,J58) -> Botulinum-Toxin-Injections-For-Acne | M58: "> | N58: =PROPER(CONCATENATE(F58," ",G58," ",H58," ",I58," ",J58)) -> Botulinum Toxin Injections For Acne | O58: </a> <br /> | P58: =CONCATENATE(K58,L58,M58,N58,O58) -> <a target="_blank" href="botox.php?botox=Botulinum-Toxin-Injections-For-Acne">Botulinum Toxin Injections For Acne</a> <br />
A59: 160 | B59: AED | D59: =CONCATENATE($O$1,B59,$O$1,A59) -> AED 160 | F59: Botox | G59: juvederm | H59: Injections | I59: For | J59: Abdomen | K59: <a target="_blank" href="botox.php?botox= | L59: =CONCATENATE(F59,$N$2,G59,$N$2,H59,$N$2,I59,$N$2,J59) -> Botox-juvederm-Injections-For-Abdomen | M59: "> | N59: =PROPER(CONCATENATE(F59," ",G59," ",H59," ",I59," ",J59)) -> Botox Juvederm Injections For Abdomen | O59: </a> <br /> | P59: =CONCATENATE(K59,L59,M59,N59,O59) -> <a target="_blank" href="botox.php?botox=Botox-juvederm-Injections-For-Abdomen">Botox Juvederm Injections For Abdomen</a> <br />
A60: 400 | B60: AED | D60: =CONCATENATE($O$1,B60,$O$1,A60) -> AED 400 | F60: Botox | G60: juvederm | H60: Injections | I60: For | J60: Areola | K60: <a target="_blank" href="botox.php?botox= | L60: =CONCATENATE(F60,$N$2,G60,$N$2,H60,$N$2,I60,$N$2,J60) -> Botox-juvederm-Injections-For-Areola | M60: "> | N60: =PROPER(CONCATENATE(F60," ",G60," ",H60," ",I60," ",J60)) -> Botox Juvederm Injections For Areola | O60: </a> <br /> | P60: =CONCATENATE(K60,L60,M60,N60,O60) -> <a target="_blank" href="botox.php?botox=Botox-juvederm-Injections-For-Areola">Botox Juvederm Injections For Areola</a> <br />
A61: 400 | B61: AED | D61: =CONCATENATE($O$1,B61,$O$1,A61) -> AED 400 | F61: Botox | G61: juvederm | H61: Injections | I61: For | J61: Arm | K61: <a target="_blank" href="botox.php?botox= | L61: =CONCATENATE(F61,$N$2,G61,$N$2,H61,$N$2,I61,$N$2,J61) -> Botox-juvederm-Injections-For-Arm | M61: "> | N61: =PROPER(CONCATENATE(F61," ",G61," ",H61," ",I61," ",J61)) -> Botox Juvederm Injections For Arm | O61: </a> <br /> | P61: =CONCATENATE(K61,L61,M61,N61,O61) -> <a target="_blank" href="botox.php?botox=Botox-juvederm-Injections-For-Arm">Botox Juvederm Injections For Arm</a> <br />
A62: 120 | B62: AED | D62: =CONCATENATE($O$1,B62,$O$1,A62) -> AED 120 | F62: Botox | G62: juvederm | H62: Injections | I62: For | J62: Armpit | K62: <a target="_blank" href="botox.php?botox= | L62: =CONCATENATE(F62,$N$2,G62,$N$2,H62,$N$2,I62,$N$2,J62) -> Botox-juvederm-Injections-For-Armpit | M62: "> | N62: =PROPER(CONCATENATE(F62," ",G62," ",H62," ",I62," ",J62)) -> Botox Juvederm Injections For Armpit | O62: </a> <br /> | P62: =CONCATENATE(K62,L62,M62,N62,O62) -> <a target="_blank" href="botox.php?botox=Botox-juvederm-Injections-For-Armpit">Botox Juvederm Injections For Armpit</a> <br />
A63: 400 | B63: AED | D63: =CONCATENATE($O$1,B63,$O$1,A63) -> AED 400 | F63: Botox | G63: juvederm | H63: Injections | I63: For | J63: Back | K63: <a target="_blank" href="botox.php?botox= | L63: =CONCATENATE(F63,$N$2,G63,$N$2,H63,$N$2,I63,$N$2,J63) -> Botox-juvederm-Injections-For-Back | M63: "> | N63: =PROPER(CONCATENATE(F63," ",G63," ",H63," ",I63," ",J63)) -> Botox Juvederm Injections For Back | O63: </a> <br /> | P63: =CONCATENATE(K63,L63,M63,N63,O63) -> <a target="_blank" href="botox.php?botox=Botox-juvederm-Injections-For-Back">Botox Juvederm Injections For Back</a> <br />
A64: 40 | B64: AED | D64: =CONCATENATE($O$1,B64,$O$1,A64) -> AED 40 | F64: Botox | G64: juvederm | H64: Injections | I64: For | J64: Back-Neck | K64: <a target="_blank" href="botox.php?botox= | L64: =CONCATENATE(F64,$N$2,G64,$N$2,H64,$N$2,I64,$N$2,J64) -> Botox-juvederm-Injections-For-Back-Neck | M64: "> | N64: =PROPER(CONCATENATE(F64," ",G64," ",H64," ",I64," ",J64)) -> Botox Juvederm Injections For Back-Neck | O64: </a> <br /> | P64: =CONCATENATE(K64,L64,M64,N64,O64) -> <a target="_blank" href="botox.php?botox=Botox-juvederm-Injections-For-Back-Neck">Botox Juvederm Injections For Back-Neck</a> <br />
A65: 40 | B65: AED | D65: =CONCATENATE($O$1,B65,$O$1,A65) -> AED 40 | F65: Botox | G65: juvederm | H65: Injections | I65: For | J65: Skin | K65: <a target="_blank" href="botox.php?botox= | L65: =CONCATENATE(F65,$N$2,G65,$N$2,H65,$N$2,I65,$N$2,J65) -> Botox-juvederm-Injections-For-Skin | M65: "> | N65: =PROPER(CONCATENATE(F65," ",G65," ",H65," ",I65," ",J65)) -> Botox Juvederm Injections For Skin | O65: </a> <br /> | P65: =CONCATENATE(K65,L65,M65,N65,O65) -> <a target="_blank" href="botox.php?botox=Botox-juvederm-Injections-For-Skin">Botox Juvederm Injections For Skin</a> <br />
A66: 160 | B66: AED | D66: =CONCATENATE($O$1,B66,$O$1,A66) -> AED 160 | F66: Botox | G66: juvederm | H66: Injections | I66: For | J66: Jawline | K66: <a target="_blank" href="botox.php?botox= | L66: =CONCATENATE(F66,$N$2,G66,$N$2,H66,$N$2,I66,$N$2,J66) -> Botox-juvederm-Injections-For-Jawline | M66: "> | N66: =PROPER(CONCATENATE(F66," ",G66," ",H66," ",I66," ",J66)) -> Botox Juvederm Injections For Jawline | O66: </a> <br /> | P66: =CONCATENATE(K66,L66,M66,N66,O66) -> <a target="_blank" href="botox.php?botox=Botox-juvederm-Injections-For-Jawline">Botox Juvederm Injections For Jawline</a> <br />
... A196: 40 | B196: AED | D196: =CONCATENATE($O$1,B196,$O$1,A196) -> AED 40 | F196: Botox | G196: Injections | H196: Treatment | I196: For | J196: Forehead-Lines | K196: <a target="_blank" href="botox.php?botox= | L196: =CONCATENATE(F196,$N$2,G196,$N$2,H196,$N$2,I196,$N$2,J196) -> Botox-Injections-Treatment-For-Forehead-Lines | M196: "> | N196: =PROPER(CONCATENATE(F196," ",G196," ",H196," ",I196," ",J196)) -> Botox Injections Treatment For Forehead-Lines | O196: </a> <br /> | P196: =CONCATENATE(K196,L196,M196,N196,O196) -> <a target="_blank" href="botox.php?botox=Botox-Injections-Treatment-For-Forehead-Lines">Botox Injections Treatment For Forehead-Lines</a> <br />
F197: Botox | G197: Injections | H197: Treatment | I197: For | J197: Crow-Feet | K197: <a target="_blank" href="botox.php?botox= | L197: =CONCATENATE(F197,$N$2,G197,$N$2,H197,$N$2,I197,$N$2,J197) -> Botox-Injections-Treatment-For-Crow-Feet | M197: "> | N197: =PROPER(CONCATENATE(F197," ",G197," ",H197," ",I197," ",J197)) -> Botox Injections Treatment For Crow-Feet | O197: </a> <br /> | P197: =CONCATENATE(K197,L197,M197,N197,O197) -> <a target="_blank" href="botox.php?botox=Botox-Injections-Treatment-For-Crow-Feet">Botox Injections Treatment For Crow-Feet</a> <br />
F198: Botox | G198: Injections | H198: Treatment | I198: For | J198: Half-Face | K198: <a target="_blank" href="botox.php?botox= | L198: =CONCATENATE(F198,$N$2,G198,$N$2,H198,$N$2,I198,$N$2,J198) -> Botox-Injections-Treatment-For-Half-Face | M198: "> | N198: =PROPER(CONCATENATE(F198," ",G198," ",H198," ",I198," ",J198)) -> Botox Injections Treatment For Half-Face | O198: </a> <br /> | P198: =CONCATENATE(K198,L198,M198,N198,O198) -> <a target="_blank" href="botox.php?botox=Botox-Injections-Treatment-For-Half-Face">Botox Injections Treatment For Half-Face</a> <br />
F199: Botox | G199: Injections | H199: Treatment | I199: For | J199: Smile-Lines | K199: <a target="_blank" href="botox.php?botox= | L199: =CONCATENATE(F199,$N$2,G199,$N$2,H199,$N$2,I199,$N$2,J199) -> Botox-Injections-Treatment-For-Smile-Lines | M199: "> | N199: =PROPER(CONCATENATE(F199," ",G199," ",H199," ",I199," ",J199)) -> Botox Injections Treatment For Smile-Lines | O199: </a> <br /> | P199: =CONCATENATE(K199,L199,M199,N199,O199) -> <a target="_blank" href="botox.php?botox=Botox-Injections-Treatment-For-Smile-Lines">Botox Injections Treatment For Smile-Lines</a> <br />
F200: Botox | G200: Injections | H200: Treatment | I200: For | J200: Hands | K200: <a target="_blank" href="botox.php?botox= | L200: =CONCATENATE(F200,$N$2,G200,$N$2,H200,$N$2,I200,$N$2,J200) -> Botox-Injections-Treatment-For-Hands | M200: "> | N200: =PROPER(CONCATENATE(F200," ",G200," ",H200," ",I200," ",J200)) -> Botox Injections Treatment For Hands | O200: </a> <br /> | P200: =CONCATENATE(K200,L200,M200,N200,O200) -> <a target="_blank" href="botox.php?botox=Botox-Injections-Treatment-For-Hands">Botox Injections Treatment For Hands</a> <br />
F201: Botox | G201: Injections | H201: Treatment | I201: For | J201: Hips | K201: <a target="_blank" href="botox.php?botox= | L201: =CONCATENATE(F201,$N$2,G201,$N$2,H201,$N$2,I201,$N$2,J201) -> Botox-Injections-Treatment-For-Hips | M201: "> | N201: =PROPER(CONCATENATE(F201," ",G201," ",H201," ",I201," ",J201)) -> Botox Injections Treatment For Hips | O201: </a> <br /> | P201: =CONCATENATE(K201,L201,M201,N201,O201) -> <a target="_blank" href="botox.php?botox=Botox-Injections-Treatment-For-Hips">Botox Injections Treatment For Hips</a> <br />
F202: Botox | G202: Injections | H202: Treatment | I202: For | J202: Jaw | K202: <a target="_blank" href="botox.php?botox= | L202: =CONCATENATE(F202,$N$2,G202,$N$2,H202,$N$2,I202,$N$2,J202) -> Botox-Injections-Treatment-For-Jaw | M202: "> | N202: =PROPER(CONCATENATE(F202," ",G202," ",H202," ",I202," ",J202)) -> Botox Injections Treatment For Jaw | O202: </a> <br /> | P202: =CONCATENATE(K202,L202,M202,N202,O202) -> <a target="_blank" href="botox.php?botox=Botox-Injections-Treatment-For-Jaw">Botox Injections Treatment For Jaw</a> <br />
F203: Botox | G203: Injections | H203: Treatment | I203: For | J203: Lower-Back | K203: <a target="_blank" href="botox.php?botox= | L203: =CONCATENATE(F203,$N$2,G203,$N$2,H203,$N$2,I203,$N$2,J203) -> Botox-Injections-Treatment-For-Lower-Back | M203: "> | N203: =PROPER(CONCATENATE(F203," ",G203," ",H203," ",I203," ",J203)) -> Botox Injections Treatment For Lower-Back | O203: </a> <br /> | P203: =CONCATENATE(K203,L203,M203,N203,O203) -> <a target="_blank" href="botox.php?botox=Botox-Injections-Treatment-For-Lower-Back">Botox Injections Treatment For Lower-Back</a> <br />
